Workbook
Name ProjName: 'Start Here'!$C$5
Name Address: 'Start Here'!$C$6
Name ProjStart: 'Start Here'!$C$7
Name TargetEnd: 'Start Here'!$C$8
Name TotalBudget: 'Start Here'!$C$9
Name TotalArea: 'Start Here'!$C$10
Name AsOfOverride: 'Start Here'!$C$11
Name Currency: 'Start Here'!$C$14
Name CustomSym: 'Start Here'!$C$15
Name TaxName: 'Start Here'!$C$16
Name VatRate: 'Start Here'!$C$17
Name DefInclTax: 'Start Here'!$C$18
Name AreaUnit: 'Start Here'!$C$19
Name WeekStart: 'Start Here'!$C$20
Name BudgetWarnPct: 'Start Here'!$C$21
Name ContPct: 'Start Here'!$C$24
Name AlertDays: 'Start Here'!$C$25
Name DecideBuf: 'Start Here'!$C$26
Name OrderBuf: 'Start Here'!$C$27
Name OverpayTol: 'Start Here'!$C$28
Name ContAmt: 'Start Here'!$C$31
Name WorkBudget: 'Start Here'!$C$32
Name CurSym: 'Start Here'!$C$33
Name AsOf: 'Start Here'!$C$34
Name TaxWord: 'Start Here'!$C$35
Name BudgetSum: 'Budget'!$C$38
Name CommittedTotal: 'Budget'!$I$38
Name InvoicedTotal: 'Budget'!$J$38
Name PaidTotal: 'Budget'!$K$38
Name ForecastTotal: 'Budget'!$L$38
Name PendingCO: 'Budget'!$L$40
Name IssuesOpenCost: 'Budget'!$L$41
Name RiskTotal: 'Budget'!$L$42
Name ForecastRisk: 'Budget'!$L$43
Name ContUsed: 'Budget'!$L$44
Name WPrice: 'Quotes'!$C$6
Name WTime: 'Quotes'!$D$6
Name WWar: 'Quotes'!$E$6
Name WComp: 'Quotes'!$F$6
Name WGut: 'Quotes'!$G$6
Name QBlockCat: 'Quotes'!$M$9:$M$18
Name QBlockInv: 'Quotes'!$O$9:$O$18
Name Cash30: 'Payments'!$AC$38
Name CashMonths: 'Payments'!$Z$41:$Z$52
Name ForecastEnd: 'Timeline'!$D$4
Name DecisionsWaiting: 'Selections & Orders'!$B$5
Name OrdersDue: 'Selections & Orders'!$E$5
Name OrdersLate: 'Selections & Orders'!$J$5
Name DeliveriesLate: 'Selections & Orders'!$P$5
Name OpenHigh: 'Issues & Punch List'!$B$5
Name OpenIssues: 'Issues & Punch List'!$O$8:$O$207
Name DocsMissing: 'Vault'!$R$6:$R$35
Name AlertCount: 'Engine'!$Y$2
Name OverdueCount: 'Engine'!$Y$3
Name UrgentCount: 'Engine'!$Y$4
Name WeekAlertCount: 'Engine'!$Y$5
Name WeekStartDate: 'This Week'!$C$4
Name WeekEndDate: 'This Week'!$C$5

Sheet Start Here
B1: 🏠 Renovation OS — Start Here
B2: What this tab does: set up your project once (yellow cells), then follow the 5 steps on the right.
B3: © 2026 Hang Nguyen — Renovation OS. Licensed to the original purchaser for personal use only. Do not share, copy, resell or redistribute.
B4: YOUR PROJECT | F4: GET STARTED IN 10 MINUTES
B5: Project name | C5: Maple Lane Renovation | D5: Shown as the Dashboard title. | F5: 1 | G5: Fill in the yellow cells on the left
B6: Property address | C6: 12 Maple Lane | D6: For your own reference. | G6: Project dates, total budget, currency, tax. Everything else calculates itself.
B7: Project start date | C7: 46083 | D7: First day of the project (design counts!). The Timeline starts here. | F7: 2 | G7: Budget tab: set a budget per category
B8: Target move-in date | C8: 46255 | D8: The date you want to live in the house again. | G8: Rename categories if you like. Aim for the total to match your working budget.
B9: ="Total budget incl. "&TaxWord&" ("&CurSym&")" | C9: 135000 | D9: Everything you can spend, including tax and your safety buffer. | F9: 3 | G9: Contractors + Quotes: add who you work with
B10: ="Total floor area ("&AreaUnit&")" | C10: 1528 | D10: Optional — used for cost per m² / ft². | G10: Compare quotes side by side — the hidden-cost checklist shows the TRUE price.
B11: “Today” override (optional) | C11: 46188 | D11: DEMO is frozen on this date so every feature shows data — clear this cell to use today's date. | F11: 4 | G11: Timeline: set durations and dependencies
G12: Dates, Gantt chart and order-by dates for your materials follow automatically.
B13: PREFERENCES | F13: 5 | G13: Every Monday open Dashboard + This Week
B14: Currency | C14: USD $ | D14: Shown next to every amount header. Pick ‘Other’ to type your own symbol. | G14: Do the ranked actions. On Friday fill the Friday Review. That's the whole routine.
B15: Custom currency symbol | D15: Only used when Currency = Other.
B16: Tax name | C16: Sales tax | D16: VAT, Sales tax, GST… used in labels.
B17: Default tax rate | C17: 0.08 | D17: Used to add tax to quotes entered WITHOUT tax. | F17: COLOUR LEGEND
B18: Prices usually quoted incl. tax? | C18: Yes | D18: Pre-fills each quote; you can still change it per quote. | G18: Light-yellow cell = YOU TYPE HERE (or pick from the dropdown).
B19: Area unit | C19: ft² | D19: m² or ft² for room sizes. | G19: White / grey cell = automatic. Protected so you can't break a formula.
B20: Week starts on | C20: Sunday | D20: Used by This Week and the Gantt chart. | F20: 🟢 | G20: On track — nothing to do.
B21: Budget ‘attention’ band | C21: 0.05 | D21: A budget line turns 🟡 when forecast is over budget by up to this %, 🔴 above. | F21: 🟡 | G21: Needs attention soon (within your alert window).
F22: 🔴 | G22: Urgent — overdue, over budget or at risk.
B23: ALERT SETTINGS | G23: White cells are locked and protected, so a formula can never be broken by accident. Type only in the yellow cells.
B24: Contingency (safety buffer) % | C24: 0.1 | D24: 10–15% is typical. Kept aside from your total budget.
B25: Alert window (days) | C25: 7 | D25: Things due within this many days show as 🟡 ‘this week’. | F25: YOUR TABS
B26: Decide-before-order buffer (days) | C26: 7 | D26: Decide this many days before the order-by date. | F26: ▸ | G26: Dashboard | I26: Your renovation at a glance + ranked next actions.
B27: Order safety buffer (days) | C27: 5 | D27: Extra days between delivery and installation. | F27: ▸ | G27: This Week | I27: Monday plan and Friday review.
B28: Overpayment tolerance % | C28: 0.1 | D28: Warn when paid % is more than this ahead of work done %. | F28: ▸ | G28: Budget | I28: Budget vs committed vs forecast per category.
F29: ▸ | G29: Quotes | I29: Compare up to 4 quotes per trade, incl. hidden costs.
B30: CALCULATED FOR YOU | F30: ▸ | G30: Contractors | I30: Contractors, overpayment check and communication log.
B31: ="Contingency amount ("&CurSym&")" | C31: =IF(TotalBudget="",0,TotalBudget*ContPct) | D31: Kept aside for surprises — not part of your working budget. | F31: ▸ | G31: Payments | I31: Payment schedule, invoices and 12-month cash flow.
B32: ="Working budget ("&CurSym&")" | C32: =IF(TotalBudget="",0,TotalBudget-ContAmt) | D32: What you plan to spend. Budget lines should add up to this. | F32: ▸ | G32: Change Orders | I32: Change orders with impact preview before you approve.
B33: Currency symbol in use | C33: =IF(Currency="Other",IF(CustomSym="","¤",CustomSym),IFERROR(INDEX('Lists'!$Q$2:$Q$14,MATCH(Currency,'Lists'!$P$2:$P$14,0)),"¤")) | F33: ▸ | G33: Timeline | I33: Tasks, dependencies and Gantt chart.
B34: Today (as used by all tabs) | C34: =IF(AsOfOverride="",TODAY(),AsOfOverride) | F34: ▸ | G34: Rooms | I34: One card per room: money, progress, problems.
B35: Tax word used in labels | C35: =IF(OR(TaxName="None",TaxName=""),"tax",TaxName) | F35: ▸ | G35: Selections & Orders | I35: Decisions and orders — with decide-by and order-by dates.
F36: ▸ | G36: Issues & Punch List | I36: Problems found on site and the final punch list.
F37: ▸ | G37: Vault | I37: Links to every document and photo + what is missing.
F38: ▸ | G38: Warranty & Maintenance | I38: Warranties and home maintenance after the renovation.
B41: LICENCE & TERMS OF USE
B42: Renovation OS © 2026 Hang Nguyen. All rights reserved.
B43: • This file is licensed, not sold, to the original purchaser for personal, non-commercial use on their own home renovation.
B44: • You may NOT share, copy, resell, redistribute, sublicense, give away or upload this file (or any modified version or part of it) to any website, marketplace, group or other person.
B45: • The formulas, structure, layout and design are the intellectual property of Hang Nguyen. Removing this notice or the sheet protection is not permitted.
B46: • Digital product: all sales are final. No refunds once the file has been delivered.
B47: • Provided “as is” as a planning aid, without warranty. It is not financial, legal or construction advice — always check figures before you act on them.

Sheet Dashboard
B1: ="🏠 "&IF(ProjName="","My renovation",ProjName)
B2: What this tab does: your renovation at a glance — updated automatically. Nothing to type here. | I2: As of | J2: =AsOf
B3: © 2026 Hang Nguyen — Renovation OS. Licensed to the original purchaser for personal use only. Do not share, copy, resell or redistribute.
B4: ="Working budget ("&CurSym&")" | D4: ="Committed ("&CurSym&")" | F4: ="Invoiced ("&CurSym&")" | H4: ="Paid ("&CurSym&")" | J4: ="Remaining to commit ("&CurSym&")"
B5: =WorkBudget | D5: =CommittedTotal | F5: =InvoicedTotal | H5: =PaidTotal | J5: =WorkBudget-CommittedTotal
B6: ="of "&FIXED(TotalBudget,0)&" total budget" | D6: =IF(WorkBudget=0,"",ROUND(CommittedTotal/WorkBudget*100,0)&"% of working budget") | F6: =IF(CommittedTotal=0,"",ROUND(InvoicedTotal/CommittedTotal*100,0)&"% of committed") | H6: ="Cash needed next 30 days: "&FIXED(Cash30,0) | J6: ="working budget − committed"
B8: ="Forecast final cost ("&CurSym&")" | D8: ="Over / under budget ("&CurSym&")" | F8: Contingency used | H8: Project day | J8: Time elapsed
B9: =ForecastTotal | D9: =ForecastTotal-WorkBudget | F9: =ContUsed | H9: =IF(OR(ProjStart="",TargetEnd=""),"–","Day "&MAX(0,AsOf-ProjStart+1)&" of "&(TargetEnd-ProjStart+1)) | J9: =IF(OR(ProjStart="",TargetEnd=""),"–",IF(TargetEnd<=ProjStart,"–",MAX(0,MIN(1,(AsOf-ProjStart)/(TargetEnd-ProjStart)))))
B10: ="incl. risk: "&FIXED(ForecastRisk,0) | D10: =IF(ForecastTotal>WorkBudget,"▲ over working budget",IF(ForecastTotal<WorkBudget,"▼ under working budget","exactly on budget")) | F10: =REPT("█",ROUND(MIN(1,MAX(0,ContUsed))*10,0))&REPT("░",10-ROUND(MIN(1,MAX(0,ContUsed))*10,0)) | H10: =IF(TargetEnd="","set dates on Start Here",IF(TargetEnd>=AsOf,(TargetEnd-AsOf)&" days to target move-in","target date has passed")) | J10: =IF(J9="–","",REPT("█",ROUND(J9*10,0))&REPT("░",10-ROUND(J9*10,0)))
B12: Forecast move-in | D12: Open issues | F12: Overdue items | H12: Decisions waiting | J12: Orders due
B13: =IF(ForecastEnd="","–",ForecastEnd) | D13: =SUM(OpenIssues) | F13: =OverdueCount | H13: =DecisionsWaiting | J13: =OrdersDue+OrdersLate
B14: =IF(OR(ForecastEnd="",TargetEnd=""),"",IF(ForecastEnd>TargetEnd,(ForecastEnd-TargetEnd)&" days after target",IF(ForecastEnd<TargetEnd,(TargetEnd-ForecastEnd)&" days before target","on target"))) | D14: =OpenHigh&" high severity" | F14: ="of "&AlertCount&" alerts in total" | H14: ="see Selections & Orders" | J14: =OrdersLate&" already late"
B16: RENOVATION HEALTH
B17: =IF(N17=0,"🟢 ON TRACK",IF(N17=1,"🟡 NEEDS ATTENTION","🔴 ACTION REQUIRED")) | N17: =MAX(N18:N23)
B18: Budget | D18: =IF(N18=0,"🟢",IF(N18=1,"🟡","🔴")) | E18: ="Forecast "&CurSym&" "&FIXED(ForecastTotal,0)&" vs working budget "&CurSym&" "&FIXED(WorkBudget,0)&IF(N18=0," — within budget",IF(N18=1," — eating into contingency"," — above your TOTAL budget!")) | N18: =IF(ForecastTotal<=WorkBudget,0,IF(ForecastTotal<=TotalBudget,1,2))
B19: Timeline | D19: =IF(N19=0,"🟢",IF(N19=1,"🟡","🔴")) | E19: =IF(ForecastEnd="","Add a project start date and tasks",IF(O19>0,O19&" late task(s) that other tasks depend on · ","")&"forecast move-in "&IF(TargetEnd="","",IF(ForecastEnd>TargetEnd,(ForecastEnd-TargetEnd)&" days after target","on or before target"))) | N19: =IF(O19>0,2,IF(OR(ForecastEnd="",TargetEnd=""),0,IF(ForecastEnd>TargetEnd+14,2,IF(ForecastEnd>TargetEnd,1,0)))) | O19: =COUNTIFS('Timeline'!$Q$7:$Q$156,3,'Timeline'!$O$7:$O$156,">=1")
B20: Contractors & payments | D20: =IF(N20=0,"🟢",IF(N20=1,"🟡","🔴")) | E20: =O20&" overdue payment(s) · "&P20&" paying-ahead warning(s) · "&Q20&" payment(s) due within "&AlertDays&" days" | N20: =IF(OR(O20>0,P20>0),2,IF(Q20>0,1,0)) | O20: =COUNTIF('Payments'!$O$6:$O$205,"OVERDUE") | P20: =COUNTIF('Contractors'!$V$6:$V$35,2) | Q20: =COUNTIF('Payments'!$R$6:$R$205,1)
B21: Materials | D21: =IF(N21=0,"🟢",IF(N21=1,"🟡","🔴")) | E21: =OrdersLate&" late order(s) · "&DeliveriesLate&" delivery after install date · "&OrdersDue&" order(s) due within "&AlertDays&" days" | N21: =IF(OrdersLate+DeliveriesLate>0,2,IF(OrdersDue>0,1,0))
B22: Decisions | D22: =IF(N22=0,"🟢",IF(N22=1,"🟡","🔴")) | E22: =O22&" decision(s) past decide-by date · "&P22&" due within "&AlertDays&" days" | N22: =IF(O22>0,2,IF(P22>0,1,0)) | O22: =SUM('Selections & Orders'!$AE$8:$AE$157) | P22: =SUM('Selections & Orders'!$AF$8:$AF$157)
B23: Issues | D23: =IF(N23=0,"🟢",IF(N23=1,"🟡","🔴")) | E23: =OpenHigh&" open high-severity · "&SUM(OpenIssues)&" open in total" | N23: =IF(OpenHigh>0,2,IF(SUM(OpenIssues)>0,1,0))
B25: YOUR NEXT ACTIONS — ranked by urgency
B26: =IF(AlertCount=0,"🟢 Nothing needs your attention right now",IF(UrgentCount>0,"🔴 ","🟡 ")&AlertCount&IF(AlertCount=1," ACTION NEEDS"," ACTIONS NEED")&" YOUR ATTENTION") | N26: =IF(AlertCount=0,0,IF(UrgentCount>0,2,1))
B27: # | C27: Priority | D27: What to do | H27: Where | J27: Due | K27: When
B28: =IF('Engine'!L2="","",1) | C28: =IF(O28="","",IF(O28=1,"🔴 Urgent",IF(O28=2,"🟡 This week","🔵 Upcoming"))) | D28: =IF('Engine'!L2="","",'Engine'!L2) | H28: =IF('Engine'!K2="","",'Engine'!K2) | J28: =IF('Engine'!M2="","",'Engine'!M2) | K28: =IF(J28="","",IF(J28<AsOf,(AsOf-J28)&IF(AsOf-J28=1," day"," days")&" overdue",IF(J28=AsOf,"today","in "&(J28-AsOf)&IF(J28-AsOf=1," day"," days")))) | O28: ='Engine'!N2
B29: =IF('Engine'!L3="","",2) | C29: =IF(O29="","",IF(O29=1,"🔴 Urgent",IF(O29=2,"🟡 This week","🔵 Upcoming"))) | D29: =IF('Engine'!L3="","",'Engine'!L3) | H29: =IF('Engine'!K3="","",'Engine'!K3) | J29: =IF('Engine'!M3="","",'Engine'!M3) | K29: =IF(J29="","",IF(J29<AsOf,(AsOf-J29)&IF(AsOf-J29=1," day"," days")&" overdue",IF(J29=AsOf,"today","in "&(J29-AsOf)&IF(J29-AsOf=1," day"," days")))) | O29: ='Engine'!N3
B30: =IF('Engine'!L4="","",3) | C30: =IF(O30="","",IF(O30=1,"🔴 Urgent",IF(O30=2,"🟡 This week","🔵 Upcoming"))) | D30: =IF('Engine'!L4="","",'Engine'!L4) | H30: =IF('Engine'!K4="","",'Engine'!K4) | J30: =IF('Engine'!M4="","",'Engine'!M4) | K30: =IF(J30="","",IF(J30<AsOf,(AsOf-J30)&IF(AsOf-J30=1," day"," days")&" overdue",IF(J30=AsOf,"today","in "&(J30-AsOf)&IF(J30-AsOf=1," day"," days")))) | O30: ='Engine'!N4
B31: =IF('Engine'!L5="","",4) | C31: =IF(O31="","",IF(O31=1,"🔴 Urgent",IF(O31=2,"🟡 This week","🔵 Upcoming"))) | D31: =IF('Engine'!L5="","",'Engine'!L5) | H31: =IF('Engine'!K5="","",'Engine'!K5) | J31: =IF('Engine'!M5="","",'Engine'!M5) | K31: =IF(J31="","",IF(J31<AsOf,(AsOf-J31)&IF(AsOf-J31=1," day"," days")&" overdue",IF(J31=AsOf,"today","in "&(J31-AsOf)&IF(J31-AsOf=1," day"," days")))) | O31: ='Engine'!N5
B32: =IF('Engine'!L6="","",5) | C32: =IF(O32="","",IF(O32=1,"🔴 Urgent",IF(O32=2,"🟡 This week","🔵 Upcoming"))) | D32: =IF('Engine'!L6="","",'Engine'!L6) | H32: =IF('Engine'!K6="","",'Engine'!K6) | J32: =IF('Engine'!M6="","",'Engine'!M6) | K32: =IF(J32="","",IF(J32<AsOf,(AsOf-J32)&IF(AsOf-J32=1," day"," days")&" overdue",IF(J32=AsOf,"today","in "&(J32-AsOf)&IF(J32-AsOf=1," day"," days")))) | O32: ='Engine'!N6
B33: =IF('Engine'!L7="","",6) | C33: =IF(O33="","",IF(O33=1,"🔴 Urgent",IF(O33=2,"🟡 This week","🔵 Upcoming"))) | D33: =IF('Engine'!L7="","",'Engine'!L7) | H33: =IF('Engine'!K7="","",'Engine'!K7) | J33: =IF('Engine'!M7="","",'Engine'!M7) | K33: =IF(J33="","",IF(J33<AsOf,(AsOf-J33)&IF(AsOf-J33=1," day"," days")&" overdue",IF(J33=AsOf,"today","in "&(J33-AsOf)&IF(J33-AsOf=1," day"," days")))) | O33: ='Engine'!N7
B34: =IF('Engine'!L8="","",7) | C34: =IF(O34="","",IF(O34=1,"🔴 Urgent",IF(O34=2,"🟡 This week","🔵 Upcoming"))) | D34: =IF('Engine'!L8="","",'Engine'!L8) | H34: =IF('Engine'!K8="","",'Engine'!K8) | J34: =IF('Engine'!M8="","",'Engine'!M8) | K34: =IF(J34="","",IF(J34<AsOf,(AsOf-J34)&IF(AsOf-J34=1," day"," days")&" overdue",IF(J34=AsOf,"today","in "&(J34-AsOf)&IF(J34-AsOf=1," day"," days")))) | O34: ='Engine'!N8
B35: =IF('Engine'!L9="","",8) | C35: =IF(O35="","",IF(O35=1,"🔴 Urgent",IF(O35=2,"🟡 This week","🔵 Upcoming"))) | D35: =IF('Engine'!L9="","",'Engine'!L9) | H35: =IF('Engine'!K9="","",'Engine'!K9) | J35: =IF('Engine'!M9="","",'Engine'!M9) | K35: =IF(J35="","",IF(J35<AsOf,(AsOf-J35)&IF(AsOf-J35=1," day"," days")&" overdue",IF(J35=AsOf,"today","in "&(J35-AsOf)&IF(J35-AsOf=1," day"," days")))) | O35: ='Engine'!N9
B36: =IF('Engine'!L10="","",9) | C36: =IF(O36="","",IF(O36=1,"🔴 Urgent",IF(O36=2,"🟡 This week","🔵 Upcoming"))) | D36: =IF('Engine'!L10="","",'Engine'!L10) | H36: =IF('Engine'!K10="","",'Engine'!K10) | J36: =IF('Engine'!M10="","",'Engine'!M10) | K36: =IF(J36="","",IF(J36<AsOf,(AsOf-J36)&IF(AsOf-J36=1," day"," days")&" overdue",IF(J36=AsOf,"today","in "&(J36-AsOf)&IF(J36-AsOf=1," day"," days")))) | O36: ='Engine'!N10
B37: =IF('Engine'!L11="","",10) | C37: =IF(O37="","",IF(O37=1,"🔴 Urgent",IF(O37=2,"🟡 This week","🔵 Upcoming"))) | D37: =IF('Engine'!L11="","",'Engine'!L11) | H37: =IF('Engine'!K11="","",'Engine'!K11) | J37: =IF('Engine'!M11="","",'Engine'!M11) | K37: =IF(J37="","",IF(J37<AsOf,(AsOf-J37)&IF(AsOf-J37=1," day"," days")&" overdue",IF(J37=AsOf,"today","in "&(J37-AsOf)&IF(J37-AsOf=1," day"," days")))) | O37: ='Engine'!N11
B38: =IF(AlertCount>10,"+ "&(AlertCount-10)&" more — see This Week and in each tab.","")
B40: CHARTS

Sheet This Week
B1: 🗓️ This Week
B2: What this tab does: Monday — see everything that falls in this week. Friday — review what happened and write down next week's top 3.
B3: © 2026 Hang Nguyen — Renovation OS. Licensed to the original purchaser for personal use only. Do not share, copy, resell or redistribute.
B4: Week starting | C4: =AsOf-IF(WeekStart="Sunday",WEEKDAY(AsOf,1)-1,WEEKDAY(AsOf,3)) | D4: Tip: overwrite the yellow date to look at another week.
B5: Week ending | C5: =C4+6
B7: 📋 MONDAY PLAN — what falls in this week
B8: Decisions to make | C8: =COUNTIFS('Selections & Orders'!$T$8:$T$157,">="&WeekStartDate,'Selections & Orders'!$T$8:$T$157,"<="&WeekEndDate,'Selections & Orders'!$AD$8:$AD$157,1) | D8: Selections with a decide-by date this week
B9: Orders to place | C9: =COUNTIFS('Selections & Orders'!$S$8:$S$157,">="&WeekStartDate,'Selections & Orders'!$S$8:$S$157,"<="&WeekEndDate,'Selections & Orders'!$AI$8:$AI$157,1) | D9: Chosen items with an order-by date this week
B10: Payments due | C10: =COUNTIFS('Payments'!$I$6:$I$205,">="&WeekStartDate,'Payments'!$I$6:$I$205,"<="&WeekEndDate,'Payments'!$S$6:$S$205,">0") | D10: Unpaid payments with a due date this week
B11: Deliveries expected | C11: =COUNTIFS('Selections & Orders'!$W$8:$W$157,">="&WeekStartDate,'Selections & Orders'!$W$8:$W$157,"<="&WeekEndDate,'Selections & Orders'!$X$8:$X$157,"<>Yes") | D11: Orders arriving this week — someone must be on site
B12: Tasks starting | C12: =COUNTIFS('Timeline'!$J$7:$J$156,">="&WeekStartDate,'Timeline'!$J$7:$J$156,"<="&WeekEndDate) | D12: Timeline tasks starting
B13: Tasks finishing | C13: =COUNTIFS('Timeline'!$L$7:$L$156,">="&WeekStartDate,'Timeline'!$L$7:$L$156,"<="&WeekEndDate) | D13: Timeline tasks due to finish
B14: Issues with an action this week | C14: =COUNTIFS('Issues & Punch List'!$K$8:$K$207,">="&WeekStartDate,'Issues & Punch List'!$K$8:$K$207,"<="&WeekEndDate,'Issues & Punch List'!$O$8:$O$207,1) | D14: ="Open issues in total: "&SUM(OpenIssues)
B16: 🔴 TOP 10 ALERTS DUE BY THE END OF THIS WEEK (incl. overdue)
B17: Priority | C17: Due | D17: What to do | E17: Where | F17: When
B18: =IF(I18="","",IF(I18=1,"🔴 Urgent",IF(I18=2,"🟡 This week","🔵 Upcoming"))) | C18: =IF('Engine'!U2="","",'Engine'!U2) | D18: =IF('Engine'!T2="","",'Engine'!T2) | E18: =IF('Engine'!S2="","",'Engine'!S2) | F18: =IF(C18="","",IF(C18<AsOf,(AsOf-C18)&IF(AsOf-C18=1," day"," days")&" overdue",IF(C18=AsOf,"today","in "&(C18-AsOf)&IF(C18-AsOf=1," day"," days")))) | I18: ='Engine'!V2
B19: =IF(I19="","",IF(I19=1,"🔴 Urgent",IF(I19=2,"🟡 This week","🔵 Upcoming"))) | C19: =IF('Engine'!U3="","",'Engine'!U3) | D19: =IF('Engine'!T3="","",'Engine'!T3) | E19: =IF('Engine'!S3="","",'Engine'!S3) | F19: =IF(C19="","",IF(C19<AsOf,(AsOf-C19)&IF(AsOf-C19=1," day"," days")&" overdue",IF(C19=AsOf,"today","in "&(C19-AsOf)&IF(C19-AsOf=1," day"," days")))) | I19: ='Engine'!V3
B20: =IF(I20="","",IF(I20=1,"🔴 Urgent",IF(I20=2,"🟡 This week","🔵 Upcoming"))) | C20: =IF('Engine'!U4="","",'Engine'!U4) | D20: =IF('Engine'!T4="","",'Engine'!T4) | E20: =IF('Engine'!S4="","",'Engine'!S4) | F20: =IF(C20="","",IF(C20<AsOf,(AsOf-C20)&IF(AsOf-C20=1," day"," days")&" overdue",IF(C20=AsOf,"today","in "&(C20-AsOf)&IF(C20-AsOf=1," day"," days")))) | I20: ='Engine'!V4
B21: =IF(I21="","",IF(I21=1,"🔴 Urgent",IF(I21=2,"🟡 This week","🔵 Upcoming"))) | C21: =IF('Engine'!U5="","",'Engine'!U5) | D21: =IF('Engine'!T5="","",'Engine'!T5) | E21: =IF('Engine'!S5="","",'Engine'!S5) | F21: =IF(C21="","",IF(C21<AsOf,(AsOf-C21)&IF(AsOf-C21=1," day"," days")&" overdue",IF(C21=AsOf,"today","in "&(C21-AsOf)&IF(C21-AsOf=1," day"," days")))) | I21: ='Engine'!V5
B22: =IF(I22="","",IF(I22=1,"🔴 Urgent",IF(I22=2,"🟡 This week","🔵 Upcoming"))) | C22: =IF('Engine'!U6="","",'Engine'!U6) | D22: =IF('Engine'!T6="","",'Engine'!T6) | E22: =IF('Engine'!S6="","",'Engine'!S6) | F22: =IF(C22="","",IF(C22<AsOf,(AsOf-C22)&IF(AsOf-C22=1," day"," days")&" overdue",IF(C22=AsOf,"today","in "&(C22-AsOf)&IF(C22-AsOf=1," day"," days")))) | I22: ='Engine'!V6
B23: =IF(I23="","",IF(I23=1,"🔴 Urgent",IF(I23=2,"🟡 This week","🔵 Upcoming"))) | C23: =IF('Engine'!U7="","",'Engine'!U7) | D23: =IF('Engine'!T7="","",'Engine'!T7) | E23: =IF('Engine'!S7="","",'Engine'!S7) | F23: =IF(C23="","",IF(C23<AsOf,(AsOf-C23)&IF(AsOf-C23=1," day"," days")&" overdue",IF(C23=AsOf,"today","in "&(C23-AsOf)&IF(C23-AsOf=1," day"," days")))) | I23: ='Engine'!V7
B24: =IF(I24="","",IF(I24=1,"🔴 Urgent",IF(I24=2,"🟡 This week","🔵 Upcoming"))) | C24: =IF('Engine'!U8="","",'Engine'!U8) | D24: =IF('Engine'!T8="","",'Engine'!T8) | E24: =IF('Engine'!S8="","",'Engine'!S8) | F24: =IF(C24="","",IF(C24<AsOf,(AsOf-C24)&IF(AsOf-C24=1," day"," days")&" overdue",IF(C24=AsOf,"today","in "&(C24-AsOf)&IF(C24-AsOf=1," day"," days")))) | I24: ='Engine'!V8
B25: =IF(I25="","",IF(I25=1,"🔴 Urgent",IF(I25=2,"🟡 This week","🔵 Upcoming"))) | C25: =IF('Engine'!U9="","",'Engine'!U9) | D25: =IF('Engine'!T9="","",'Engine'!T9) | E25: =IF('Engine'!S9="","",'Engine'!S9) | F25: =IF(C25="","",IF(C25<AsOf,(AsOf-C25)&IF(AsOf-C25=1," day"," days")&" overdue",IF(C25=AsOf,"today","in "&(C25-AsOf)&IF(C25-AsOf=1," day"," days")))) | I25: ='Engine'!V9
B26: =IF(I26="","",IF(I26=1,"🔴 Urgent",IF(I26=2,"🟡 This week","🔵 Upcoming"))) | C26: =IF('Engine'!U10="","",'Engine'!U10) | D26: =IF('Engine'!T10="","",'Engine'!T10) | E26: =IF('Engine'!S10="","",'Engine'!S10) | F26: =IF(C26="","",IF(C26<AsOf,(AsOf-C26)&IF(AsOf-C26=1," day"," days")&" overdue",IF(C26=AsOf,"today","in "&(C26-AsOf)&IF(C26-AsOf=1," day"," days")))) | I26: ='Engine'!V10
B27: =IF(I27="","",IF(I27=1,"🔴 Urgent",IF(I27=2,"🟡 This week","🔵 Upcoming"))) | C27: =IF('Engine'!U11="","",'Engine'!U11) | D27: =IF('Engine'!T11="","",'Engine'!T11) | E27: =IF('Engine'!S11="","",'Engine'!S11) | F27: =IF(C27="","",IF(C27<AsOf,(AsOf-C27)&IF(AsOf-C27=1," day"," days")&" overdue",IF(C27=AsOf,"today","in "&(C27-AsOf)&IF(C27-AsOf=1," day"," days")))) | I27: ='Engine'!V11
B28: =IF(WeekAlertCount=0,"🟢 Nothing due this week.",IF(WeekAlertCount>10,"+ "&(WeekAlertCount-10)&" more due this week","All "&WeekAlertCount&" shown."))
B30: 📝 FRIDAY REVIEW — the numbers (automatic)
B31: ="Paid this week ("&CurSym&")" | C31: =SUMIFS('Payments'!$N$6:$N$205,'Payments'!$M$6:$M$205,">="&WeekStartDate,'Payments'!$M$6:$M$205,"<="&WeekEndDate)
B32: Change orders approved this week | C32: =COUNTIFS('Change Orders'!$L$7:$L$106,"Approved",'Change Orders'!$M$7:$M$106,">="&WeekStartDate,'Change Orders'!$M$7:$M$106,"<="&WeekEndDate)
B33: ="…their extra cost ("&CurSym&")" | C33: =SUMIFS('Change Orders'!$J$7:$J$106,'Change Orders'!$L$7:$L$106,"Approved",'Change Orders'!$M$7:$M$106,">="&WeekStartDate,'Change Orders'!$M$7:$M$106,"<="&WeekEndDate)
B34: Tasks completed this week | C34: =COUNTIFS('Timeline'!$M$7:$M$156,"Done",'Timeline'!$N$7:$N$156,">="&WeekStartDate,'Timeline'!$N$7:$N$156,"<="&WeekEndDate)
B35: Issues opened this week | C35: =COUNTIFS('Issues & Punch List'!$D$8:$D$207,">="&WeekStartDate,'Issues & Punch List'!$D$8:$D$207,"<="&WeekEndDate)
B36: Issues closed this week | C36: =COUNTIFS('Issues & Punch List'!$M$8:$M$207,">="&WeekStartDate,'Issues & Punch List'!$M$8:$M$207,"<="&WeekEndDate)
B38: 📝 FRIDAY REVIEW — your notes (type in the yellow boxes)
B39: What was completed?
B40: Electrical first fix 90% done; shower enclosure delivered.
B44: What was delayed?
B45: Plumbing rough-in (pipe re-route) — now 10 days late.
B49: What changed?
B50: EV charger change order requested by electrician (pending).
B54: What is now at risk?
B55: Kitchen install on 2 Jul depends on drywall — tight.
B59: Top 3 for next week
B60: 1) Decide bathroom 2 tiles 2) Pay FlowRight after re-route fixed 3) Chase electrician insurance

Sheet Budget
B1: 💶 Budget
B2: What this tab does: compares your budget per category with what you have committed, invoiced and paid, and forecasts the final cost.
B3: © 2026 Hang Nguyen — Renovation OS. Licensed to the original purchaser for personal use only. Do not share, copy, resell or redistribute.
B4: ="Working budget ("&CurSym&")" | C4: =WorkBudget | E4: Sum of category budgets | G4: =BudgetSum | H4: =IF(WorkBudget=0,"",IF(ABS(BudgetSum-WorkBudget)<1,"✓ matches",IF(BudgetSum>WorkBudget,"▲ "&FIXED(BudgetSum-WorkBudget,0)&" more than working budget","▼ "&FIXED(WorkBudget-BudgetSum,0)&" not yet allocated")))
B7: Category | C7: ="Budget ("&CurSym&")" | D7: Stage | E7: ="Best quote ("&CurSym&")" | F7: ="Contracted ("&CurSym&")" | G7: ="Materials ("&CurSym&")" | H7: ="Approved changes ("&CurSym&")" | I7: ="Committed ("&CurSym&")" | J7: ="Invoiced ("&CurSym&")" | K7: ="Paid ("&CurSym&")" | L7: ="Forecast ("&CurSym&")" | M7: ="Variance ("&CurSym&")" | N7: Status | O7: lvl | P7: chart key
B8: Demolition | C8: 4000 | D8: Complete | E8: =IF(B8="","",IFERROR(1/SUMPRODUCT(MAX((QBlockCat=B8)*QBlockInv)),"")) | F8: =IF(B8="","",SUMIFS('Contractors'!$I$6:$I$35,'Contractors'!$D$6:$D$35,B8,'Contractors'!$L$6:$L$35,"Yes")) | G8: =IF(B8="","",SUMIFS('Selections & Orders'!$L$8:$L$157,'Selections & Orders'!$D$8:$D$157,B8)) | H8: =IF(B8="","",SUMIFS('Change Orders'!$J$7:$J$106,'Change Orders'!$F$7:$F$106,B8,'Change Orders'!$L$7:$L$106,"Approved")) | I8: =IF(B8="","",F8+G8+H8) | J8: =IF(B8="","",SUMIFS('Payments'!$L$6:$L$205,'Payments'!$P$6:$P$205,B8)) | K8: =IF(B8="","",SUMIFS('Payments'!$N$6:$N$205,'Payments'!$P$6:$P$205,B8)) | L8: =IF(B8="","",IF(OR(D8="Estimating",D8=""),MAX(C8,E8,I8,J8),MAX(I8,J8))) | M8: =IF(B8="","",C8-L8) | N8: =IF(O8="","",IF(O8=0,"🟢 On track",IF(O8=1,"🟡 Watch","🔴 Over"))) | O8: =IF(B8="","",IF(L8<=C8,0,IF(L8<=C8*(1+BudgetWarnPct),1,2))) | P8: =IF(B8="","",IF(MAX(C8,L8)>0,MAX(C8,L8)+ROW()/100000,""))
B9: Structural | C9: 9000 | D9: Complete | E9: =IF(B9="","",IFERROR(1/SUMPRODUCT(MAX((QBlockCat=B9)*QBlockInv)),"")) | F9: =IF(B9="","",SUMIFS('Contractors'!$I$6:$I$35,'Contractors'!$D$6:$D$35,B9,'Contractors'!$L$6:$L$35,"Yes")) | G9: =IF(B9="","",SUMIFS('Selections & Orders'!$L$8:$L$157,'Selections & Orders'!$D$8:$D$157,B9)) | H9: =IF(B9="","",SUMIFS('Change Orders'!$J$7:$J$106,'Change Orders'!$F$7:$F$106,B9,'Change Orders'!$L$7:$L$106,"Approved")) | I9: =IF(B9="","",F9+G9+H9) | J9: =IF(B9="","",SUMIFS('Payments'!$L$6:$L$205,'Payments'!$P$6:$P$205,B9)) | K9: =IF(B9="","",SUMIFS('Payments'!$N$6:$N$205,'Payments'!$P$6:$P$205,B9)) | L9: =IF(B9="","",IF(OR(D9="Estimating",D9=""),MAX(C9,E9,I9,J9),MAX(I9,J9))) | M9: =IF(B9="","",C9-L9) | N9: =IF(O9="","",IF(O9=0,"🟢 On track",IF(O9=1,"🟡 Watch","🔴 Over"))) | O9: =IF(B9="","",IF(L9<=C9,0,IF(L9<=C9*(1+BudgetWarnPct),1,2))) | P9: =IF(B9="","",IF(MAX(C9,L9)>0,MAX(C9,L9)+ROW()/100000,""))
B10: Plumbing | C10: 9500 | D10: Contracted | E10: =IF(B10="","",IFERROR(1/SUMPRODUCT(MAX((QBlockCat=B10)*QBlockInv)),"")) | F10: =IF(B10="","",SUMIFS('Contractors'!$I$6:$I$35,'Contractors'!$D$6:$D$35,B10,'Contractors'!$L$6:$L$35,"Yes")) | G10: =IF(B10="","",SUMIFS('Selections & Orders'!$L$8:$L$157,'Selections & Orders'!$D$8:$D$157,B10)) | H10: =IF(B10="","",SUMIFS('Change Orders'!$J$7:$J$106,'Change Orders'!$F$7:$F$106,B10,'Change Orders'!$L$7:$L$106,"Approved")) | I10: =IF(B10="","",F10+G10+H10) | J10: =IF(B10="","",SUMIFS('Payments'!$L$6:$L$205,'Payments'!$P$6:$P$205,B10)) | K10: =IF(B10="","",SUMIFS('Payments'!$N$6:$N$205,'Payments'!$P$6:$P$205,B10)) | L10: =IF(B10="","",IF(OR(D10="Estimating",D10=""),MAX(C10,E10,I10,J10),MAX(I10,J10))) | M10: =IF(B10="","",C10-L10) | N10: =IF(O10="","",IF(O10=0,"🟢 On track",IF(O10=1,"🟡 Watch","🔴 Over"))) | O10: =IF(B10="","",IF(L10<=C10,0,IF(L10<=C10*(1+BudgetWarnPct),1,2))) | P10: =IF(B10="","",IF(MAX(C10,L10)>0,MAX(C10,L10)+ROW()/100000,""))
B11: Electrical | C11: 10000 | D11: Contracted | E11: =IF(B11="","",IFERROR(1/SUMPRODUCT(MAX((QBlockCat=B11)*QBlockInv)),"")) | F11: =IF(B11="","",SUMIFS('Contractors'!$I$6:$I$35,'Contractors'!$D$6:$D$35,B11,'Contractors'!$L$6:$L$35,"Yes")) | G11: =IF(B11="","",SUMIFS('Selections & Orders'!$L$8:$L$157,'Selections & Orders'!$D$8:$D$157,B11)) | H11: =IF(B11="","",SUMIFS('Change Orders'!$J$7:$J$106,'Change Orders'!$F$7:$F$106,B11,'Change Orders'!$L$7:$L$106,"Approved")) | I11: =IF(B11="","",F11+G11+H11) | J11: =IF(B11="","",SUMIFS('Payments'!$L$6:$L$205,'Payments'!$P$6:$P$205,B11)) | K11: =IF(B11="","",SUMIFS('Payments'!$N$6:$N$205,'Payments'!$P$6:$P$205,B11)) | L11: =IF(B11="","",IF(OR(D11="Estimating",D11=""),MAX(C11,E11,I11,J11),MAX(I11,J11))) | M11: =IF(B11="","",C11-L11) | N11: =IF(O11="","",IF(O11=0,"🟢 On track",IF(O11=1,"🟡 Watch","🔴 Over"))) | O11: =IF(B11="","",IF(L11<=C11,0,IF(L11<=C11*(1+BudgetWarnPct),1,2))) | P11: =IF(B11="","",IF(MAX(C11,L11)>0,MAX(C11,L11)+ROW()/100000,""))
B12: HVAC | C12: 9000 | D12: Contracted | E12: =IF(B12="","",IFERROR(1/SUMPRODUCT(MAX((QBlockCat=B12)*QBlockInv)),"")) | F12: =IF(B12="","",SUMIFS('Contractors'!$I$6:$I$35,'Contractors'!$D$6:$D$35,B12,'Contractors'!$L$6:$L$35,"Yes")) | G12: =IF(B12="","",SUMIFS('Selections & Orders'!$L$8:$L$157,'Selections & Orders'!$D$8:$D$157,B12)) | H12: =IF(B12="","",SUMIFS('Change Orders'!$J$7:$J$106,'Change Orders'!$F$7:$F$106,B12,'Change Orders'!$L$7:$L$106,"Approved")) | I12: =IF(B12="","",F12+G12+H12) | J12: =IF(B12="","",SUMIFS('Payments'!$L$6:$L$205,'Payments'!$P$6:$P$205,B12)) | K12: =IF(B12="","",SUMIFS('Payments'!$N$6:$N$205,'Payments'!$P$6:$P$205,B12)) | L12: =IF(B12="","",IF(OR(D12="Estimating",D12=""),MAX(C12,E12,I12,J12),MAX(I12,J12))) | M12: =IF(B12="","",C12-L12) | N12: =IF(O12="","",IF(O12=0,"🟢 On track",IF(O12=1,"🟡 Watch","🔴 Over"))) | O12: =IF(B12="","",IF(L12<=C12,0,IF(L12<=C12*(1+BudgetWarnPct),1,2))) | P12: =IF(B12="","",IF(MAX(C12,L12)>0,MAX(C12,L12)+ROW()/100000,""))
B13: Windows & doors | C13: 12000 | D13: Contracted | E13: =IF(B13="","",IFERROR(1/SUMPRODUCT(MAX((QBlockCat=B13)*QBlockInv)),"")) | F13: =IF(B13="","",SUMIFS('Contractors'!$I$6:$I$35,'Contractors'!$D$6:$D$35,B13,'Contractors'!$L$6:$L$35,"Yes")) | G13: =IF(B13="","",SUMIFS('Selections & Orders'!$L$8:$L$157,'Selections & Orders'!$D$8:$D$157,B13)) | H13: =IF(B13="","",SUMIFS('Change Orders'!$J$7:$J$106,'Change Orders'!$F$7:$F$106,B13,'Change Orders'!$L$7:$L$106,"Approved")) | I13: =IF(B13="","",F13+G13+H13) | J13: =IF(B13="","",SUMIFS('Payments'!$L$6:$L$205,'Payments'!$P$6:$P$205,B13)) | K13: =IF(B13="","",SUMIFS('Payments'!$N$6:$N$205,'Payments'!$P$6:$P$205,B13)) | L13: =IF(B13="","",IF(OR(D13="Estimating",D13=""),MAX(C13,E13,I13,J13),MAX(I13,J13))) | M13: =IF(B13="","",C13-L13) | N13: =IF(O13="","",IF(O13=0,"🟢 On track",IF(O13=1,"🟡 Watch","🔴 Over"))) | O13: =IF(B13="","",IF(L13<=C13,0,IF(L13<=C13*(1+BudgetWarnPct),1,2))) | P13: =IF(B13="","",IF(MAX(C13,L13)>0,MAX(C13,L13)+ROW()/100000,""))
B14: Roofing | C14: 3000 | D14: Estimating | E14: =IF(B14="","",IFERROR(1/SUMPRODUCT(MAX((QBlockCat=B14)*QBlockInv)),"")) | F14: =IF(B14="","",SUMIFS('Contractors'!$I$6:$I$35,'Contractors'!$D$6:$D$35,B14,'Contractors'!$L$6:$L$35,"Yes")) | G14: =IF(B14="","",SUMIFS('Selections & Orders'!$L$8:$L$157,'Selections & Orders'!$D$8:$D$157,B14)) | H14: =IF(B14="","",SUMIFS('Change Orders'!$J$7:$J$106,'Change Orders'!$F$7:$F$106,B14,'Change Orders'!$L$7:$L$106,"Approved")) | I14: =IF(B14="","",F14+G14+H14) | J14: =IF(B14="","",SUMIFS('Payments'!$L$6:$L$205,'Payments'!$P$6:$P$205,B14)) | K14: =IF(B14="","",SUMIFS('Payments'!$N$6:$N$205,'Payments'!$P$6:$P$205,B14)) | L14: =IF(B14="","",IF(OR(D14="Estimating",D14=""),MAX(C14,E14,I14,J14),MAX(I14,J14))) | M14: =IF(B14="","",C14-L14) | N14: =IF(O14="","",IF(O14=0,"🟢 On track",IF(O14=1,"🟡 Watch","🔴 Over"))) | O14: =IF(B14="","",IF(L14<=C14,0,IF(L14<=C14*(1+BudgetWarnPct),1,2))) | P14: =IF(B14="","",IF(MAX(C14,L14)>0,MAX(C14,L14)+ROW()/100000,""))
B15: Kitchen | C15: 20000 | D15: Contracted | E15: =IF(B15="","",IFERROR(1/SUMPRODUCT(MAX((QBlockCat=B15)*QBlockInv)),"")) | F15: =IF(B15="","",SUMIFS('Contractors'!$I$6:$I$35,'Contractors'!$D$6:$D$35,B15,'Contractors'!$L$6:$L$35,"Yes")) | G15: =IF(B15="","",SUMIFS('Selections & Orders'!$L$8:$L$157,'Selections & Orders'!$D$8:$D$157,B15)) | H15: =IF(B15="","",SUMIFS('Change Orders'!$J$7:$J$106,'Change Orders'!$F$7:$F$106,B15,'Change Orders'!$L$7:$L$106,"Approved")) | I15: =IF(B15="","",F15+G15+H15) | J15: =IF(B15="","",SUMIFS('Payments'!$L$6:$L$205,'Payments'!$P$6:$P$205,B15)) | K15: =IF(B15="","",SUMIFS('Payments'!$N$6:$N$205,'Payments'!$P$6:$P$205,B15)) | L15: =IF(B15="","",IF(OR(D15="Estimating",D15=""),MAX(C15,E15,I15,J15),MAX(I15,J15))) | M15: =IF(B15="","",C15-L15) | N15: =IF(O15="","",IF(O15=0,"🟢 On track",IF(O15=1,"🟡 Watch","🔴 Over"))) | O15: =IF(B15="","",IF(L15<=C15,0,IF(L15<=C15*(1+BudgetWarnPct),1,2))) | P15: =IF(B15="","",IF(MAX(C15,L15)>0,MAX(C15,L15)+ROW()/100000,""))
B16: Bathrooms | C16: 15000 | D16: Contracted | E16: =IF(B16="","",IFERROR(1/SUMPRODUCT(MAX((QBlockCat=B16)*QBlockInv)),"")) | F16: =IF(B16="","",SUMIFS('Contractors'!$I$6:$I$35,'Contractors'!$D$6:$D$35,B16,'Contractors'!$L$6:$L$35,"Yes")) | G16: =IF(B16="","",SUMIFS('Selections & Orders'!$L$8:$L$157,'Selections & Orders'!$D$8:$D$157,B16)) | H16: =IF(B16="","",SUMIFS('Change Orders'!$J$7:$J$106,'Change Orders'!$F$7:$F$106,B16,'Change Orders'!$L$7:$L$106,"Approved")) | I16: =IF(B16="","",F16+G16+H16) | J16: =IF(B16="","",SUMIFS('Payments'!$L$6:$L$205,'Payments'!$P$6:$P$205,B16)) | K16: =IF(B16="","",SUMIFS('Payments'!$N$6:$N$205,'Payments'!$P$6:$P$205,B16)) | L16: =IF(B16="","",IF(OR(D16="Estimating",D16=""),MAX(C16,E16,I16,J16),MAX(I16,J16))) | M16: =IF(B16="","",C16-L16) | N16: =IF(O16="","",IF(O16=0,"🟢 On track",IF(O16=1,"🟡 Watch","🔴 Over"))) | O16: =IF(B16="","",IF(L16<=C16,0,IF(L16<=C16*(1+BudgetWarnPct),1,2))) | P16: =IF(B16="","",IF(MAX(C16,L16)>0,MAX(C16,L16)+ROW()/100000,""))
B17: Flooring | C17: 8500 | D17: Estimating | E17: =IF(B17="","",IFERROR(1/SUMPRODUCT(MAX((QBlockCat=B17)*QBlockInv)),"")) | F17: =IF(B17="","",SUMIFS('Contractors'!$I$6:$I$35,'Contractors'!$D$6:$D$35,B17,'Contractors'!$L$6:$L$35,"Yes")) | G17: =IF(B17="","",SUMIFS('Selections & Orders'!$L$8:$L$157,'Selections & Orders'!$D$8:$D$157,B17)) | H17: =IF(B17="","",SUMIFS('Change Orders'!$J$7:$J$106,'Change Orders'!$F$7:$F$106,B17,'Change Orders'!$L$7:$L$106,"Approved")) | I17: =IF(B17="","",F17+G17+H17) | J17: =IF(B17="","",SUMIFS('Payments'!$L$6:$L$205,'Payments'!$P$6:$P$205,B17)) | K17: =IF(B17="","",SUMIFS('Payments'!$N$6:$N$205,'Payments'!$P$6:$P$205,B17)) | L17: =IF(B17="","",IF(OR(D17="Estimating",D17=""),MAX(C17,E17,I17,J17),MAX(I17,J17))) | M17: =IF(B17="","",C17-L17) | N17: =IF(O17="","",IF(O17=0,"🟢 On track",IF(O17=1,"🟡 Watch","🔴 Over"))) | O17: =IF(B17="","",IF(L17<=C17,0,IF(L17<=C17*(1+BudgetWarnPct),1,2))) | P17: =IF(B17="","",IF(MAX(C17,L17)>0,MAX(C17,L17)+ROW()/100000,""))
B18: Painting | C18: 4500 | D18: Estimating | E18: =IF(B18="","",IFERROR(1/SUMPRODUCT(MAX((QBlockCat=B18)*QBlockInv)),"")) | F18: =IF(B18="","",SUMIFS('Contractors'!$I$6:$I$35,'Contractors'!$D$6:$D$35,B18,'Contractors'!$L$6:$L$35,"Yes")) | G18: =IF(B18="","",SUMIFS('Selections & Orders'!$L$8:$L$157,'Selections & Orders'!$D$8:$D$157,B18)) | H18: =IF(B18="","",SUMIFS('Change Orders'!$J$7:$J$106,'Change Orders'!$F$7:$F$106,B18,'Change Orders'!$L$7:$L$106,"Approved")) | I18: =IF(B18="","",F18+G18+H18) | J18: =IF(B18="","",SUMIFS('Payments'!$L$6:$L$205,'Payments'!$P$6:$P$205,B18)) | K18: =IF(B18="","",SUMIFS('Payments'!$N$6:$N$205,'Payments'!$P$6:$P$205,B18)) | L18: =IF(B18="","",IF(OR(D18="Estimating",D18=""),MAX(C18,E18,I18,J18),MAX(I18,J18))) | M18: =IF(B18="","",C18-L18) | N18: =IF(O18="","",IF(O18=0,"🟢 On track",IF(O18=1,"🟡 Watch","🔴 Over"))) | O18: =IF(B18="","",IF(L18<=C18,0,IF(L18<=C18*(1+BudgetWarnPct),1,2))) | P18: =IF(B18="","",IF(MAX(C18,L18)>0,MAX(C18,L18)+ROW()/100000,""))
B19: Landscaping | C19: 2000 | D19: Estimating | E19: =IF(B19="","",IFERROR(1/SUMPRODUCT(MAX((QBlockCat=B19)*QBlockInv)),"")) | F19: =IF(B19="","",SUMIFS('Contractors'!$I$6:$I$35,'Contractors'!$D$6:$D$35,B19,'Contractors'!$L$6:$L$35,"Yes")) | G19: =IF(B19="","",SUMIFS('Selections & Orders'!$L$8:$L$157,'Selections & Orders'!$D$8:$D$157,B19)) | H19: =IF(B19="","",SUMIFS('Change Orders'!$J$7:$J$106,'Change Orders'!$F$7:$F$106,B19,'Change Orders'!$L$7:$L$106,"Approved")) | I19: =IF(B19="","",F19+G19+H19) | J19: =IF(B19="","",SUMIFS('Payments'!$L$6:$L$205,'Payments'!$P$6:$P$205,B19)) | K19: =IF(B19="","",SUMIFS('Payments'!$N$6:$N$205,'Payments'!$P$6:$P$205,B19)) | L19: =IF(B19="","",IF(OR(D19="Estimating",D19=""),MAX(C19,E19,I19,J19),MAX(I19,J19))) | M19: =IF(B19="","",C19-L19) | N19: =IF(O19="","",IF(O19=0,"🟢 On track",IF(O19=1,"🟡 Watch","🔴 Over"))) | O19: =IF(B19="","",IF(L19<=C19,0,IF(L19<=C19*(1+BudgetWarnPct),1,2))) | P19: =IF(B19="","",IF(MAX(C19,L19)>0,MAX(C19,L19)+ROW()/100000,""))
... B25: Other | C25: 500 | D25: Estimating | E25: =IF(B25="","",IFERROR(1/SUMPRODUCT(MAX((QBlockCat=B25)*QBlockInv)),"")) | F25: =IF(B25="","",SUMIFS('Contractors'!$I$6:$I$35,'Contractors'!$D$6:$D$35,B25,'Contractors'!$L$6:$L$35,"Yes")) | G25: =IF(B25="","",SUMIFS('Selections & Orders'!$L$8:$L$157,'Selections & Orders'!$D$8:$D$157,B25)) | H25: =IF(B25="","",SUMIFS('Change Orders'!$J$7:$J$106,'Change Orders'!$F$7:$F$106,B25,'Change Orders'!$L$7:$L$106,"Approved")) | I25: =IF(B25="","",F25+G25+H25) | J25: =IF(B25="","",SUMIFS('Payments'!$L$6:$L$205,'Payments'!$P$6:$P$205,B25)) | K25: =IF(B25="","",SUMIFS('Payments'!$N$6:$N$205,'Payments'!$P$6:$P$205,B25)) | L25: =IF(B25="","",IF(OR(D25="Estimating",D25=""),MAX(C25,E25,I25,J25),MAX(I25,J25))) | M25: =IF(B25="","",C25-L25) | N25: =IF(O25="","",IF(O25=0,"🟢 On track",IF(O25=1,"🟡 Watch","🔴 Over"))) | O25: =IF(B25="","",IF(L25<=C25,0,IF(L25<=C25*(1+BudgetWarnPct),1,2))) | P25: =IF(B25="","",IF(MAX(C25,L25)>0,MAX(C25,L25)+ROW()/100000,""))
E26: =IF(B26="","",IFERROR(1/SUMPRODUCT(MAX((QBlockCat=B26)*QBlockInv)),"")) | F26: =IF(B26="","",SUMIFS('Contractors'!$I$6:$I$35,'Contractors'!$D$6:$D$35,B26,'Contractors'!$L$6:$L$35,"Yes")) | G26: =IF(B26="","",SUMIFS('Selections & Orders'!$L$8:$L$157,'Selections & Orders'!$D$8:$D$157,B26)) | H26: =IF(B26="","",SUMIFS('Change Orders'!$J$7:$J$106,'Change Orders'!$F$7:$F$106,B26,'Change Orders'!$L$7:$L$106,"Approved")) | I26: =IF(B26="","",F26+G26+H26) | J26: =IF(B26="","",SUMIFS('Payments'!$L$6:$L$205,'Payments'!$P$6:$P$205,B26)) | K26: =IF(B26="","",SUMIFS('Payments'!$N$6:$N$205,'Payments'!$P$6:$P$205,B26)) | L26: =IF(B26="","",IF(OR(D26="Estimating",D26=""),MAX(C26,E26,I26,J26),MAX(I26,J26))) | M26: =IF(B26="","",C26-L26) | N26: =IF(O26="","",IF(O26=0,"🟢 On track",IF(O26=1,"🟡 Watch","🔴 Over"))) | O26: =IF(B26="","",IF(L26<=C26,0,IF(L26<=C26*(1+BudgetWarnPct),1,2))) | P26: =IF(B26="","",IF(MAX(C26,L26)>0,MAX(C26,L26)+ROW()/100000,""))
E27: =IF(B27="","",IFERROR(1/SUMPRODUCT(MAX((QBlockCat=B27)*QBlockInv)),"")) | F27: =IF(B27="","",SUMIFS('Contractors'!$I$6:$I$35,'Contractors'!$D$6:$D$35,B27,'Contractors'!$L$6:$L$35,"Yes")) | G27: =IF(B27="","",SUMIFS('Selections & Orders'!$L$8:$L$157,'Selections & Orders'!$D$8:$D$157,B27)) | H27: =IF(B27="","",SUMIFS('Change Orders'!$J$7:$J$106,'Change Orders'!$F$7:$F$106,B27,'Change Orders'!$L$7:$L$106,"Approved")) | I27: =IF(B27="","",F27+G27+H27) | J27: =IF(B27="","",SUMIFS('Payments'!$L$6:$L$205,'Payments'!$P$6:$P$205,B27)) | K27: =IF(B27="","",SUMIFS('Payments'!$N$6:$N$205,'Payments'!$P$6:$P$205,B27)) | L27: =IF(B27="","",IF(OR(D27="Estimating",D27=""),MAX(C27,E27,I27,J27),MAX(I27,J27))) | M27: =IF(B27="","",C27-L27) | N27: =IF(O27="","",IF(O27=0,"🟢 On track",IF(O27=1,"🟡 Watch","🔴 Over"))) | O27: =IF(B27="","",IF(L27<=C27,0,IF(L27<=C27*(1+BudgetWarnPct),1,2))) | P27: =IF(B27="","",IF(MAX(C27,L27)>0,MAX(C27,L27)+ROW()/100000,""))
E28: =IF(B28="","",IFERROR(1/SUMPRODUCT(MAX((QBlockCat=B28)*QBlockInv)),"")) | F28: =IF(B28="","",SUMIFS('Contractors'!$I$6:$I$35,'Contractors'!$D$6:$D$35,B28,'Contractors'!$L$6:$L$35,"Yes")) | G28: =IF(B28="","",SUMIFS('Selections & Orders'!$L$8:$L$157,'Selections & Orders'!$D$8:$D$157,B28)) | H28: =IF(B28="","",SUMIFS('Change Orders'!$J$7:$J$106,'Change Orders'!$F$7:$F$106,B28,'Change Orders'!$L$7:$L$106,"Approved")) | I28: =IF(B28="","",F28+G28+H28) | J28: =IF(B28="","",SUMIFS('Payments'!$L$6:$L$205,'Payments'!$P$6:$P$205,B28)) | K28: =IF(B28="","",SUMIFS('Payments'!$N$6:$N$205,'Payments'!$P$6:$P$205,B28)) | L28: =IF(B28="","",IF(OR(D28="Estimating",D28=""),MAX(C28,E28,I28,J28),MAX(I28,J28))) | M28: =IF(B28="","",C28-L28) | N28: =IF(O28="","",IF(O28=0,"🟢 On track",IF(O28=1,"🟡 Watch","🔴 Over"))) | O28: =IF(B28="","",IF(L28<=C28,0,IF(L28<=C28*(1+BudgetWarnPct),1,2))) | P28: =IF(B28="","",IF(MAX(C28,L28)>0,MAX(C28,L28)+ROW()/100000,""))
E29: =IF(B29="","",IFERROR(1/SUMPRODUCT(MAX((QBlockCat=B29)*QBlockInv)),"")) | F29: =IF(B29="","",SUMIFS('Contractors'!$I$6:$I$35,'Contractors'!$D$6:$D$35,B29,'Contractors'!$L$6:$L$35,"Yes")) | G29: =IF(B29="","",SUMIFS('Selections & Orders'!$L$8:$L$157,'Selections & Orders'!$D$8:$D$157,B29)) | H29: =IF(B29="","",SUMIFS('Change Orders'!$J$7:$J$106,'Change Orders'!$F$7:$F$106,B29,'Change Orders'!$L$7:$L$106,"Approved")) | I29: =IF(B29="","",F29+G29+H29) | J29: =IF(B29="","",SUMIFS('Payments'!$L$6:$L$205,'Payments'!$P$6:$P$205,B29)) | K29: =IF(B29="","",SUMIFS('Payments'!$N$6:$N$205,'Payments'!$P$6:$P$205,B29)) | L29: =IF(B29="","",IF(OR(D29="Estimating",D29=""),MAX(C29,E29,I29,J29),MAX(I29,J29))) | M29: =IF(B29="","",C29-L29) | N29: =IF(O29="","",IF(O29=0,"🟢 On track",IF(O29=1,"🟡 Watch","🔴 Over"))) | O29: =IF(B29="","",IF(L29<=C29,0,IF(L29<=C29*(1+BudgetWarnPct),1,2))) | P29: =IF(B29="","",IF(MAX(C29,L29)>0,MAX(C29,L29)+ROW()/100000,""))
E30: =IF(B30="","",IFERROR(1/SUMPRODUCT(MAX((QBlockCat=B30)*QBlockInv)),"")) | F30: =IF(B30="","",SUMIFS('Contractors'!$I$6:$I$35,'Contractors'!$D$6:$D$35,B30,'Contractors'!$L$6:$L$35,"Yes")) | G30: =IF(B30="","",SUMIFS('Selections & Orders'!$L$8:$L$157,'Selections & Orders'!$D$8:$D$157,B30)) | H30: =IF(B30="","",SUMIFS('Change Orders'!$J$7:$J$106,'Change Orders'!$F$7:$F$106,B30,'Change Orders'!$L$7:$L$106,"Approved")) | I30: =IF(B30="","",F30+G30+H30) | J30: =IF(B30="","",SUMIFS('Payments'!$L$6:$L$205,'Payments'!$P$6:$P$205,B30)) | K30: =IF(B30="","",SUMIFS('Payments'!$N$6:$N$205,'Payments'!$P$6:$P$205,B30)) | L30: =IF(B30="","",IF(OR(D30="Estimating",D30=""),MAX(C30,E30,I30,J30),MAX(I30,J30))) | M30: =IF(B30="","",C30-L30) | N30: =IF(O30="","",IF(O30=0,"🟢 On track",IF(O30=1,"🟡 Watch","🔴 Over"))) | O30: =IF(B30="","",IF(L30<=C30,0,IF(L30<=C30*(1+BudgetWarnPct),1,2))) | P30: =IF(B30="","",IF(MAX(C30,L30)>0,MAX(C30,L30)+ROW()/100000,""))
E31: =IF(B31="","",IFERROR(1/SUMPRODUCT(MAX((QBlockCat=B31)*QBlockInv)),"")) | F31: =IF(B31="","",SUMIFS('Contractors'!$I$6:$I$35,'Contractors'!$D$6:$D$35,B31,'Contractors'!$L$6:$L$35,"Yes")) | G31: =IF(B31="","",SUMIFS('Selections & Orders'!$L$8:$L$157,'Selections & Orders'!$D$8:$D$157,B31)) | H31: =IF(B31="","",SUMIFS('Change Orders'!$J$7:$J$106,'Change Orders'!$F$7:$F$106,B31,'Change Orders'!$L$7:$L$106,"Approved")) | I31: =IF(B31="","",F31+G31+H31) | J31: =IF(B31="","",SUMIFS('Payments'!$L$6:$L$205,'Payments'!$P$6:$P$205,B31)) | K31: =IF(B31="","",SUMIFS('Payments'!$N$6:$N$205,'Payments'!$P$6:$P$205,B31)) | L31: =IF(B31="","",IF(OR(D31="Estimating",D31=""),MAX(C31,E31,I31,J31),MAX(I31,J31))) | M31: =IF(B31="","",C31-L31) | N31: =IF(O31="","",IF(O31=0,"🟢 On track",IF(O31=1,"🟡 Watch","🔴 Over"))) | O31: =IF(B31="","",IF(L31<=C31,0,IF(L31<=C31*(1+BudgetWarnPct),1,2))) | P31: =IF(B31="","",IF(MAX(C31,L31)>0,MAX(C31,L31)+ROW()/100000,""))
E32: =IF(B32="","",IFERROR(1/SUMPRODUCT(MAX((QBlockCat=B32)*QBlockInv)),"")) | F32: =IF(B32="","",SUMIFS('Contractors'!$I$6:$I$35,'Contractors'!$D$6:$D$35,B32,'Contractors'!$L$6:$L$35,"Yes")) | G32: =IF(B32="","",SUMIFS('Selections & Orders'!$L$8:$L$157,'Selections & Orders'!$D$8:$D$157,B32)) | H32: =IF(B32="","",SUMIFS('Change Orders'!$J$7:$J$106,'Change Orders'!$F$7:$F$106,B32,'Change Orders'!$L$7:$L$106,"Approved")) | I32: =IF(B32="","",F32+G32+H32) | J32: =IF(B32="","",SUMIFS('Payments'!$L$6:$L$205,'Payments'!$P$6:$P$205,B32)) | K32: =IF(B32="","",SUMIFS('Payments'!$N$6:$N$205,'Payments'!$P$6:$P$205,B32)) | L32: =IF(B32="","",IF(OR(D32="Estimating",D32=""),MAX(C32,E32,I32,J32),MAX(I32,J32))) | M32: =IF(B32="","",C32-L32) | N32: =IF(O32="","",IF(O32=0,"🟢 On track",IF(O32=1,"🟡 Watch","🔴 Over"))) | O32: =IF(B32="","",IF(L32<=C32,0,IF(L32<=C32*(1+BudgetWarnPct),1,2))) | P32: =IF(B32="","",IF(MAX(C32,L32)>0,MAX(C32,L32)+ROW()/100000,""))
E33: =IF(B33="","",IFERROR(1/SUMPRODUCT(MAX((QBlockCat=B33)*QBlockInv)),"")) | F33: =IF(B33="","",SUMIFS('Contractors'!$I$6:$I$35,'Contractors'!$D$6:$D$35,B33,'Contractors'!$L$6:$L$35,"Yes")) | G33: =IF(B33="","",SUMIFS('Selections & Orders'!$L$8:$L$157,'Selections & Orders'!$D$8:$D$157,B33)) | H33: =IF(B33="","",SUMIFS('Change Orders'!$J$7:$J$106,'Change Orders'!$F$7:$F$106,B33,'Change Orders'!$L$7:$L$106,"Approved")) | I33: =IF(B33="","",F33+G33+H33) | J33: =IF(B33="","",SUMIFS('Payments'!$L$6:$L$205,'Payments'!$P$6:$P$205,B33)) | K33: =IF(B33="","",SUMIFS('Payments'!$N$6:$N$205,'Payments'!$P$6:$P$205,B33)) | L33: =IF(B33="","",IF(OR(D33="Estimating",D33=""),MAX(C33,E33,I33,J33),MAX(I33,J33))) | M33: =IF(B33="","",C33-L33) | N33: =IF(O33="","",IF(O33=0,"🟢 On track",IF(O33=1,"🟡 Watch","🔴 Over"))) | O33: =IF(B33="","",IF(L33<=C33,0,IF(L33<=C33*(1+BudgetWarnPct),1,2))) | P33: =IF(B33="","",IF(MAX(C33,L33)>0,MAX(C33,L33)+ROW()/100000,""))
E34: =IF(B34="","",IFERROR(1/SUMPRODUCT(MAX((QBlockCat=B34)*QBlockInv)),"")) | F34: =IF(B34="","",SUMIFS('Contractors'!$I$6:$I$35,'Contractors'!$D$6:$D$35,B34,'Contractors'!$L$6:$L$35,"Yes")) | G34: =IF(B34="","",SUMIFS('Selections & Orders'!$L$8:$L$157,'Selections & Orders'!$D$8:$D$157,B34)) | H34: =IF(B34="","",SUMIFS('Change Orders'!$J$7:$J$106,'Change Orders'!$F$7:$F$106,B34,'Change Orders'!$L$7:$L$106,"Approved")) | I34: =IF(B34="","",F34+G34+H34) | J34: =IF(B34="","",SUMIFS('Payments'!$L$6:$L$205,'Payments'!$P$6:$P$205,B34)) | K34: =IF(B34="","",SUMIFS('Payments'!$N$6:$N$205,'Payments'!$P$6:$P$205,B34)) | L34: =IF(B34="","",IF(OR(D34="Estimating",D34=""),MAX(C34,E34,I34,J34),MAX(I34,J34))) | M34: =IF(B34="","",C34-L34) | N34: =IF(O34="","",IF(O34=0,"🟢 On track",IF(O34=1,"🟡 Watch","🔴 Over"))) | O34: =IF(B34="","",IF(L34<=C34,0,IF(L34<=C34*(1+BudgetWarnPct),1,2))) | P34: =IF(B34="","",IF(MAX(C34,L34)>0,MAX(C34,L34)+ROW()/100000,""))
E35: =IF(B35="","",IFERROR(1/SUMPRODUCT(MAX((QBlockCat=B35)*QBlockInv)),"")) | F35: =IF(B35="","",SUMIFS('Contractors'!$I$6:$I$35,'Contractors'!$D$6:$D$35,B35,'Contractors'!$L$6:$L$35,"Yes")) | G35: =IF(B35="","",SUMIFS('Selections & Orders'!$L$8:$L$157,'Selections & Orders'!$D$8:$D$157,B35)) | H35: =IF(B35="","",SUMIFS('Change Orders'!$J$7:$J$106,'Change Orders'!$F$7:$F$106,B35,'Change Orders'!$L$7:$L$106,"Approved")) | I35: =IF(B35="","",F35+G35+H35) | J35: =IF(B35="","",SUMIFS('Payments'!$L$6:$L$205,'Payments'!$P$6:$P$205,B35)) | K35: =IF(B35="","",SUMIFS('Payments'!$N$6:$N$205,'Payments'!$P$6:$P$205,B35)) | L35: =IF(B35="","",IF(OR(D35="Estimating",D35=""),MAX(C35,E35,I35,J35),MAX(I35,J35))) | M35: =IF(B35="","",C35-L35) | N35: =IF(O35="","",IF(O35=0,"🟢 On track",IF(O35=1,"🟡 Watch","🔴 Over"))) | O35: =IF(B35="","",IF(L35<=C35,0,IF(L35<=C35*(1+BudgetWarnPct),1,2))) | P35: =IF(B35="","",IF(MAX(C35,L35)>0,MAX(C35,L35)+ROW()/100000,""))
E36: =IF(B36="","",IFERROR(1/SUMPRODUCT(MAX((QBlockCat=B36)*QBlockInv)),"")) | F36: =IF(B36="","",SUMIFS('Contractors'!$I$6:$I$35,'Contractors'!$D$6:$D$35,B36,'Contractors'!$L$6:$L$35,"Yes")) | G36: =IF(B36="","",SUMIFS('Selections & Orders'!$L$8:$L$157,'Selections & Orders'!$D$8:$D$157,B36)) | H36: =IF(B36="","",SUMIFS('Change Orders'!$J$7:$J$106,'Change Orders'!$F$7:$F$106,B36,'Change Orders'!$L$7:$L$106,"Approved")) | I36: =IF(B36="","",F36+G36+H36) | J36: =IF(B36="","",SUMIFS('Payments'!$L$6:$L$205,'Payments'!$P$6:$P$205,B36)) | K36: =IF(B36="","",SUMIFS('Payments'!$N$6:$N$205,'Payments'!$P$6:$P$205,B36)) | L36: =IF(B36="","",IF(OR(D36="Estimating",D36=""),MAX(C36,E36,I36,J36),MAX(I36,J36))) | M36: =IF(B36="","",C36-L36) | N36: =IF(O36="","",IF(O36=0,"🟢 On track",IF(O36=1,"🟡 Watch","🔴 Over"))) | O36: =IF(B36="","",IF(L36<=C36,0,IF(L36<=C36*(1+BudgetWarnPct),1,2))) | P36: =IF(B36="","",IF(MAX(C36,L36)>0,MAX(C36,L36)+ROW()/100000,""))
E37: =IF(B37="","",IFERROR(1/SUMPRODUCT(MAX((QBlockCat=B37)*QBlockInv)),"")) | F37: =IF(B37="","",SUMIFS('Contractors'!$I$6:$I$35,'Contractors'!$D$6:$D$35,B37,'Contractors'!$L$6:$L$35,"Yes")) | G37: =IF(B37="","",SUMIFS('Selections & Orders'!$L$8:$L$157,'Selections & Orders'!$D$8:$D$157,B37)) | H37: =IF(B37="","",SUMIFS('Change Orders'!$J$7:$J$106,'Change Orders'!$F$7:$F$106,B37,'Change Orders'!$L$7:$L$106,"Approved")) | I37: =IF(B37="","",F37+G37+H37) | J37: =IF(B37="","",SUMIFS('Payments'!$L$6:$L$205,'Payments'!$P$6:$P$205,B37)) | K37: =IF(B37="","",SUMIFS('Payments'!$N$6:$N$205,'Payments'!$P$6:$P$205,B37)) | L37: =IF(B37="","",IF(OR(D37="Estimating",D37=""),MAX(C37,E37,I37,J37),MAX(I37,J37))) | M37: =IF(B37="","",C37-L37) | N37: =IF(O37="","",IF(O37=0,"🟢 On track",IF(O37=1,"🟡 Watch","🔴 Over"))) | O37: =IF(B37="","",IF(L37<=C37,0,IF(L37<=C37*(1+BudgetWarnPct),1,2))) | P37: =IF(B37="","",IF(MAX(C37,L37)>0,MAX(C37,L37)+ROW()/100000,""))
B38: TOTAL | C38: =SUM(C8:C37) | F38: =SUM(F8:F37) | G38: =SUM(G8:G37) | H38: =SUM(H8:H37) | I38: =SUM(I8:I37) | J38: =SUM(J8:J37) | K38: =SUM(K8:K37) | L38: =SUM(L8:L37) | M38: =SUM(M8:M37) | N38: =IF(O38=0,"🟢 On track",IF(O38=1,"🟡 Watch","🔴 Over")) | O38: =IF(L38<=C38,0,IF(L38<=C38*(1+BudgetWarnPct),1,2))
B39: RISK — what could still come on top of the forecast
B40: Pending change orders (not approved yet) | L40: =SUMIFS('Change Orders'!$J$7:$J$106,'Change Orders'!$L$7:$L$106,"Pending") | Q40: =IF(AND(WorkBudget>0,ForecastTotal>WorkBudget),AsOf,"") | R40: =IF(Q40="","",1) | S40: =IF(R40="","","Forecast is over your working budget by "&CurSym&" "&FIXED(ForecastTotal-WorkBudget,0)&" — review Budget")
B41: Estimated cost of open issues | L41: =SUM('Issues & Punch List'!$T$8:$T$207) | Q41: =IF(ContUsed>0.75,AsOf,"") | R41: =IF(Q41="","",1) | S41: =IF(R41="","","Contingency "&ROUND(ContUsed*100,0)&"% used — pause optional changes")
B42: RISK (could still be added) | L42: =L40+L41
B43: FORECAST INCL. RISK | L43: =ForecastTotal+L42
B44: Contingency used by forecast | L44: =IF(ContAmt>0,MAX(0,ForecastTotal-WorkBudget)/ContAmt,0) | M44: =REPT("█",ROUND(MIN(1,ContUsed)*10,0))&REPT("░",10-ROUND(MIN(1,ContUsed)*10,0))

Sheet Quotes
B1: ⚖️ Quotes
B2: What this tab does: compares up to 4 contractors per trade side by side and reveals the TRUE cost once hidden extras are added.
B3: © 2026 Hang Nguyen — Renovation OS. Licensed to the original purchaser for personal use only. Do not share, copy, resell or redistribute.
B4: SCORING WEIGHTS (points, should total 100)
C5: Price | D5: Timeline | E5: Warranty | F5: Checklist | G5: Gut & refs | H5: Total
B6: Cheapest TRUE cost, shortest timeline and longest warranty get full points; others get proportional points. | C6: 40 | D6: 20 | E6: 15 | F6: 15 | G6: 10 | H6: =SUM(C6:G6)
B7: Tip: type prices exactly as quoted. Yellow checklist cells: estimate what a missing item will cost you — it is added to the TRUE COST.
M8: block cat | N8: best true | O8: 1/best | P8: warn | T8: expiry due | U8: pri | V8: text
B9: COMPARISON 1 ▸ trade: | C9: Kitchen | E9: =IF(COUNT($C$43:$J$43)=0,"Enter up to 4 quotes below","🏆 Best overall: "&INDEX($C$11:$J$11,MATCH(MAX($C$43:$J$43),$C$43:$J$43,0))&" — true cost "&CurSym&" "&FIXED(INDEX($C$35:$J$35,MATCH(MAX($C$43:$J$43),$C$43:$J$43,0)),0)) | M9: =IF(C9="","",C9) | N9: =IF(OR(M9="",COUNT($C35:$J35)=0),"",MIN($C35:$J35)) | O9: =IF(N9="",0,IF(N9>0,1/N9,0)) | T9: =IF(OR(C11="",C19=""),"",IF(OR(IFERROR(INDEX('Budget'!$D$8:$D$37,MATCH($C$9,'Budget'!$B$8:$B$37,0)),"")="Contracted",IFERROR(INDEX('Budget'!$D$8:$D$37,MATCH($C$9,'Budget'!$B$8:$B$37,0)),"")="Complete"),"",IF(C19<AsOf,"",C19))) | U9: =IF(T9="","",IF(T9<AsOf,1,IF(T9<=AsOf+AlertDays,2,IF(T9<=AsOf+2*AlertDays,3,"")))) | V9: =IF(U9="","","Quote expires: "&C11&IF($C$9="",""," ("&$C$9&")")&" — decide or ask for an extension")
C10: Contractor 1 | E10: Contractor 2 | G10: Contractor 3 | I10: Contractor 4 | M10: =IF(C48="","",C48) | N10: =IF(OR(M10="",COUNT($C74:$J74)=0),"",MIN($C74:$J74)) | O10: =IF(N10="",0,IF(N10>0,1/N10,0)) | T10: =IF(OR(E11="",E19=""),"",IF(OR(IFERROR(INDEX('Budget'!$D$8:$D$37,MATCH($C$9,'Budget'!$B$8:$B$37,0)),"")="Contracted",IFERROR(INDEX('Budget'!$D$8:$D$37,MATCH($C$9,'Budget'!$B$8:$B$37,0)),"")="Complete"),"",IF(E19<AsOf,"",E19))) | U10: =IF(T10="","",IF(T10<AsOf,1,IF(T10<=AsOf+AlertDays,2,IF(T10<=AsOf+2*AlertDays,3,"")))) | V10: =IF(U10="","","Quote expires: "&E11&IF($C$9="",""," ("&$C$9&")")&" — decide or ask for an extension")
B11: Contractor / company | C11: BudgetKitchen Co | E11: Nordic Kitchens | G11: Kitchen World | M11: =IF(C87="","",C87) | N11: =IF(OR(M11="",COUNT($C113:$J113)=0),"",MIN($C113:$J113)) | O11: =IF(N11="",0,IF(N11>0,1/N11,0)) | T11: =IF(OR(G11="",G19=""),"",IF(OR(IFERROR(INDEX('Budget'!$D$8:$D$37,MATCH($C$9,'Budget'!$B$8:$B$37,0)),"")="Contracted",IFERROR(INDEX('Budget'!$D$8:$D$37,MATCH($C$9,'Budget'!$B$8:$B$37,0)),"")="Complete"),"",IF(G19<AsOf,"",G19))) | U11: =IF(T11="","",IF(T11<AsOf,1,IF(T11<=AsOf+AlertDays,2,IF(T11<=AsOf+2*AlertDays,3,"")))) | V11: =IF(U11="","","Quote expires: "&G11&IF($C$9="",""," ("&$C$9&")")&" — decide or ask for an extension")
B12: ="Quoted price ("&CurSym&")" | C12: 16900 | E12: 19400 | G12: 18200 | M12: =IF(C126="","",C126) | N12: =IF(OR(M12="",COUNT($C152:$J152)=0),"",MIN($C152:$J152)) | O12: =IF(N12="",0,IF(N12>0,1/N12,0)) | T12: =IF(OR(I11="",I19=""),"",IF(OR(IFERROR(INDEX('Budget'!$D$8:$D$37,MATCH($C$9,'Budget'!$B$8:$B$37,0)),"")="Contracted",IFERROR(INDEX('Budget'!$D$8:$D$37,MATCH($C$9,'Budget'!$B$8:$B$37,0)),"")="Complete"),"",IF(I19<AsOf,"",I19))) | U12: =IF(T12="","",IF(T12<AsOf,1,IF(T12<=AsOf+AlertDays,2,IF(T12<=AsOf+2*AlertDays,3,"")))) | V12: =IF(U12="","","Quote expires: "&I11&IF($C$9="",""," ("&$C$9&")")&" — decide or ask for an extension")
B13: ="Price includes "&TaxWord&"?" | C13: Yes | E13: Yes | G13: No | I13: =DefInclTax | M13: =IF(C165="","",C165) | N13: =IF(OR(M13="",COUNT($C191:$J191)=0),"",MIN($C191:$J191)) | O13: =IF(N13="",0,IF(N13>0,1/N13,0)) | T13: =IF(OR(C50="",C58=""),"",IF(OR(IFERROR(INDEX('Budget'!$D$8:$D$37,MATCH($C$48,'Budget'!$B$8:$B$37,0)),"")="Contracted",IFERROR(INDEX('Budget'!$D$8:$D$37,MATCH($C$48,'Budget'!$B$8:$B$37,0)),"")="Complete"),"",IF(C58<AsOf,"",C58))) | U13: =IF(T13="","",IF(T13<AsOf,1,IF(T13<=AsOf+AlertDays,2,IF(T13<=AsOf+2*AlertDays,3,"")))) | V13: =IF(U13="","","Quote expires: "&C50&IF($C$48="",""," ("&$C$48&")")&" — decide or ask for an extension")
B14: ="Price incl. "&TaxWord&" ("&CurSym&")" | C14: =IF(C12="","",IF(C13="No",C12*(1+VatRate),C12)) | E14: =IF(E12="","",IF(E13="No",E12*(1+VatRate),E12)) | G14: =IF(G12="","",IF(G13="No",G12*(1+VatRate),G12)) | I14: =IF(I12="","",IF(I13="No",I12*(1+VatRate),I12)) | M14: =IF(C204="","",C204) | N14: =IF(OR(M14="",COUNT($C230:$J230)=0),"",MIN($C230:$J230)) | O14: =IF(N14="",0,IF(N14>0,1/N14,0)) | T14: =IF(OR(E50="",E58=""),"",IF(OR(IFERROR(INDEX('Budget'!$D$8:$D$37,MATCH($C$48,'Budget'!$B$8:$B$37,0)),"")="Contracted",IFERROR(INDEX('Budget'!$D$8:$D$37,MATCH($C$48,'Budget'!$B$8:$B$37,0)),"")="Complete"),"",IF(E58<AsOf,"",E58))) | U14: =IF(T14="","",IF(T14<AsOf,1,IF(T14<=AsOf+AlertDays,2,IF(T14<=AsOf+2*AlertDays,3,"")))) | V14: =IF(U14="","","Quote expires: "&E50&IF($C$48="",""," ("&$C$48&")")&" — decide or ask for an extension")
B15: Timeline (weeks) | C15: 3 | E15: 2 | G15: 4 | M15: =IF(C243="","",C243) | N15: =IF(OR(M15="",COUNT($C269:$J269)=0),"",MIN($C269:$J269)) | O15: =IF(N15="",0,IF(N15>0,1/N15,0)) | T15: =IF(OR(G50="",G58=""),"",IF(OR(IFERROR(INDEX('Budget'!$D$8:$D$37,MATCH($C$48,'Budget'!$B$8:$B$37,0)),"")="Contracted",IFERROR(INDEX('Budget'!$D$8:$D$37,MATCH($C$48,'Budget'!$B$8:$B$37,0)),"")="Complete"),"",IF(G58<AsOf,"",G58))) | U15: =IF(T15="","",IF(T15<AsOf,1,IF(T15<=AsOf+AlertDays,2,IF(T15<=AsOf+2*AlertDays,3,"")))) | V15: =IF(U15="","","Quote expires: "&G50&IF($C$48="",""," ("&$C$48&")")&" — decide or ask for an extension")
B16: Warranty (years) | C16: 2 | E16: 5 | G16: 3 | M16: =IF(C282="","",C282) | N16: =IF(OR(M16="",COUNT($C308:$J308)=0),"",MIN($C308:$J308)) | O16: =IF(N16="",0,IF(N16>0,1/N16,0)) | T16: =IF(OR(I50="",I58=""),"",IF(OR(IFERROR(INDEX('Budget'!$D$8:$D$37,MATCH($C$48,'Budget'!$B$8:$B$37,0)),"")="Contracted",IFERROR(INDEX('Budget'!$D$8:$D$37,MATCH($C$48,'Budget'!$B$8:$B$37,0)),"")="Complete"),"",IF(I58<AsOf,"",I58))) | U16: =IF(T16="","",IF(T16<AsOf,1,IF(T16<=AsOf+AlertDays,2,IF(T16<=AsOf+2*AlertDays,3,"")))) | V16: =IF(U16="","","Quote expires: "&I50&IF($C$48="",""," ("&$C$48&")")&" — decide or ask for an extension")
B17: References checked? | C17: No | E17: Yes | G17: Yes | M17: =IF(C321="","",C321) | N17: =IF(OR(M17="",COUNT($C347:$J347)=0),"",MIN($C347:$J347)) | O17: =IF(N17="",0,IF(N17>0,1/N17,0)) | T17: =IF(OR(C89="",C97=""),"",IF(OR(IFERROR(INDEX('Budget'!$D$8:$D$37,MATCH($C$87,'Budget'!$B$8:$B$37,0)),"")="Contracted",IFERROR(INDEX('Budget'!$D$8:$D$37,MATCH($C$87,'Budget'!$B$8:$B$37,0)),"")="Complete"),"",IF(C97<AsOf,"",C97))) | U17: =IF(T17="","",IF(T17<AsOf,1,IF(T17<=AsOf+AlertDays,2,IF(T17<=AsOf+2*AlertDays,3,"")))) | V17: =IF(U17="","","Quote expires: "&C89&IF($C$87="",""," ("&$C$87&")")&" — decide or ask for an extension")
B18: Gut feeling (1–5) | C18: 2 | E18: 5 | G18: 3 | M18: =IF(C360="","",C360) | N18: =IF(OR(M18="",COUNT($C386:$J386)=0),"",MIN($C386:$J386)) | O18: =IF(N18="",0,IF(N18>0,1/N18,0)) | T18: =IF(OR(E89="",E97=""),"",IF(OR(IFERROR(INDEX('Budget'!$D$8:$D$37,MATCH($C$87,'Budget'!$B$8:$B$37,0)),"")="Contracted",IFERROR(INDEX('Budget'!$D$8:$D$37,MATCH($C$87,'Budget'!$B$8:$B$37,0)),"")="Complete"),"",IF(E97<AsOf,"",E97))) | U18: =IF(T18="","",IF(T18<AsOf,1,IF(T18<=AsOf+AlertDays,2,IF(T18<=AsOf+2*AlertDays,3,"")))) | V18: =IF(U18="","","Quote expires: "&E89&IF($C$87="",""," ("&$C$87&")")&" — decide or ask for an extension")
B19: Quote valid until | C19: 46157 | E19: 46162 | G19: 46172 | T19: =IF(OR(G89="",G97=""),"",IF(OR(IFERROR(INDEX('Budget'!$D$8:$D$37,MATCH($C$87,'Budget'!$B$8:$B$37,0)),"")="Contracted",IFERROR(INDEX('Budget'!$D$8:$D$37,MATCH($C$87,'Budget'!$B$8:$B$37,0)),"")="Complete"),"",IF(G97<AsOf,"",G97))) | U19: =IF(T19="","",IF(T19<AsOf,1,IF(T19<=AsOf+AlertDays,2,IF(T19<=AsOf+2*AlertDays,3,"")))) | V19: =IF(U19="","","Quote expires: "&G89&IF($C$87="",""," ("&$C$87&")")&" — decide or ask for an extension")
B20: HIDDEN-COST CHECKLIST | C20: Included? | D20: ="Extra "&CurSym | E20: Included? | F20: ="Extra "&CurSym | G20: Included? | H20: ="Extra "&CurSym | I20: Included? | J20: ="Extra "&CurSym | T20: =IF(OR(I89="",I97=""),"",IF(OR(IFERROR(INDEX('Budget'!$D$8:$D$37,MATCH($C$87,'Budget'!$B$8:$B$37,0)),"")="Contracted",IFERROR(INDEX('Budget'!$D$8:$D$37,MATCH($C$87,'Budget'!$B$8:$B$37,0)),"")="Complete"),"",IF(I97<AsOf,"",I97))) | U20: =IF(T20="","",IF(T20<AsOf,1,IF(T20<=AsOf+AlertDays,2,IF(T20<=AsOf+2*AlertDays,3,"")))) | V20: =IF(U20="","","Quote expires: "&I89&IF($C$87="",""," ("&$C$87&")")&" — decide or ask for an extension")
B21: Demolition | C21: Not included | D21: 600 | E21: Included | G21: Included | T21: =IF(OR(C128="",C136=""),"",IF(OR(IFERROR(INDEX('Budget'!$D$8:$D$37,MATCH($C$126,'Budget'!$B$8:$B$37,0)),"")="Contracted",IFERROR(INDEX('Budget'!$D$8:$D$37,MATCH($C$126,'Budget'!$B$8:$B$37,0)),"")="Complete"),"",IF(C136<AsOf,"",C136))) | U21: =IF(T21="","",IF(T21<AsOf,1,IF(T21<=AsOf+AlertDays,2,IF(T21<=AsOf+2*AlertDays,3,"")))) | V21: =IF(U21="","","Quote expires: "&C128&IF($C$126="",""," ("&$C$126&")")&" — decide or ask for an extension")
B22: Waste disposal | C22: Not included | D22: 350 | E22: Included | G22: Included | T22: =IF(OR(E128="",E136=""),"",IF(OR(IFERROR(INDEX('Budget'!$D$8:$D$37,MATCH($C$126,'Budget'!$B$8:$B$37,0)),"")="Contracted",IFERROR(INDEX('Budget'!$D$8:$D$37,MATCH($C$126,'Budget'!$B$8:$B$37,0)),"")="Complete"),"",IF(E136<AsOf,"",E136))) | U22: =IF(T22="","",IF(T22<AsOf,1,IF(T22<=AsOf+AlertDays,2,IF(T22<=AsOf+2*AlertDays,3,"")))) | V22: =IF(U22="","","Quote expires: "&E128&IF($C$126="",""," ("&$C$126&")")&" — decide or ask for an extension")
B23: Delivery | C23: Not included | D23: 450 | E23: Included | G23: Included | T23: =IF(OR(G128="",G136=""),"",IF(OR(IFERROR(INDEX('Budget'!$D$8:$D$37,MATCH($C$126,'Budget'!$B$8:$B$37,0)),"")="Contracted",IFERROR(INDEX('Budget'!$D$8:$D$37,MATCH($C$126,'Budget'!$B$8:$B$37,0)),"")="Complete"),"",IF(G136<AsOf,"",G136))) | U23: =IF(T23="","",IF(T23<AsOf,1,IF(T23<=AsOf+AlertDays,2,IF(T23<=AsOf+2*AlertDays,3,"")))) | V23: =IF(U23="","","Quote expires: "&G128&IF($C$126="",""," ("&$C$126&")")&" — decide or ask for an extension")
B24: Permits | C24: Included | E24: Included | G24: Included | T24: =IF(OR(I128="",I136=""),"",IF(OR(IFERROR(INDEX('Budget'!$D$8:$D$37,MATCH($C$126,'Budget'!$B$8:$B$37,0)),"")="Contracted",IFERROR(INDEX('Budget'!$D$8:$D$37,MATCH($C$126,'Budget'!$B$8:$B$37,0)),"")="Complete"),"",IF(I136<AsOf,"",I136))) | U24: =IF(T24="","",IF(T24<AsOf,1,IF(T24<=AsOf+AlertDays,2,IF(T24<=AsOf+2*AlertDays,3,"")))) | V24: =IF(U24="","","Quote expires: "&I128&IF($C$126="",""," ("&$C$126&")")&" — decide or ask for an extension")
B25: Materials specified | C25: Included | E25: Included | G25: Included | T25: =IF(OR(C167="",C175=""),"",IF(OR(IFERROR(INDEX('Budget'!$D$8:$D$37,MATCH($C$165,'Budget'!$B$8:$B$37,0)),"")="Contracted",IFERROR(INDEX('Budget'!$D$8:$D$37,MATCH($C$165,'Budget'!$B$8:$B$37,0)),"")="Complete"),"",IF(C175<AsOf,"",C175))) | U25: =IF(T25="","",IF(T25<AsOf,1,IF(T25<=AsOf+AlertDays,2,IF(T25<=AsOf+2*AlertDays,3,"")))) | V25: =IF(U25="","","Quote expires: "&C167&IF($C$165="",""," ("&$C$165&")")&" — decide or ask for an extension")
B26: Labor specified | C26: Included | E26: Included | G26: Included | T26: =IF(OR(E167="",E175=""),"",IF(OR(IFERROR(INDEX('Budget'!$D$8:$D$37,MATCH($C$165,'Budget'!$B$8:$B$37,0)),"")="Contracted",IFERROR(INDEX('Budget'!$D$8:$D$37,MATCH($C$165,'Budget'!$B$8:$B$37,0)),"")="Complete"),"",IF(E175<AsOf,"",E175))) | U26: =IF(T26="","",IF(T26<AsOf,1,IF(T26<=AsOf+AlertDays,2,IF(T26<=AsOf+2*AlertDays,3,"")))) | V26: =IF(U26="","","Quote expires: "&E167&IF($C$165="",""," ("&$C$165&")")&" — decide or ask for an extension")
B27: Finishing | C27: Unclear | D27: 800 | E27: Included | G27: Included | T27: =IF(OR(G167="",G175=""),"",IF(OR(IFERROR(INDEX('Budget'!$D$8:$D$37,MATCH($C$165,'Budget'!$B$8:$B$37,0)),"")="Contracted",IFERROR(INDEX('Budget'!$D$8:$D$37,MATCH($C$165,'Budget'!$B$8:$B$37,0)),"")="Complete"),"",IF(G175<AsOf,"",G175))) | U27: =IF(T27="","",IF(T27<AsOf,1,IF(T27<=AsOf+AlertDays,2,IF(T27<=AsOf+2*AlertDays,3,"")))) | V27: =IF(U27="","","Quote expires: "&G167&IF($C$165="",""," ("&$C$165&")")&" — decide or ask for an extension")
B28: Cleanup | C28: Not included | D28: 200 | E28: Included | G28: Unclear | H28: 150 | T28: =IF(OR(I167="",I175=""),"",IF(OR(IFERROR(INDEX('Budget'!$D$8:$D$37,MATCH($C$165,'Budget'!$B$8:$B$37,0)),"")="Contracted",IFERROR(INDEX('Budget'!$D$8:$D$37,MATCH($C$165,'Budget'!$B$8:$B$37,0)),"")="Complete"),"",IF(I175<AsOf,"",I175))) | U28: =IF(T28="","",IF(T28<AsOf,1,IF(T28<=AsOf+AlertDays,2,IF(T28<=AsOf+2*AlertDays,3,"")))) | V28: =IF(U28="","","Quote expires: "&I167&IF($C$165="",""," ("&$C$165&")")&" — decide or ask for an extension")
B29: =TaxWord&" shown in price" | C29: Included | E29: Included | G29: Included | T29: =IF(OR(C206="",C214=""),"",IF(OR(IFERROR(INDEX('Budget'!$D$8:$D$37,MATCH($C$204,'Budget'!$B$8:$B$37,0)),"")="Contracted",IFERROR(INDEX('Budget'!$D$8:$D$37,MATCH($C$204,'Budget'!$B$8:$B$37,0)),"")="Complete"),"",IF(C214<AsOf,"",C214))) | U29: =IF(T29="","",IF(T29<AsOf,1,IF(T29<=AsOf+AlertDays,2,IF(T29<=AsOf+2*AlertDays,3,"")))) | V29: =IF(U29="","","Quote expires: "&C206&IF($C$204="",""," ("&$C$204&")")&" — decide or ask for an extension")
B30: Electrical upgrades | C30: Not included | D30: 900 | E30: Included | G30: Unclear | H30: 400 | T30: =IF(OR(E206="",E214=""),"",IF(OR(IFERROR(INDEX('Budget'!$D$8:$D$37,MATCH($C$204,'Budget'!$B$8:$B$37,0)),"")="Contracted",IFERROR(INDEX('Budget'!$D$8:$D$37,MATCH($C$204,'Budget'!$B$8:$B$37,0)),"")="Complete"),"",IF(E214<AsOf,"",E214))) | U30: =IF(T30="","",IF(T30<AsOf,1,IF(T30<=AsOf+AlertDays,2,IF(T30<=AsOf+2*AlertDays,3,"")))) | V30: =IF(U30="","","Quote expires: "&E206&IF($C$204="",""," ("&$C$204&")")&" — decide or ask for an extension")
B31: Plumbing modifications | C31: Not included | D31: 700 | E31: Included | G31: Included | T31: =IF(OR(G206="",G214=""),"",IF(OR(IFERROR(INDEX('Budget'!$D$8:$D$37,MATCH($C$204,'Budget'!$B$8:$B$37,0)),"")="Contracted",IFERROR(INDEX('Budget'!$D$8:$D$37,MATCH($C$204,'Budget'!$B$8:$B$37,0)),"")="Complete"),"",IF(G214<AsOf,"",G214))) | U31: =IF(T31="","",IF(T31<AsOf,1,IF(T31<=AsOf+AlertDays,2,IF(T31<=AsOf+2*AlertDays,3,"")))) | V31: =IF(U31="","","Quote expires: "&G206&IF($C$204="",""," ("&$C$204&")")&" — decide or ask for an extension")
B32: Payment schedule defined | C32: Unclear | D32: 0 | E32: Included | G32: Included | T32: =IF(OR(I206="",I214=""),"",IF(OR(IFERROR(INDEX('Budget'!$D$8:$D$37,MATCH($C$204,'Budget'!$B$8:$B$37,0)),"")="Contracted",IFERROR(INDEX('Budget'!$D$8:$D$37,MATCH($C$204,'Budget'!$B$8:$B$37,0)),"")="Complete"),"",IF(I214<AsOf,"",I214))) | U32: =IF(T32="","",IF(T32<AsOf,1,IF(T32<=AsOf+AlertDays,2,IF(T32<=AsOf+2*AlertDays,3,"")))) | V32: =IF(U32="","","Quote expires: "&I206&IF($C$204="",""," ("&$C$204&")")&" — decide or ask for an extension")
B33: Warranty in writing | C33: Included | E33: Included | G33: Included | T33: =IF(OR(C245="",C253=""),"",IF(OR(IFERROR(INDEX('Budget'!$D$8:$D$37,MATCH($C$243,'Budget'!$B$8:$B$37,0)),"")="Contracted",IFERROR(INDEX('Budget'!$D$8:$D$37,MATCH($C$243,'Budget'!$B$8:$B$37,0)),"")="Complete"),"",IF(C253<AsOf,"",C253))) | U33: =IF(T33="","",IF(T33<AsOf,1,IF(T33<=AsOf+AlertDays,2,IF(T33<=AsOf+2*AlertDays,3,"")))) | V33: =IF(U33="","","Quote expires: "&C245&IF($C$243="",""," ("&$C$243&")")&" — decide or ask for an extension")
B34: ="Hidden extras ("&CurSym&")" | C34: =IF(C11="","",SUMPRODUCT((C21:C33<>"Included")*D21:D33)) | E34: =IF(E11="","",SUMPRODUCT((E21:E33<>"Included")*F21:F33)) | G34: =IF(G11="","",SUMPRODUCT((G21:G33<>"Included")*H21:H33)) | I34: =IF(I11="","",SUMPRODUCT((I21:I33<>"Included")*J21:J33)) | T34: =IF(OR(E245="",E253=""),"",IF(OR(IFERROR(INDEX('Budget'!$D$8:$D$37,MATCH($C$243,'Budget'!$B$8:$B$37,0)),"")="Contracted",IFERROR(INDEX('Budget'!$D$8:$D$37,MATCH($C$243,'Budget'!$B$8:$B$37,0)),"")="Complete"),"",IF(E253<AsOf,"",E253))) | U34: =IF(T34="","",IF(T34<AsOf,1,IF(T34<=AsOf+AlertDays,2,IF(T34<=AsOf+2*AlertDays,3,"")))) | V34: =IF(U34="","","Quote expires: "&E245&IF($C$243="",""," ("&$C$243&")")&" — decide or ask for an extension")
B35: ="TRUE COST ("&CurSym&")" | C35: =IF(OR(C11="",C14=""),"",C14+C34) | E35: =IF(OR(E11="",E14=""),"",E14+E34) | G35: =IF(OR(G11="",G14=""),"",G14+G34) | I35: =IF(OR(I11="",I14=""),"",I14+I34) | T35: =IF(OR(G245="",G253=""),"",IF(OR(IFERROR(INDEX('Budget'!$D$8:$D$37,MATCH($C$243,'Budget'!$B$8:$B$37,0)),"")="Contracted",IFERROR(INDEX('Budget'!$D$8:$D$37,MATCH($C$243,'Budget'!$B$8:$B$37,0)),"")="Complete"),"",IF(G253<AsOf,"",G253))) | U35: =IF(T35="","",IF(T35<AsOf,1,IF(T35<=AsOf+AlertDays,2,IF(T35<=AsOf+2*AlertDays,3,"")))) | V35: =IF(U35="","","Quote expires: "&G245&IF($C$243="",""," ("&$C$243&")")&" — decide or ask for an extension")
B36: Completeness | C36: =IF(C11="","",COUNTIF(C21:C33,"Included")/13) | E36: =IF(E11="","",COUNTIF(E21:E33,"Included")/13) | G36: =IF(G11="","",COUNTIF(G21:G33,"Included")/13) | I36: =IF(I11="","",COUNTIF(I21:I33,"Included")/13) | T36: =IF(OR(I245="",I253=""),"",IF(OR(IFERROR(INDEX('Budget'!$D$8:$D$37,MATCH($C$243,'Budget'!$B$8:$B$37,0)),"")="Contracted",IFERROR(INDEX('Budget'!$D$8:$D$37,MATCH($C$243,'Budget'!$B$8:$B$37,0)),"")="Complete"),"",IF(I253<AsOf,"",I253))) | U36: =IF(T36="","",IF(T36<AsOf,1,IF(T36<=AsOf+AlertDays,2,IF(T36<=AsOf+2*AlertDays,3,"")))) | V36: =IF(U36="","","Quote expires: "&I245&IF($C$243="",""," ("&$C$243&")")&" — decide or ask for an extension")
B37: SCORE | T37: =IF(OR(C284="",C292=""),"",IF(OR(IFERROR(INDEX('Budget'!$D$8:$D$37,MATCH($C$282,'Budget'!$B$8:$B$37,0)),"")="Contracted",IFERROR(INDEX('Budget'!$D$8:$D$37,MATCH($C$282,'Budget'!$B$8:$B$37,0)),"")="Complete"),"",IF(C292<AsOf,"",C292))) | U37: =IF(T37="","",IF(T37<AsOf,1,IF(T37<=AsOf+AlertDays,2,IF(T37<=AsOf+2*AlertDays,3,"")))) | V37: =IF(U37="","","Quote expires: "&C284&IF($C$282="",""," ("&$C$282&")")&" — decide or ask for an extension")
B38: Price points | C38: =IF(C35="","",IF(C35>0,MIN($C35:$J35)/C35,0)*WPrice) | E38: =IF(E35="","",IF(E35>0,MIN($C35:$J35)/E35,0)*WPrice) | G38: =IF(G35="","",IF(G35>0,MIN($C35:$J35)/G35,0)*WPrice) | I38: =IF(I35="","",IF(I35>0,MIN($C35:$J35)/I35,0)*WPrice) | T38: =IF(OR(E284="",E292=""),"",IF(OR(IFERROR(INDEX('Budget'!$D$8:$D$37,MATCH($C$282,'Budget'!$B$8:$B$37,0)),"")="Contracted",IFERROR(INDEX('Budget'!$D$8:$D$37,MATCH($C$282,'Budget'!$B$8:$B$37,0)),"")="Complete"),"",IF(E292<AsOf,"",E292))) | U38: =IF(T38="","",IF(T38<AsOf,1,IF(T38<=AsOf+AlertDays,2,IF(T38<=AsOf+2*AlertDays,3,"")))) | V38: =IF(U38="","","Quote expires: "&E284&IF($C$282="",""," ("&$C$282&")")&" — decide or ask for an extension")
B39: Timeline points | C39: =IF(C35="","",IF(C15>0,MIN($C15:$J15)/C15,0)*WTime) | E39: =IF(E35="","",IF(E15>0,MIN($C15:$J15)/E15,0)*WTime) | G39: =IF(G35="","",IF(G15>0,MIN($C15:$J15)/G15,0)*WTime) | I39: =IF(I35="","",IF(I15>0,MIN($C15:$J15)/I15,0)*WTime) | T39: =IF(OR(G284="",G292=""),"",IF(OR(IFERROR(INDEX('Budget'!$D$8:$D$37,MATCH($C$282,'Budget'!$B$8:$B$37,0)),"")="Contracted",IFERROR(INDEX('Budget'!$D$8:$D$37,MATCH($C$282,'Budget'!$B$8:$B$37,0)),"")="Complete"),"",IF(G292<AsOf,"",G292))) | U39: =IF(T39="","",IF(T39<AsOf,1,IF(T39<=AsOf+AlertDays,2,IF(T39<=AsOf+2*AlertDays,3,"")))) | V39: =IF(U39="","","Quote expires: "&G284&IF($C$282="",""," ("&$C$282&")")&" — decide or ask for an extension")
B40: Warranty points | C40: =IF(C35="","",IF(MAX($C16:$J16)>0,C16/MAX($C16:$J16),0)*WWar) | E40: =IF(E35="","",IF(MAX($C16:$J16)>0,E16/MAX($C16:$J16),0)*WWar) | G40: =IF(G35="","",IF(MAX($C16:$J16)>0,G16/MAX($C16:$J16),0)*WWar) | I40: =IF(I35="","",IF(MAX($C16:$J16)>0,I16/MAX($C16:$J16),0)*WWar) | T40: =IF(OR(I284="",I292=""),"",IF(OR(IFERROR(INDEX('Budget'!$D$8:$D$37,MATCH($C$282,'Budget'!$B$8:$B$37,0)),"")="Contracted",IFERROR(INDEX('Budget'!$D$8:$D$37,MATCH($C$282,'Budget'!$B$8:$B$37,0)),"")="Complete"),"",IF(I292<AsOf,"",I292))) | U40: =IF(T40="","",IF(T40<AsOf,1,IF(T40<=AsOf+AlertDays,2,IF(T40<=AsOf+2*AlertDays,3,"")))) | V40: =IF(U40="","","Quote expires: "&I284&IF($C$282="",""," ("&$C$282&")")&" — decide or ask for an extension")
B41: Completeness points | C41: =IF(C35="","",C36*WComp) | E41: =IF(E35="","",E36*WComp) | G41: =IF(G35="","",G36*WComp) | I41: =IF(I35="","",I36*WComp) | T41: =IF(OR(C323="",C331=""),"",IF(OR(IFERROR(INDEX('Budget'!$D$8:$D$37,MATCH($C$321,'Budget'!$B$8:$B$37,0)),"")="Contracted",IFERROR(INDEX('Budget'!$D$8:$D$37,MATCH($C$321,'Budget'!$B$8:$B$37,0)),"")="Complete"),"",IF(C331<AsOf,"",C331))) | U41: =IF(T41="","",IF(T41<AsOf,1,IF(T41<=AsOf+AlertDays,2,IF(T41<=AsOf+2*AlertDays,3,"")))) | V41: =IF(U41="","","Quote expires: "&C323&IF($C$321="",""," ("&$C$321&")")&" — decide or ask for an extension")
B42: Gut & references points | C42: =IF(C35="","",(IF(C18="",0,C18/5)*0.7+IF(C17="Yes",0.3,0))*WGut) | E42: =IF(E35="","",(IF(E18="",0,E18/5)*0.7+IF(E17="Yes",0.3,0))*WGut) | G42: =IF(G35="","",(IF(G18="",0,G18/5)*0.7+IF(G17="Yes",0.3,0))*WGut) | I42: =IF(I35="","",(IF(I18="",0,I18/5)*0.7+IF(I17="Yes",0.3,0))*WGut) | T42: =IF(OR(E323="",E331=""),"",IF(OR(IFERROR(INDEX('Budget'!$D$8:$D$37,MATCH($C$321,'Budget'!$B$8:$B$37,0)),"")="Contracted",IFERROR(INDEX('Budget'!$D$8:$D$37,MATCH($C$321,'Budget'!$B$8:$B$37,0)),"")="Complete"),"",IF(E331<AsOf,"",E331))) | U42: =IF(T42="","",IF(T42<AsOf,1,IF(T42<=AsOf+AlertDays,2,IF(T42<=AsOf+2*AlertDays,3,"")))) | V42: =IF(U42="","","Quote expires: "&E323&IF($C$321="",""," ("&$C$321&")")&" — decide or ask for an extension")
B43: TOTAL SCORE | C43: =IF(C35="","",ROUND(SUM(C38:C42),1)) | E43: =IF(E35="","",ROUND(SUM(E38:E42),1)) | G43: =IF(G35="","",ROUND(SUM(G38:G42),1)) | I43: =IF(I35="","",ROUND(SUM(I38:I42),1)) | T43: =IF(OR(G323="",G331=""),"",IF(OR(IFERROR(INDEX('Budget'!$D$8:$D$37,MATCH($C$321,'Budget'!$B$8:$B$37,0)),"")="Contracted",IFERROR(INDEX('Budget'!$D$8:$D$37,MATCH($C$321,'Budget'!$B$8:$B$37,0)),"")="Complete"),"",IF(G331<AsOf,"",G331))) | U43: =IF(T43="","",IF(T43<AsOf,1,IF(T43<=AsOf+AlertDays,2,IF(T43<=AsOf+2*AlertDays,3,"")))) | V43: =IF(U43="","","Quote expires: "&G323&IF($C$321="",""," ("&$C$321&")")&" — decide or ask for an extension")
B44: Ranking | C44: =IF(C43="","",IF(C43=MAX($C43:$J43),"🏆 WINNER","#"&(1+COUNTIF($C43:$J43,">"&C43)))) | E44: =IF(E43="","",IF(E43=MAX($C43:$J43),"🏆 WINNER","#"&(1+COUNTIF($C43:$J43,">"&E43)))) | G44: =IF(G43="","",IF(G43=MAX($C43:$J43),"🏆 WINNER","#"&(1+COUNTIF($C43:$J43,">"&G43)))) | I44: =IF(I43="","",IF(I43=MAX($C43:$J43),"🏆 WINNER","#"&(1+COUNTIF($C43:$J43,">"&I43)))) | T44: =IF(OR(I323="",I331=""),"",IF(OR(IFERROR(INDEX('Budget'!$D$8:$D$37,MATCH($C$321,'Budget'!$B$8:$B$37,0)),"")="Contracted",IFERROR(INDEX('Budget'!$D$8:$D$37,MATCH($C$321,'Budget'!$B$8:$B$37,0)),"")="Complete"),"",IF(I331<AsOf,"",I331))) | U44: =IF(T44="","",IF(T44<AsOf,1,IF(T44<=AsOf+AlertDays,2,IF(T44<=AsOf+2*AlertDays,3,"")))) | V44: =IF(U44="","","Quote expires: "&I323&IF($C$321="",""," ("&$C$321&")")&" — decide or ask for an extension")
B45: =IF(COUNT($C35:$J35)<2,"",IF(INDEX($C11:$J11,MATCH(MIN($C14:$J14),$C14:$J14,0))<>INDEX($C11:$J11,MATCH(MIN($C35:$J35),$C35:$J35,0)),"⚠️ Hidden costs change the ranking! Cheapest quoted price: "&INDEX($C11:$J11,MATCH(MIN($C14:$J14),$C14:$J14,0))&" → cheapest TRUE cost: "&INDEX($C11:$J11,MATCH(MIN($C35:$J35),$C35:$J35,0)),"✓ The cheapest quote is also the cheapest true cost.")) | P45: =IF(B45="",0,IF(LEFT(B45,1)="✓",0,1)) | T45: =IF(OR(C362="",C370=""),"",IF(OR(IFERROR(INDEX('Budget'!$D$8:$D$37,MATCH($C$360,'Budget'!$B$8:$B$37,0)),"")="Contracted",IFERROR(INDEX('Budget'!$D$8:$D$37,MATCH($C$360,'Budget'!$B$8:$B$37,0)),"")="Complete"),"",IF(C370<AsOf,"",C370))) | U45: =IF(T45="","",IF(T45<AsOf,1,IF(T45<=AsOf+AlertDays,2,IF(T45<=AsOf+2*AlertDays,3,"")))) | V45: =IF(U45="","","Quote expires: "&C362&IF($C$360="",""," ("&$C$360&")")&" — decide or ask for an extension")
T46: =IF(OR(E362="",E370=""),"",IF(OR(IFERROR(INDEX('Budget'!$D$8:$D$37,MATCH($C$360,'Budget'!$B$8:$B$37,0)),"")="Contracted",IFERROR(INDEX('Budget'!$D$8:$D$37,MATCH($C$360,'Budget'!$B$8:$B$37,0)),"")="Complete"),"",IF(E370<AsOf,"",E370))) | U46: =IF(T46="","",IF(T46<AsOf,1,IF(T46<=AsOf+AlertDays,2,IF(T46<=AsOf+2*AlertDays,3,"")))) | V46: =IF(U46="","","Quote expires: "&E362&IF($C$360="",""," ("&$C$360&")")&" — decide or ask for an extension")
T47: =IF(OR(G362="",G370=""),"",IF(OR(IFERROR(INDEX('Budget'!$D$8:$D$37,MATCH($C$360,'Budget'!$B$8:$B$37,0)),"")="Contracted",IFERROR(INDEX('Budget'!$D$8:$D$37,MATCH($C$360,'Budget'!$B$8:$B$37,0)),"")="Complete"),"",IF(G370<AsOf,"",G370))) | U47: =IF(T47="","",IF(T47<AsOf,1,IF(T47<=AsOf+AlertDays,2,IF(T47<=AsOf+2*AlertDays,3,"")))) | V47: =IF(U47="","","Quote expires: "&G362&IF($C$360="",""," ("&$C$360&")")&" — decide or ask for an extension")
B48: COMPARISON 2 ▸ trade: | C48: Flooring | E48: =IF(COUNT($C$82:$J$82)=0,"Enter up to 4 quotes below","🏆 Best overall: "&INDEX($C$50:$J$50,MATCH(MAX($C$82:$J$82),$C$82:$J$82,0))&" — true cost "&CurSym&" "&FIXED(INDEX($C$74:$J$74,MATCH(MAX($C$82:$J$82),$C$82:$J$82,0)),0)) | T48: =IF(OR(I362="",I370=""),"",IF(OR(IFERROR(INDEX('Budget'!$D$8:$D$37,MATCH($C$360,'Budget'!$B$8:$B$37,0)),"")="Contracted",IFERROR(INDEX('Budget'!$D$8:$D$37,MATCH($C$360,'Budget'!$B$8:$B$37,0)),"")="Complete"),"",IF(I370<AsOf,"",I370))) | U48: =IF(T48="","",IF(T48<AsOf,1,IF(T48<=AsOf+AlertDays,2,IF(T48<=AsOf+2*AlertDays,3,"")))) | V48: =IF(U48="","","Quote expires: "&I362&IF($C$360="",""," ("&$C$360&")")&" — decide or ask for an extension")
C49: Contractor 1 | E49: Contractor 2 | G49: Contractor 3 | I49: Contractor 4
B50: Contractor / company | C50: Oak & Plank Flooring | E50: FloorMasters
B51: ="Quoted price ("&CurSym&")" | C51: 8900 | E51: 8200
B52: ="Price includes "&TaxWord&"?" | C52: Yes | E52: Yes | G52: =DefInclTax | I52: =DefInclTax
B53: ="Price incl. "&TaxWord&" ("&CurSym&")" | C53: =IF(C51="","",IF(C52="No",C51*(1+VatRate),C51)) | E53: =IF(E51="","",IF(E52="No",E51*(1+VatRate),E51)) | G53: =IF(G51="","",IF(G52="No",G51*(1+VatRate),G51)) | I53: =IF(I51="","",IF(I52="No",I51*(1+VatRate),I51))
B54: Timeline (weeks) | C54: 2 | E54: 3
B55: Warranty (years) | C55: 10 | E55: 5
B56: References checked? | C56: Yes | E56: No
B57: Gut feeling (1–5) | C57: 4 | E57: 3
B58: Quote valid until | C58: 46192 | E58: 46218
B59: HIDDEN-COST CHECKLIST | C59: Included? | D59: ="Extra "&CurSym | E59: Included? | F59: ="Extra "&CurSym | G59: Included? | H59: ="Extra "&CurSym | I59: Included? | J59: ="Extra "&CurSym
B60: Demolition | C60: Included | E60: Included
B61: Waste disposal | C61: Included | E61: Not included | F61: 250
B62: Delivery | C62: Unclear | D62: 150 | E62: Not included | F62: 200
B63: Permits | C63: Included | E63: Included
B64: Materials specified | C64: Included | E64: Included
B65: Labor specified | C65: Included | E65: Included
B66: Finishing | C66: Not included | D66: 600 | E66: Not included | F66: 900
B67: Cleanup | C67: Included | E67: Not included | F67: 150
B68: =TaxWord&" shown in price" | C68: Included | E68: Included
B69: Electrical upgrades | C69: Included | E69: Included
B70: Plumbing modifications | C70: Included | E70: Included
B71: Payment schedule defined | C71: Included | E71: Unclear | F71: 0
B72: Warranty in writing | C72: Included | E72: Included
B73: ="Hidden extras ("&CurSym&")" | C73: =IF(C50="","",SUMPRODUCT((C60:C72<>"Included")*D60:D72)) | E73: =IF(E50="","",SUMPRODUCT((E60:E72<>"Included")*F60:F72)) | G73: =IF(G50="","",SUMPRODUCT((G60:G72<>"Included")*H60:H72)) | I73: =IF(I50="","",SUMPRODUCT((I60:I72<>"Included")*J60:J72))
B74: ="TRUE COST ("&CurSym&")" | C74: =IF(OR(C50="",C53=""),"",C53+C73) | E74: =IF(OR(E50="",E53=""),"",E53+E73) | G74: =IF(OR(G50="",G53=""),"",G53+G73) | I74: =IF(OR(I50="",I53=""),"",I53+I73)
B75: Completeness | C75: =IF(C50="","",COUNTIF(C60:C72,"Included")/13) | E75: =IF(E50="","",COUNTIF(E60:E72,"Included")/13) | G75: =IF(G50="","",COUNTIF(G60:G72,"Included")/13) | I75: =IF(I50="","",COUNTIF(I60:I72,"Included")/13)
B76: SCORE
B77: Price points | C77: =IF(C74="","",IF(C74>0,MIN($C74:$J74)/C74,0)*WPrice) | E77: =IF(E74="","",IF(E74>0,MIN($C74:$J74)/E74,0)*WPrice) | G77: =IF(G74="","",IF(G74>0,MIN($C74:$J74)/G74,0)*WPrice) | I77: =IF(I74="","",IF(I74>0,MIN($C74:$J74)/I74,0)*WPrice)
B78: Timeline points | C78: =IF(C74="","",IF(C54>0,MIN($C54:$J54)/C54,0)*WTime) | E78: =IF(E74="","",IF(E54>0,MIN($C54:$J54)/E54,0)*WTime) | G78: =IF(G74="","",IF(G54>0,MIN($C54:$J54)/G54,0)*WTime) | I78: =IF(I74="","",IF(I54>0,MIN($C54:$J54)/I54,0)*WTime)
B79: Warranty points | C79: =IF(C74="","",IF(MAX($C55:$J55)>0,C55/MAX($C55:$J55),0)*WWar) | E79: =IF(E74="","",IF(MAX($C55:$J55)>0,E55/MAX($C55:$J55),0)*WWar) | G79: =IF(G74="","",IF(MAX($C55:$J55)>0,G55/MAX($C55:$J55),0)*WWar) | I79: =IF(I74="","",IF(MAX($C55:$J55)>0,I55/MAX($C55:$J55),0)*WWar)
B80: Completeness points | C80: =IF(C74="","",C75*WComp) | E80: =IF(E74="","",E75*WComp) | G80: =IF(G74="","",G75*WComp) | I80: =IF(I74="","",I75*WComp)
B81: Gut & references points | C81: =IF(C74="","",(IF(C57="",0,C57/5)*0.7+IF(C56="Yes",0.3,0))*WGut) | E81: =IF(E74="","",(IF(E57="",0,E57/5)*0.7+IF(E56="Yes",0.3,0))*WGut) | G81: =IF(G74="","",(IF(G57="",0,G57/5)*0.7+IF(G56="Yes",0.3,0))*WGut) | I81: =IF(I74="","",(IF(I57="",0,I57/5)*0.7+IF(I56="Yes",0.3,0))*WGut)
B82: TOTAL SCORE | C82: =IF(C74="","",ROUND(SUM(C77:C81),1)) | E82: =IF(E74="","",ROUND(SUM(E77:E81),1)) | G82: =IF(G74="","",ROUND(SUM(G77:G81),1)) | I82: =IF(I74="","",ROUND(SUM(I77:I81),1))
B83: Ranking | C83: =IF(C82="","",IF(C82=MAX($C82:$J82),"🏆 WINNER","#"&(1+COUNTIF($C82:$J82,">"&C82)))) | E83: =IF(E82="","",IF(E82=MAX($C82:$J82),"🏆 WINNER","#"&(1+COUNTIF($C82:$J82,">"&E82)))) | G83: =IF(G82="","",IF(G82=MAX($C82:$J82),"🏆 WINNER","#"&(1+COUNTIF($C82:$J82,">"&G82)))) | I83: =IF(I82="","",IF(I82=MAX($C82:$J82),"🏆 WINNER","#"&(1+COUNTIF($C82:$J82,">"&I82))))
B84: =IF(COUNT($C74:$J74)<2,"",IF(INDEX($C50:$J50,MATCH(MIN($C53:$J53),$C53:$J53,0))<>INDEX($C50:$J50,MATCH(MIN($C74:$J74),$C74:$J74,0)),"⚠️ Hidden costs change the ranking! Cheapest quoted price: "&INDEX($C50:$J50,MATCH(MIN($C53:$J53),$C53:$J53,0))&" → cheapest TRUE cost: "&INDEX($C50:$J50,MATCH(MIN($C74:$J74),$C74:$J74,0)),"✓ The cheapest quote is also the cheapest true cost.")) | P84: =IF(B84="",0,IF(LEFT(B84,1)="✓",0,1))
B87: COMPARISON 3 ▸ trade: | C87: Painting | E87: =IF(COUNT($C$121:$J$121)=0,"Enter up to 4 quotes below","🏆 Best overall: "&INDEX($C$89:$J$89,MATCH(MAX($C$121:$J$121),$C$121:$J$121,0))&" — true cost "&CurSym&" "&FIXED(INDEX($C$113:$J$113,MATCH(MAX($C$121:$J$121),$C$121:$J$121,0)),0))
C88: Contractor 1 | E88: Contractor 2 | G88: Contractor 3 | I88: Contractor 4
B89: Contractor / company | C89: Finish Line Painters | E89: ColourPro
B90: ="Quoted price ("&CurSym&")" | C90: 4700 | E90: 5300
B91: ="Price includes "&TaxWord&"?" | C91: Yes | E91: Yes | G91: =DefInclTax | I91: =DefInclTax
B92: ="Price incl. "&TaxWord&" ("&CurSym&")" | C92: =IF(C90="","",IF(C91="No",C90*(1+VatRate),C90)) | E92: =IF(E90="","",IF(E91="No",E90*(1+VatRate),E90)) | G92: =IF(G90="","",IF(G91="No",G90*(1+VatRate),G90)) | I92: =IF(I90="","",IF(I91="No",I90*(1+VatRate),I90))
B93: Timeline (weeks) | C93: 2 | E93: 2
B94: Warranty (years) | C94: 2 | E94: 1
B95: References checked? | C95: Yes | E95: No
B96: Gut feeling (1–5) | C96: 4 | E96: 3
B97: Quote valid until | C97: 46234 | E97: 46199
B98: HIDDEN-COST CHECKLIST | C98: Included? | D98: ="Extra "&CurSym | E98: Included? | F98: ="Extra "&CurSym | G98: Included? | H98: ="Extra "&CurSym | I98: Included? | J98: ="Extra "&CurSym
B99: Demolition | C99: Included | E99: Included
B100: Waste disposal | C100: Included | E100: Included
B101: Delivery | C101: Included | E101: Included
B102: Permits | C102: Included | E102: Included
...

Sheet Contractors
B1: 👷 Contractors
B2: What this tab does: one row per contractor — contract, paperwork, progress and a warning when you pay ahead of the work. Communication log below.
B3: © 2026 Hang Nguyen — Renovation OS. Licensed to the original purchaser for personal use only. Do not share, copy, resell or redistribute.
B5: Company | C5: Trade | D5: Budget category | E5: Main room | F5: Contact person | G5: Phone | H5: Email | I5: ="Contract value ("&CurSym&")" | J5: ="Approved changes ("&CurSym&")" | K5: ="Total contract ("&CurSym&")" | L5: Contract signed? | M5: Start | N5: Expected completion | O5: Insurance ✓ | P5: License ✓ | Q5: Warranty (years) | R5: % work complete | S5: ="Paid to date ("&CurSym&")" | T5: Paid % | U5: Overpayment check | V5: lvl | W5: due | X5: pri | Y5: text
B6: Hansen Demolition | C6: Demolition & strip-out | D6: Demolition | E6: Whole house | F6: Lars Hansen | G6: +31 6 1234 5678 | H6: lars@hansen-demo.example | I6: 3800 | J6: =IF(B6="","",SUMIFS('Change Orders'!$J$7:$J$106,'Change Orders'!$E$7:$E$106,B6,'Change Orders'!$L$7:$L$106,"Approved")) | K6: =IF(B6="","",I6+J6) | L6: Yes | M6: 46132 | N6: 46141 | O6: Yes | P6: Yes | Q6: 1 | R6: 1 | S6: =IF(B6="","",SUMIFS('Payments'!$N$6:$N$205,'Payments'!$B$6:$B$205,B6)) | T6: =IF(OR(B6="",K6=0),"",S6/K6) | U6: =IF(V6="","",IF(V6=2,"⚠️ Paying ahead of work","✓ OK")) | V6: =IF(T6="","",IF(T6-R6>OverpayTol,2,0)) | W6: =IF(V6=2,AsOf,"") | X6: =IF(W6="","",1) | Y6: =IF(X6="","","Paying ahead of work: "&B6&" — paid "&ROUND(T6*100,0)&"%, work done "&ROUND(R6*100,0)&"%")
B7: Solid Structures Ltd | C7: Builder / structural | D7: Structural | E7: Living room | F7: Maria Costa | G7: +31 6 2345 6789 | H7: maria@solidstructures.example | I7: 9400 | J7: =IF(B7="","",SUMIFS('Change Orders'!$J$7:$J$106,'Change Orders'!$E$7:$E$106,B7,'Change Orders'!$L$7:$L$106,"Approved")) | K7: =IF(B7="","",I7+J7) | L7: Yes | M7: 46142 | N7: 46153 | O7: Yes | P7: Yes | Q7: 10 | R7: 1 | S7: =IF(B7="","",SUMIFS('Payments'!$N$6:$N$205,'Payments'!$B$6:$B$205,B7)) | T7: =IF(OR(B7="",K7=0),"",S7/K7) | U7: =IF(V7="","",IF(V7=2,"⚠️ Paying ahead of work","✓ OK")) | V7: =IF(T7="","",IF(T7-R7>OverpayTol,2,0)) | W7: =IF(V7=2,AsOf,"") | X7: =IF(W7="","",1) | Y7: =IF(X7="","","Paying ahead of work: "&B7&" — paid "&ROUND(T7*100,0)&"%, work done "&ROUND(R7*100,0)&"%")
B8: FlowRight Plumbing | C8: Plumbing | D8: Plumbing | E8: Whole house | F8: Tom de Vries | G8: +31 6 3456 7890 | H8: tom@flowright.example | I8: 9200 | J8: =IF(B8="","",SUMIFS('Change Orders'!$J$7:$J$106,'Change Orders'!$E$7:$E$106,B8,'Change Orders'!$L$7:$L$106,"Approved")) | K8: =IF(B8="","",I8+J8) | L8: Yes | M8: 46154 | N8: 46178 | O8: Yes | P8: Yes | Q8: 2 | R8: 0.6 | S8: =IF(B8="","",SUMIFS('Payments'!$N$6:$N$205,'Payments'!$B$6:$B$205,B8)) | T8: =IF(OR(B8="",K8=0),"",S8/K8) | U8: =IF(V8="","",IF(V8=2,"⚠️ Paying ahead of work","✓ OK")) | V8: =IF(T8="","",IF(T8-R8>OverpayTol,2,0)) | W8: =IF(V8=2,AsOf,"") | X8: =IF(W8="","",1) | Y8: =IF(X8="","","Paying ahead of work: "&B8&" — paid "&ROUND(T8*100,0)&"%, work done "&ROUND(R8*100,0)&"%")
B9: Bright Spark Electric | C9: Electrical | D9: Electrical | E9: Whole house | F9: Ahmed Karimi | G9: +31 6 4567 8901 | H9: ahmed@brightspark.example | I9: 10500 | J9: =IF(B9="","",SUMIFS('Change Orders'!$J$7:$J$106,'Change Orders'!$E$7:$E$106,B9,'Change Orders'!$L$7:$L$106,"Approved")) | K9: =IF(B9="","",I9+J9) | L9: Yes | M9: 46154 | N9: 46188 | O9: Yes | P9: No | Q9: 2 | R9: 0.35 | S9: =IF(B9="","",SUMIFS('Payments'!$N$6:$N$205,'Payments'!$B$6:$B$205,B9)) | T9: =IF(OR(B9="",K9=0),"",S9/K9) | U9: =IF(V9="","",IF(V9=2,"⚠️ Paying ahead of work","✓ OK")) | V9: =IF(T9="","",IF(T9-R9>OverpayTol,2,0)) | W9: =IF(V9=2,AsOf,"") | X9: =IF(W9="","",1) | Y9: =IF(X9="","","Paying ahead of work: "&B9&" — paid "&ROUND(T9*100,0)&"%, work done "&ROUND(R9*100,0)&"%")
B10: ClimaHeat HVAC | C10: Heat pump & ventilation | D10: HVAC | E10: Whole house | F10: Eva Jansen | G10: +31 6 5678 9012 | H10: eva@climaheat.example | I10: 9300 | J10: =IF(B10="","",SUMIFS('Change Orders'!$J$7:$J$106,'Change Orders'!$E$7:$E$106,B10,'Change Orders'!$L$7:$L$106,"Approved")) | K10: =IF(B10="","",I10+J10) | L10: Yes | M10: 46179 | N10: 46188 | O10: Yes | P10: Yes | Q10: 5 | R10: 0.25 | S10: =IF(B10="","",SUMIFS('Payments'!$N$6:$N$205,'Payments'!$B$6:$B$205,B10)) | T10: =IF(OR(B10="",K10=0),"",S10/K10) | U10: =IF(V10="","",IF(V10=2,"⚠️ Paying ahead of work","✓ OK")) | V10: =IF(T10="","",IF(T10-R10>OverpayTol,2,0)) | W10: =IF(V10=2,AsOf,"") | X10: =IF(W10="","",1) | Y10: =IF(X10="","","Paying ahead of work: "&B10&" — paid "&ROUND(T10*100,0)&"%, work done "&ROUND(R10*100,0)&"%")
B11: ClearView Windows | C11: Windows & doors | D11: Windows & doors | E11: Whole house | F11: Pieter Smit | G11: +31 6 6789 0123 | H11: pieter@clearview.example | I11: 12400 | J11: =IF(B11="","",SUMIFS('Change Orders'!$J$7:$J$106,'Change Orders'!$E$7:$E$106,B11,'Change Orders'!$L$7:$L$106,"Approved")) | K11: =IF(B11="","",I11+J11) | L11: Yes | M11: 46142 | N11: 46149 | O11: Yes | P11: Yes | Q11: 10 | R11: 0.9 | S11: =IF(B11="","",SUMIFS('Payments'!$N$6:$N$205,'Payments'!$B$6:$B$205,B11)) | T11: =IF(OR(B11="",K11=0),"",S11/K11) | U11: =IF(V11="","",IF(V11=2,"⚠️ Paying ahead of work","✓ OK")) | V11: =IF(T11="","",IF(T11-R11>OverpayTol,2,0)) | W11: =IF(V11=2,AsOf,"") | X11: =IF(W11="","",1) | Y11: =IF(X11="","","Paying ahead of work: "&B11&" — paid "&ROUND(T11*100,0)&"%, work done "&ROUND(R11*100,0)&"%")
B12: Nordic Kitchens | C12: Kitchen supply & install | D12: Kitchen | E12: Kitchen | F12: Sofie Berg | G12: +31 6 7890 1234 | H12: sofie@nordickitchens.example | I12: 19400 | J12: =IF(B12="","",SUMIFS('Change Orders'!$J$7:$J$106,'Change Orders'!$E$7:$E$106,B12,'Change Orders'!$L$7:$L$106,"Approved")) | K12: =IF(B12="","",I12+J12) | L12: Yes | M12: 46205 | N12: 46216 | O12: Yes | P12: Yes | Q12: 5 | R12: 0 | S12: =IF(B12="","",SUMIFS('Payments'!$N$6:$N$205,'Payments'!$B$6:$B$205,B12)) | T12: =IF(OR(B12="",K12=0),"",S12/K12) | U12: =IF(V12="","",IF(V12=2,"⚠️ Paying ahead of work","✓ OK")) | V12: =IF(T12="","",IF(T12-R12>OverpayTol,2,0)) | W12: =IF(V12=2,AsOf,"") | X12: =IF(W12="","",1) | Y12: =IF(X12="","","Paying ahead of work: "&B12&" — paid "&ROUND(T12*100,0)&"%, work done "&ROUND(R12*100,0)&"%")
B13: Aqua Bath Studio | C13: Bathroom fit-out | D13: Bathrooms | E13: Bathroom 1 | F13: Luca Romano | G13: +31 6 8901 2345 | H13: luca@aquabath.example | I13: 11200 | J13: =IF(B13="","",SUMIFS('Change Orders'!$J$7:$J$106,'Change Orders'!$E$7:$E$106,B13,'Change Orders'!$L$7:$L$106,"Approved")) | K13: =IF(B13="","",I13+J13) | L13: Yes | M13: 46205 | N13: 46229 | O13: Yes | P13: Yes | Q13: 5 | R13: 0 | S13: =IF(B13="","",SUMIFS('Payments'!$N$6:$N$205,'Payments'!$B$6:$B$205,B13)) | T13: =IF(OR(B13="",K13=0),"",S13/K13) | U13: =IF(V13="","",IF(V13=2,"⚠️ Paying ahead of work","✓ OK")) | V13: =IF(T13="","",IF(T13-R13>OverpayTol,2,0)) | W13: =IF(V13=2,AsOf,"") | X13: =IF(W13="","",1) | Y13: =IF(X13="","","Paying ahead of work: "&B13&" — paid "&ROUND(T13*100,0)&"%, work done "&ROUND(R13*100,0)&"%")
B14: GreenPlan Architects | C14: Architect & permits | D14: Professional fees | E14: Whole house | F14: Nina Visser | G14: +31 6 9012 3456 | H14: nina@greenplan.example | I14: 4800 | J14: =IF(B14="","",SUMIFS('Change Orders'!$J$7:$J$106,'Change Orders'!$E$7:$E$106,B14,'Change Orders'!$L$7:$L$106,"Approved")) | K14: =IF(B14="","",I14+J14) | L14: Yes | M14: 46083 | N14: 46248 | O14: Yes | P14: Yes | Q14: 0 | R14: 0.75 | S14: =IF(B14="","",SUMIFS('Payments'!$N$6:$N$205,'Payments'!$B$6:$B$205,B14)) | T14: =IF(OR(B14="",K14=0),"",S14/K14) | U14: =IF(V14="","",IF(V14=2,"⚠️ Paying ahead of work","✓ OK")) | V14: =IF(T14="","",IF(T14-R14>OverpayTol,2,0)) | W14: =IF(V14=2,AsOf,"") | X14: =IF(W14="","",1) | Y14: =IF(X14="","","Paying ahead of work: "&B14&" — paid "&ROUND(T14*100,0)&"%, work done "&ROUND(R14*100,0)&"%")
B15: Finish Line Painters | C15: Painting & decorating | D15: Painting | E15: Whole house | F15: Johan Bakker | G15: +31 6 0123 4567 | H15: johan@finishline.example | I15: 4700 | J15: =IF(B15="","",SUMIFS('Change Orders'!$J$7:$J$106,'Change Orders'!$E$7:$E$106,B15,'Change Orders'!$L$7:$L$106,"Approved")) | K15: =IF(B15="","",I15+J15) | L15: No | O15: Yes | P15: Yes | Q15: 2 | R15: 0 | S15: =IF(B15="","",SUMIFS('Payments'!$N$6:$N$205,'Payments'!$B$6:$B$205,B15)) | T15: =IF(OR(B15="",K15=0),"",S15/K15) | U15: =IF(V15="","",IF(V15=2,"⚠️ Paying ahead of work","✓ OK")) | V15: =IF(T15="","",IF(T15-R15>OverpayTol,2,0)) | W15: =IF(V15=2,AsOf,"") | X15: =IF(W15="","",1) | Y15: =IF(X15="","","Paying ahead of work: "&B15&" — paid "&ROUND(T15*100,0)&"%, work done "&ROUND(R15*100,0)&"%")
B16: Oak & Plank Flooring | C16: Flooring | D16: Flooring | E16: Whole house | F16: Mila Peters | G16: +31 6 1122 3344 | H16: mila@oakplank.example | J16: =IF(B16="","",SUMIFS('Change Orders'!$J$7:$J$106,'Change Orders'!$E$7:$E$106,B16,'Change Orders'!$L$7:$L$106,"Approved")) | K16: =IF(B16="","",I16+J16) | L16: No | O16: Yes | P16: Yes | Q16: 10 | S16: =IF(B16="","",SUMIFS('Payments'!$N$6:$N$205,'Payments'!$B$6:$B$205,B16)) | T16: =IF(OR(B16="",K16=0),"",S16/K16) | U16: =IF(V16="","",IF(V16=2,"⚠️ Paying ahead of work","✓ OK")) | V16: =IF(T16="","",IF(T16-R16>OverpayTol,2,0)) | W16: =IF(V16=2,AsOf,"") | X16: =IF(W16="","",1) | Y16: =IF(X16="","","Paying ahead of work: "&B16&" — paid "&ROUND(T16*100,0)&"%, work done "&ROUND(R16*100,0)&"%")
J17: =IF(B17="","",SUMIFS('Change Orders'!$J$7:$J$106,'Change Orders'!$E$7:$E$106,B17,'Change Orders'!$L$7:$L$106,"Approved")) | K17: =IF(B17="","",I17+J17) | S17: =IF(B17="","",SUMIFS('Payments'!$N$6:$N$205,'Payments'!$B$6:$B$205,B17)) | T17: =IF(OR(B17="",K17=0),"",S17/K17) | U17: =IF(V17="","",IF(V17=2,"⚠️ Paying ahead of work","✓ OK")) | V17: =IF(T17="","",IF(T17-R17>OverpayTol,2,0)) | W17: =IF(V17=2,AsOf,"") | X17: =IF(W17="","",1) | Y17: =IF(X17="","","Paying ahead of work: "&B17&" — paid "&ROUND(T17*100,0)&"%, work done "&ROUND(R17*100,0)&"%")
J18: =IF(B18="","",SUMIFS('Change Orders'!$J$7:$J$106,'Change Orders'!$E$7:$E$106,B18,'Change Orders'!$L$7:$L$106,"Approved")) | K18: =IF(B18="","",I18+J18) | S18: =IF(B18="","",SUMIFS('Payments'!$N$6:$N$205,'Payments'!$B$6:$B$205,B18)) | T18: =IF(OR(B18="",K18=0),"",S18/K18) | U18: =IF(V18="","",IF(V18=2,"⚠️ Paying ahead of work","✓ OK")) | V18: =IF(T18="","",IF(T18-R18>OverpayTol,2,0)) | W18: =IF(V18=2,AsOf,"") | X18: =IF(W18="","",1) | Y18: =IF(X18="","","Paying ahead of work: "&B18&" — paid "&ROUND(T18*100,0)&"%, work done "&ROUND(R18*100,0)&"%")
J19: =IF(B19="","",SUMIFS('Change Orders'!$J$7:$J$106,'Change Orders'!$E$7:$E$106,B19,'Change Orders'!$L$7:$L$106,"Approved")) | K19: =IF(B19="","",I19+J19) | S19: =IF(B19="","",SUMIFS('Payments'!$N$6:$N$205,'Payments'!$B$6:$B$205,B19)) | T19: =IF(OR(B19="",K19=0),"",S19/K19) | U19: =IF(V19="","",IF(V19=2,"⚠️ Paying ahead of work","✓ OK")) | V19: =IF(T19="","",IF(T19-R19>OverpayTol,2,0)) | W19: =IF(V19=2,AsOf,"") | X19: =IF(W19="","",1) | Y19: =IF(X19="","","Paying ahead of work: "&B19&" — paid "&ROUND(T19*100,0)&"%, work done "&ROUND(R19*100,0)&"%")
J20: =IF(B20="","",SUMIFS('Change Orders'!$J$7:$J$106,'Change Orders'!$E$7:$E$106,B20,'Change Orders'!$L$7:$L$106,"Approved")) | K20: =IF(B20="","",I20+J20) | S20: =IF(B20="","",SUMIFS('Payments'!$N$6:$N$205,'Payments'!$B$6:$B$205,B20)) | T20: =IF(OR(B20="",K20=0),"",S20/K20) | U20: =IF(V20="","",IF(V20=2,"⚠️ Paying ahead of work","✓ OK")) | V20: =IF(T20="","",IF(T20-R20>OverpayTol,2,0)) | W20: =IF(V20=2,AsOf,"") | X20: =IF(W20="","",1) | Y20: =IF(X20="","","Paying ahead of work: "&B20&" — paid "&ROUND(T20*100,0)&"%, work done "&ROUND(R20*100,0)&"%")
J21: =IF(B21="","",SUMIFS('Change Orders'!$J$7:$J$106,'Change Orders'!$E$7:$E$106,B21,'Change Orders'!$L$7:$L$106,"Approved")) | K21: =IF(B21="","",I21+J21) | S21: =IF(B21="","",SUMIFS('Payments'!$N$6:$N$205,'Payments'!$B$6:$B$205,B21)) | T21: =IF(OR(B21="",K21=0),"",S21/K21) | U21: =IF(V21="","",IF(V21=2,"⚠️ Paying ahead of work","✓ OK")) | V21: =IF(T21="","",IF(T21-R21>OverpayTol,2,0)) | W21: =IF(V21=2,AsOf,"") | X21: =IF(W21="","",1) | Y21: =IF(X21="","","Paying ahead of work: "&B21&" — paid "&ROUND(T21*100,0)&"%, work done "&ROUND(R21*100,0)&"%")
J22: =IF(B22="","",SUMIFS('Change Orders'!$J$7:$J$106,'Change Orders'!$E$7:$E$106,B22,'Change Orders'!$L$7:$L$106,"Approved")) | K22: =IF(B22="","",I22+J22) | S22: =IF(B22="","",SUMIFS('Payments'!$N$6:$N$205,'Payments'!$B$6:$B$205,B22)) | T22: =IF(OR(B22="",K22=0),"",S22/K22) | U22: =IF(V22="","",IF(V22=2,"⚠️ Paying ahead of work","✓ OK")) | V22: =IF(T22="","",IF(T22-R22>OverpayTol,2,0)) | W22: =IF(V22=2,AsOf,"") | X22: =IF(W22="","",1) | Y22: =IF(X22="","","Paying ahead of work: "&B22&" — paid "&ROUND(T22*100,0)&"%, work done "&ROUND(R22*100,0)&"%")
J23: =IF(B23="","",SUMIFS('Change Orders'!$J$7:$J$106,'Change Orders'!$E$7:$E$106,B23,'Change Orders'!$L$7:$L$106,"Approved")) | K23: =IF(B23="","",I23+J23) | S23: =IF(B23="","",SUMIFS('Payments'!$N$6:$N$205,'Payments'!$B$6:$B$205,B23)) | T23: =IF(OR(B23="",K23=0),"",S23/K23) | U23: =IF(V23="","",IF(V23=2,"⚠️ Paying ahead of work","✓ OK")) | V23: =IF(T23="","",IF(T23-R23>OverpayTol,2,0)) | W23: =IF(V23=2,AsOf,"") | X23: =IF(W23="","",1) | Y23: =IF(X23="","","Paying ahead of work: "&B23&" — paid "&ROUND(T23*100,0)&"%, work done "&ROUND(R23*100,0)&"%")
J24: =IF(B24="","",SUMIFS('Change Orders'!$J$7:$J$106,'Change Orders'!$E$7:$E$106,B24,'Change Orders'!$L$7:$L$106,"Approved")) | K24: =IF(B24="","",I24+J24) | S24: =IF(B24="","",SUMIFS('Payments'!$N$6:$N$205,'Payments'!$B$6:$B$205,B24)) | T24: =IF(OR(B24="",K24=0),"",S24/K24) | U24: =IF(V24="","",IF(V24=2,"⚠️ Paying ahead of work","✓ OK")) | V24: =IF(T24="","",IF(T24-R24>OverpayTol,2,0)) | W24: =IF(V24=2,AsOf,"") | X24: =IF(W24="","",1) | Y24: =IF(X24="","","Paying ahead of work: "&B24&" — paid "&ROUND(T24*100,0)&"%, work done "&ROUND(R24*100,0)&"%")
J25: =IF(B25="","",SUMIFS('Change Orders'!$J$7:$J$106,'Change Orders'!$E$7:$E$106,B25,'Change Orders'!$L$7:$L$106,"Approved")) | K25: =IF(B25="","",I25+J25) | S25: =IF(B25="","",SUMIFS('Payments'!$N$6:$N$205,'Payments'!$B$6:$B$205,B25)) | T25: =IF(OR(B25="",K25=0),"",S25/K25) | U25: =IF(V25="","",IF(V25=2,"⚠️ Paying ahead of work","✓ OK")) | V25: =IF(T25="","",IF(T25-R25>OverpayTol,2,0)) | W25: =IF(V25=2,AsOf,"") | X25: =IF(W25="","",1) | Y25: =IF(X25="","","Paying ahead of work: "&B25&" — paid "&ROUND(T25*100,0)&"%, work done "&ROUND(R25*100,0)&"%")
J26: =IF(B26="","",SUMIFS('Change Orders'!$J$7:$J$106,'Change Orders'!$E$7:$E$106,B26,'Change Orders'!$L$7:$L$106,"Approved")) | K26: =IF(B26="","",I26+J26) | S26: =IF(B26="","",SUMIFS('Payments'!$N$6:$N$205,'Payments'!$B$6:$B$205,B26)) | T26: =IF(OR(B26="",K26=0),"",S26/K26) | U26: =IF(V26="","",IF(V26=2,"⚠️ Paying ahead of work","✓ OK")) | V26: =IF(T26="","",IF(T26-R26>OverpayTol,2,0)) | W26: =IF(V26=2,AsOf,"") | X26: =IF(W26="","",1) | Y26: =IF(X26="","","Paying ahead of work: "&B26&" — paid "&ROUND(T26*100,0)&"%, work done "&ROUND(R26*100,0)&"%")
J27: =IF(B27="","",SUMIFS('Change Orders'!$J$7:$J$106,'Change Orders'!$E$7:$E$106,B27,'Change Orders'!$L$7:$L$106,"Approved")) | K27: =IF(B27="","",I27+J27) | S27: =IF(B27="","",SUMIFS('Payments'!$N$6:$N$205,'Payments'!$B$6:$B$205,B27)) | T27: =IF(OR(B27="",K27=0),"",S27/K27) | U27: =IF(V27="","",IF(V27=2,"⚠️ Paying ahead of work","✓ OK")) | V27: =IF(T27="","",IF(T27-R27>OverpayTol,2,0)) | W27: =IF(V27=2,AsOf,"") | X27: =IF(W27="","",1) | Y27: =IF(X27="","","Paying ahead of work: "&B27&" — paid "&ROUND(T27*100,0)&"%, work done "&ROUND(R27*100,0)&"%")
J28: =IF(B28="","",SUMIFS('Change Orders'!$J$7:$J$106,'Change Orders'!$E$7:$E$106,B28,'Change Orders'!$L$7:$L$106,"Approved")) | K28: =IF(B28="","",I28+J28) | S28: =IF(B28="","",SUMIFS('Payments'!$N$6:$N$205,'Payments'!$B$6:$B$205,B28)) | T28: =IF(OR(B28="",K28=0),"",S28/K28) | U28: =IF(V28="","",IF(V28=2,"⚠️ Paying ahead of work","✓ OK")) | V28: =IF(T28="","",IF(T28-R28>OverpayTol,2,0)) | W28: =IF(V28=2,AsOf,"") | X28: =IF(W28="","",1) | Y28: =IF(X28="","","Paying ahead of work: "&B28&" — paid "&ROUND(T28*100,0)&"%, work done "&ROUND(R28*100,0)&"%")
... J35: =IF(B35="","",SUMIFS('Change Orders'!$J$7:$J$106,'Change Orders'!$E$7:$E$106,B35,'Change Orders'!$L$7:$L$106,"Approved")) | K35: =IF(B35="","",I35+J35) | S35: =IF(B35="","",SUMIFS('Payments'!$N$6:$N$205,'Payments'!$B$6:$B$205,B35)) | T35: =IF(OR(B35="",K35=0),"",S35/K35) | U35: =IF(V35="","",IF(V35=2,"⚠️ Paying ahead of work","✓ OK")) | V35: =IF(T35="","",IF(T35-R35>OverpayTol,2,0)) | W35: =IF(V35=2,AsOf,"") | X35: =IF(W35="","",1) | Y35: =IF(X35="","","Paying ahead of work: "&B35&" — paid "&ROUND(T35*100,0)&"%, work done "&ROUND(R35*100,0)&"%")
B38: COMMUNICATION LOG — every call, email and site conversation. Follow-ups turn into alerts.
B40: Contractor | C40: Date | D40: What was said / agreed | I40: Follow-up needed? | J40: Follow-up date | K40: Follow-up done? | W40: due | X40: pri | Y40: text
B41: Bright Spark Electric | C41: 46175 | D41: Asked for revised schedule after 1-week slip — no reply yet | I41: Yes | J41: 46183 | K41: No | W41: =IF(AND(B41<>"",I41="Yes",K41<>"Yes",J41<>""),J41,"") | X41: =IF(W41="","",IF(W41<AsOf,1,IF(W41<=AsOf+AlertDays,2,IF(W41<=AsOf+2*AlertDays,3,"")))) | Y41: =IF(X41="","","Follow up with "&B41&": "&D41)
B42: Oak & Plank Flooring | C42: 46185 | D42: Quote received; asked them to include skirting boards | I42: Yes | J42: 46191 | K42: No | W42: =IF(AND(B42<>"",I42="Yes",K42<>"Yes",J42<>""),J42,"") | X42: =IF(W42="","",IF(W42<AsOf,1,IF(W42<=AsOf+AlertDays,2,IF(W42<=AsOf+2*AlertDays,3,"")))) | Y42: =IF(X42="","","Follow up with "&B42&": "&D42)
B43: Nordic Kitchens | C43: 46170 | D43: Confirmed install start 2 July, delivery 1 July | I43: No | W43: =IF(AND(B43<>"",I43="Yes",K43<>"Yes",J43<>""),J43,"") | X43: =IF(W43="","",IF(W43<AsOf,1,IF(W43<=AsOf+AlertDays,2,IF(W43<=AsOf+2*AlertDays,3,"")))) | Y43: =IF(X43="","","Follow up with "&B43&": "&D43)
B44: FlowRight Plumbing | C44: 46182 | D44: Pipe re-routing caused delay; rough-in now late | I44: Yes | J44: 46174 | K44: Yes | W44: =IF(AND(B44<>"",I44="Yes",K44<>"Yes",J44<>""),J44,"") | X44: =IF(W44="","",IF(W44<AsOf,1,IF(W44<=AsOf+AlertDays,2,IF(W44<=AsOf+2*AlertDays,3,"")))) | Y44: =IF(X44="","","Follow up with "&B44&": "&D44)
W45: =IF(AND(B45<>"",I45="Yes",K45<>"Yes",J45<>""),J45,"") | X45: =IF(W45="","",IF(W45<AsOf,1,IF(W45<=AsOf+AlertDays,2,IF(W45<=AsOf+2*AlertDays,3,"")))) | Y45: =IF(X45="","","Follow up with "&B45&": "&D45)
W46: =IF(AND(B46<>"",I46="Yes",K46<>"Yes",J46<>""),J46,"") | X46: =IF(W46="","",IF(W46<AsOf,1,IF(W46<=AsOf+AlertDays,2,IF(W46<=AsOf+2*AlertDays,3,"")))) | Y46: =IF(X46="","","Follow up with "&B46&": "&D46)
W47: =IF(AND(B47<>"",I47="Yes",K47<>"Yes",J47<>""),J47,"") | X47: =IF(W47="","",IF(W47<AsOf,1,IF(W47<=AsOf+AlertDays,2,IF(W47<=AsOf+2*AlertDays,3,"")))) | Y47: =IF(X47="","","Follow up with "&B47&": "&D47)
W48: =IF(AND(B48<>"",I48="Yes",K48<>"Yes",J48<>""),J48,"") | X48: =IF(W48="","",IF(W48<AsOf,1,IF(W48<=AsOf+AlertDays,2,IF(W48<=AsOf+2*AlertDays,3,"")))) | Y48: =IF(X48="","","Follow up with "&B48&": "&D48)
W49: =IF(AND(B49<>"",I49="Yes",K49<>"Yes",J49<>""),J49,"") | X49: =IF(W49="","",IF(W49<AsOf,1,IF(W49<=AsOf+AlertDays,2,IF(W49<=AsOf+2*AlertDays,3,"")))) | Y49: =IF(X49="","","Follow up with "&B49&": "&D49)
W50: =IF(AND(B50<>"",I50="Yes",K50<>"Yes",J50<>""),J50,"") | X50: =IF(W50="","",IF(W50<AsOf,1,IF(W50<=AsOf+AlertDays,2,IF(W50<=AsOf+2*AlertDays,3,"")))) | Y50: =IF(X50="","","Follow up with "&B50&": "&D50)
W51: =IF(AND(B51<>"",I51="Yes",K51<>"Yes",J51<>""),J51,"") | X51: =IF(W51="","",IF(W51<AsOf,1,IF(W51<=AsOf+AlertDays,2,IF(W51<=AsOf+2*AlertDays,3,"")))) | Y51: =IF(X51="","","Follow up with "&B51&": "&D51)
W52: =IF(AND(B52<>"",I52="Yes",K52<>"Yes",J52<>""),J52,"") | X52: =IF(W52="","",IF(W52<AsOf,1,IF(W52<=AsOf+AlertDays,2,IF(W52<=AsOf+2*AlertDays,3,"")))) | Y52: =IF(X52="","","Follow up with "&B52&": "&D52)
W53: =IF(AND(B53<>"",I53="Yes",K53<>"Yes",J53<>""),J53,"") | X53: =IF(W53="","",IF(W53<AsOf,1,IF(W53<=AsOf+AlertDays,2,IF(W53<=AsOf+2*AlertDays,3,"")))) | Y53: =IF(X53="","","Follow up with "&B53&": "&D53)
W54: =IF(AND(B54<>"",I54="Yes",K54<>"Yes",J54<>""),J54,"") | X54: =IF(W54="","",IF(W54<AsOf,1,IF(W54<=AsOf+AlertDays,2,IF(W54<=AsOf+2*AlertDays,3,"")))) | Y54: =IF(X54="","","Follow up with "&B54&": "&D54)
W55: =IF(AND(B55<>"",I55="Yes",K55<>"Yes",J55<>""),J55,"") | X55: =IF(W55="","",IF(W55<AsOf,1,IF(W55<=AsOf+AlertDays,2,IF(W55<=AsOf+2*AlertDays,3,"")))) | Y55: =IF(X55="","","Follow up with "&B55&": "&D55)
W56: =IF(AND(B56<>"",I56="Yes",K56<>"Yes",J56<>""),J56,"") | X56: =IF(W56="","",IF(W56<AsOf,1,IF(W56<=AsOf+AlertDays,2,IF(W56<=AsOf+2*AlertDays,3,"")))) | Y56: =IF(X56="","","Follow up with "&B56&": "&D56)
... W190: =IF(AND(B190<>"",I190="Yes",K190<>"Yes",J190<>""),J190,"") | X190: =IF(W190="","",IF(W190<AsOf,1,IF(W190<=AsOf+AlertDays,2,IF(W190<=AsOf+2*AlertDays,3,"")))) | Y190: =IF(X190="","","Follow up with "&B190&": "&D190)

Sheet Payments
B1: 💳 Payments
B2: What this tab does: your payment schedule, invoices and payments per contractor — plus a 12-month cash-flow forecast (right side →).
B3: © 2026 Hang Nguyen — Renovation OS. Licensed to the original purchaser for personal use only. Do not share, copy, resell or redistribute.
Z4: PER-CONTRACTOR SUMMARY
B5: Paid to (contractor / supplier) | C5: Milestone / what for | D5: Room (optional) | E5: Category (if not a contractor) | F5: % of contract | G5: ="…or fixed amount ("&CurSym&")" | H5: ="Scheduled ("&CurSym&")" | I5: Due date | J5: Invoice # | K5: Invoice date | L5: ="Invoiced ("&CurSym&")" | M5: Paid date | N5: ="Paid ("&CurSym&")" | O5: Status | P5: Category (auto) | Q5: room | R5: lvl | S5: unpaid | T5: 1/due | U5: due | V5: pri | W5: text | Z5: Contractor | AA5: ="Total contract ("&CurSym&")" | AB5: ="Invoiced ("&CurSym&")" | AC5: ="Paid ("&CurSym&")" | AD5: ="Still to pay ("&CurSym&")" | AE5: Next payment | AF5: ="Next amount ("&CurSym&")"
B6: GreenPlan Architects | C6: Design package 50% | F6: 0.5 | H6: =IF(B6="","",IF(G6<>"",G6,IF(F6<>"",F6*IFERROR(INDEX('Contractors'!$I$6:$I$35,MATCH(B6,'Contractors'!$B$6:$B$35,0)),0),""))) | I6: 46106 | J6: GP-01 | K6: 46101 | L6: 2400 | M6: 46105 | N6: 2400 | O6: =IF(B6="","",IF(M6<>"","Paid",IF(AND(I6<>"",I6<AsOf),"OVERDUE",IF(OR(K6<>"",L6<>""),"Invoiced","Scheduled")))) | P6: =IF(B6="","",IF(E6<>"",E6,IFERROR(INDEX('Contractors'!$D$6:$D$35,MATCH(B6,'Contractors'!$B$6:$B$35,0)),""))) | Q6: =IF(B6="","",IF(D6<>"",D6,IFERROR(INDEX('Contractors'!$E$6:$E$35,MATCH(B6,'Contractors'!$B$6:$B$35,0)),""))) | R6: =IF(O6="","",IF(O6="OVERDUE",2,IF(O6="Paid",0,IF(AND(I6<>"",I6<=AsOf+AlertDays),1,0)))) | S6: =IF(AND(B6<>"",M6="",I6<>""),IF(L6<>"",L6,IF(H6="",0,H6)),0) | T6: =IF(AND(B6<>"",M6="",I6<>""),1/I6,0) | U6: =IF(AND(B6<>"",M6="",I6<>""),I6,"") | V6: =IF(U6="","",IF(U6<AsOf,1,IF(U6<=AsOf+AlertDays,2,IF(U6<=AsOf+2*AlertDays,3,"")))) | W6: =IF(V6="","",IF(O6="OVERDUE","Overdue payment: ","Payment due: ")&B6&" — "&C6&" ("&CurSym&" "&FIXED(S6,0)&")") | Z6: =IF('Contractors'!B6="","",'Contractors'!B6) | AA6: =IF(Z6="","",'Contractors'!K6) | AB6: =IF(Z6="","",SUMIFS($L$6:$L$205,$B$6:$B$205,Z6)) | AC6: =IF(Z6="","",SUMIFS($N$6:$N$205,$B$6:$B$205,Z6)) | AD6: =IF(Z6="","",AA6-AC6) | AE6: =IF(Z6="","",IFERROR(1/SUMPRODUCT(MAX(($B$6:$B$205=Z6)*$T$6:$T$205)),"")) | AF6: =IF(AE6="","",SUMIFS($S$6:$S$205,$B$6:$B$205,Z6,$I$6:$I$205,AE6))
B7: City Building Dept | C7: Building permit fee | E7: Permits | G7: 1350 | H7: =IF(B7="","",IF(G7<>"",G7,IF(F7<>"",F7*IFERROR(INDEX('Contractors'!$I$6:$I$35,MATCH(B7,'Contractors'!$B$6:$B$35,0)),0),""))) | I7: 46111 | J7: PERMIT-2026-114 | K7: 46106 | L7: 1350 | M7: 46109 | N7: 1350 | O7: =IF(B7="","",IF(M7<>"","Paid",IF(AND(I7<>"",I7<AsOf),"OVERDUE",IF(OR(K7<>"",L7<>""),"Invoiced","Scheduled")))) | P7: =IF(B7="","",IF(E7<>"",E7,IFERROR(INDEX('Contractors'!$D$6:$D$35,MATCH(B7,'Contractors'!$B$6:$B$35,0)),""))) | Q7: =IF(B7="","",IF(D7<>"",D7,IFERROR(INDEX('Contractors'!$E$6:$E$35,MATCH(B7,'Contractors'!$B$6:$B$35,0)),""))) | R7: =IF(O7="","",IF(O7="OVERDUE",2,IF(O7="Paid",0,IF(AND(I7<>"",I7<=AsOf+AlertDays),1,0)))) | S7: =IF(AND(B7<>"",M7="",I7<>""),IF(L7<>"",L7,IF(H7="",0,H7)),0) | T7: =IF(AND(B7<>"",M7="",I7<>""),1/I7,0) | U7: =IF(AND(B7<>"",M7="",I7<>""),I7,"") | V7: =IF(U7="","",IF(U7<AsOf,1,IF(U7<=AsOf+AlertDays,2,IF(U7<=AsOf+2*AlertDays,3,"")))) | W7: =IF(V7="","",IF(O7="OVERDUE","Overdue payment: ","Payment due: ")&B7&" — "&C7&" ("&CurSym&" "&FIXED(S7,0)&")") | Z7: =IF('Contractors'!B7="","",'Contractors'!B7) | AA7: =IF(Z7="","",'Contractors'!K7) | AB7: =IF(Z7="","",SUMIFS($L$6:$L$205,$B$6:$B$205,Z7)) | AC7: =IF(Z7="","",SUMIFS($N$6:$N$205,$B$6:$B$205,Z7)) | AD7: =IF(Z7="","",AA7-AC7) | AE7: =IF(Z7="","",IFERROR(1/SUMPRODUCT(MAX(($B$6:$B$205=Z7)*$T$6:$T$205)),"")) | AF7: =IF(AE7="","",SUMIFS($S$6:$S$205,$B$6:$B$205,Z7,$I$6:$I$205,AE7))
B8: GreenPlan Architects | C8: Permit approved 25% | F8: 0.25 | H8: =IF(B8="","",IF(G8<>"",G8,IF(F8<>"",F8*IFERROR(INDEX('Contractors'!$I$6:$I$35,MATCH(B8,'Contractors'!$B$6:$B$35,0)),0),""))) | I8: 46134 | J8: GP-02 | K8: 46132 | L8: 1200 | M8: 46133 | N8: 1200 | O8: =IF(B8="","",IF(M8<>"","Paid",IF(AND(I8<>"",I8<AsOf),"OVERDUE",IF(OR(K8<>"",L8<>""),"Invoiced","Scheduled")))) | P8: =IF(B8="","",IF(E8<>"",E8,IFERROR(INDEX('Contractors'!$D$6:$D$35,MATCH(B8,'Contractors'!$B$6:$B$35,0)),""))) | Q8: =IF(B8="","",IF(D8<>"",D8,IFERROR(INDEX('Contractors'!$E$6:$E$35,MATCH(B8,'Contractors'!$B$6:$B$35,0)),""))) | R8: =IF(O8="","",IF(O8="OVERDUE",2,IF(O8="Paid",0,IF(AND(I8<>"",I8<=AsOf+AlertDays),1,0)))) | S8: =IF(AND(B8<>"",M8="",I8<>""),IF(L8<>"",L8,IF(H8="",0,H8)),0) | T8: =IF(AND(B8<>"",M8="",I8<>""),1/I8,0) | U8: =IF(AND(B8<>"",M8="",I8<>""),I8,"") | V8: =IF(U8="","",IF(U8<AsOf,1,IF(U8<=AsOf+AlertDays,2,IF(U8<=AsOf+2*AlertDays,3,"")))) | W8: =IF(V8="","",IF(O8="OVERDUE","Overdue payment: ","Payment due: ")&B8&" — "&C8&" ("&CurSym&" "&FIXED(S8,0)&")") | Z8: =IF('Contractors'!B8="","",'Contractors'!B8) | AA8: =IF(Z8="","",'Contractors'!K8) | AB8: =IF(Z8="","",SUMIFS($L$6:$L$205,$B$6:$B$205,Z8)) | AC8: =IF(Z8="","",SUMIFS($N$6:$N$205,$B$6:$B$205,Z8)) | AD8: =IF(Z8="","",AA8-AC8) | AE8: =IF(Z8="","",IFERROR(1/SUMPRODUCT(MAX(($B$6:$B$205=Z8)*$T$6:$T$205)),"")) | AF8: =IF(AE8="","",SUMIFS($S$6:$S$205,$B$6:$B$205,Z8,$I$6:$I$205,AE8))
B9: ClearView Windows | C9: Order 40% | F9: 0.4 | H9: =IF(B9="","",IF(G9<>"",G9,IF(F9<>"",F9*IFERROR(INDEX('Contractors'!$I$6:$I$35,MATCH(B9,'Contractors'!$B$6:$B$35,0)),0),""))) | I9: 46122 | J9: CV-311 | K9: 46118 | L9: 4960 | M9: 46121 | N9: 4960 | O9: =IF(B9="","",IF(M9<>"","Paid",IF(AND(I9<>"",I9<AsOf),"OVERDUE",IF(OR(K9<>"",L9<>""),"Invoiced","Scheduled")))) | P9: =IF(B9="","",IF(E9<>"",E9,IFERROR(INDEX('Contractors'!$D$6:$D$35,MATCH(B9,'Contractors'!$B$6:$B$35,0)),""))) | Q9: =IF(B9="","",IF(D9<>"",D9,IFERROR(INDEX('Contractors'!$E$6:$E$35,MATCH(B9,'Contractors'!$B$6:$B$35,0)),""))) | R9: =IF(O9="","",IF(O9="OVERDUE",2,IF(O9="Paid",0,IF(AND(I9<>"",I9<=AsOf+AlertDays),1,0)))) | S9: =IF(AND(B9<>"",M9="",I9<>""),IF(L9<>"",L9,IF(H9="",0,H9)),0) | T9: =IF(AND(B9<>"",M9="",I9<>""),1/I9,0) | U9: =IF(AND(B9<>"",M9="",I9<>""),I9,"") | V9: =IF(U9="","",IF(U9<AsOf,1,IF(U9<=AsOf+AlertDays,2,IF(U9<=AsOf+2*AlertDays,3,"")))) | W9: =IF(V9="","",IF(O9="OVERDUE","Overdue payment: ","Payment due: ")&B9&" — "&C9&" ("&CurSym&" "&FIXED(S9,0)&")") | Z9: =IF('Contractors'!B9="","",'Contractors'!B9) | AA9: =IF(Z9="","",'Contractors'!K9) | AB9: =IF(Z9="","",SUMIFS($L$6:$L$205,$B$6:$B$205,Z9)) | AC9: =IF(Z9="","",SUMIFS($N$6:$N$205,$B$6:$B$205,Z9)) | AD9: =IF(Z9="","",AA9-AC9) | AE9: =IF(Z9="","",IFERROR(1/SUMPRODUCT(MAX(($B$6:$B$205=Z9)*$T$6:$T$205)),"")) | AF9: =IF(AE9="","",SUMIFS($S$6:$S$205,$B$6:$B$205,Z9,$I$6:$I$205,AE9))
B10: Hansen Demolition | C10: Deposit 30% | F10: 0.3 | H10: =IF(B10="","",IF(G10<>"",G10,IF(F10<>"",F10*IFERROR(INDEX('Contractors'!$I$6:$I$35,MATCH(B10,'Contractors'!$B$6:$B$35,0)),0),""))) | I10: 46127 | J10: H-101 | K10: 46122 | L10: 1140 | M10: 46126 | N10: 1140 | O10: =IF(B10="","",IF(M10<>"","Paid",IF(AND(I10<>"",I10<AsOf),"OVERDUE",IF(OR(K10<>"",L10<>""),"Invoiced","Scheduled")))) | P10: =IF(B10="","",IF(E10<>"",E10,IFERROR(INDEX('Contractors'!$D$6:$D$35,MATCH(B10,'Contractors'!$B$6:$B$35,0)),""))) | Q10: =IF(B10="","",IF(D10<>"",D10,IFERROR(INDEX('Contractors'!$E$6:$E$35,MATCH(B10,'Contractors'!$B$6:$B$35,0)),""))) | R10: =IF(O10="","",IF(O10="OVERDUE",2,IF(O10="Paid",0,IF(AND(I10<>"",I10<=AsOf+AlertDays),1,0)))) | S10: =IF(AND(B10<>"",M10="",I10<>""),IF(L10<>"",L10,IF(H10="",0,H10)),0) | T10: =IF(AND(B10<>"",M10="",I10<>""),1/I10,0) | U10: =IF(AND(B10<>"",M10="",I10<>""),I10,"") | V10: =IF(U10="","",IF(U10<AsOf,1,IF(U10<=AsOf+AlertDays,2,IF(U10<=AsOf+2*AlertDays,3,"")))) | W10: =IF(V10="","",IF(O10="OVERDUE","Overdue payment: ","Payment due: ")&B10&" — "&C10&" ("&CurSym&" "&FIXED(S10,0)&")") | Z10: =IF('Contractors'!B10="","",'Contractors'!B10) | AA10: =IF(Z10="","",'Contractors'!K10) | AB10: =IF(Z10="","",SUMIFS($L$6:$L$205,$B$6:$B$205,Z10)) | AC10: =IF(Z10="","",SUMIFS($N$6:$N$205,$B$6:$B$205,Z10)) | AD10: =IF(Z10="","",AA10-AC10) | AE10: =IF(Z10="","",IFERROR(1/SUMPRODUCT(MAX(($B$6:$B$205=Z10)*$T$6:$T$205)),"")) | AF10: =IF(AE10="","",SUMIFS($S$6:$S$205,$B$6:$B$205,Z10,$I$6:$I$205,AE10))
B11: City Skips | C11: Skip hire (2 skips) | E11: Waste removal | G11: 640 | H11: =IF(B11="","",IF(G11<>"",G11,IF(F11<>"",F11*IFERROR(INDEX('Contractors'!$I$6:$I$35,MATCH(B11,'Contractors'!$B$6:$B$35,0)),0),""))) | I11: 46134 | J11: CS-88 | K11: 46132 | L11: 640 | M11: 46134 | N11: 640 | O11: =IF(B11="","",IF(M11<>"","Paid",IF(AND(I11<>"",I11<AsOf),"OVERDUE",IF(OR(K11<>"",L11<>""),"Invoiced","Scheduled")))) | P11: =IF(B11="","",IF(E11<>"",E11,IFERROR(INDEX('Contractors'!$D$6:$D$35,MATCH(B11,'Contractors'!$B$6:$B$35,0)),""))) | Q11: =IF(B11="","",IF(D11<>"",D11,IFERROR(INDEX('Contractors'!$E$6:$E$35,MATCH(B11,'Contractors'!$B$6:$B$35,0)),""))) | R11: =IF(O11="","",IF(O11="OVERDUE",2,IF(O11="Paid",0,IF(AND(I11<>"",I11<=AsOf+AlertDays),1,0)))) | S11: =IF(AND(B11<>"",M11="",I11<>""),IF(L11<>"",L11,IF(H11="",0,H11)),0) | T11: =IF(AND(B11<>"",M11="",I11<>""),1/I11,0) | U11: =IF(AND(B11<>"",M11="",I11<>""),I11,"") | V11: =IF(U11="","",IF(U11<AsOf,1,IF(U11<=AsOf+AlertDays,2,IF(U11<=AsOf+2*AlertDays,3,"")))) | W11: =IF(V11="","",IF(O11="OVERDUE","Overdue payment: ","Payment due: ")&B11&" — "&C11&" ("&CurSym&" "&FIXED(S11,0)&")") | Z11: =IF('Contractors'!B11="","",'Contractors'!B11) | AA11: =IF(Z11="","",'Contractors'!K11) | AB11: =IF(Z11="","",SUMIFS($L$6:$L$205,$B$6:$B$205,Z11)) | AC11: =IF(Z11="","",SUMIFS($N$6:$N$205,$B$6:$B$205,Z11)) | AD11: =IF(Z11="","",AA11-AC11) | AE11: =IF(Z11="","",IFERROR(1/SUMPRODUCT(MAX(($B$6:$B$205=Z11)*$T$6:$T$205)),"")) | AF11: =IF(AE11="","",SUMIFS($S$6:$S$205,$B$6:$B$205,Z11,$I$6:$I$205,AE11))
B12: Solid Structures Ltd | C12: Deposit 30% | F12: 0.3 | H12: =IF(B12="","",IF(G12<>"",G12,IF(F12<>"",F12*IFERROR(INDEX('Contractors'!$I$6:$I$35,MATCH(B12,'Contractors'!$B$6:$B$35,0)),0),""))) | I12: 46137 | J12: SS-12 | K12: 46133 | L12: 2820 | M12: 46136 | N12: 2820 | O12: =IF(B12="","",IF(M12<>"","Paid",IF(AND(I12<>"",I12<AsOf),"OVERDUE",IF(OR(K12<>"",L12<>""),"Invoiced","Scheduled")))) | P12: =IF(B12="","",IF(E12<>"",E12,IFERROR(INDEX('Contractors'!$D$6:$D$35,MATCH(B12,'Contractors'!$B$6:$B$35,0)),""))) | Q12: =IF(B12="","",IF(D12<>"",D12,IFERROR(INDEX('Contractors'!$E$6:$E$35,MATCH(B12,'Contractors'!$B$6:$B$35,0)),""))) | R12: =IF(O12="","",IF(O12="OVERDUE",2,IF(O12="Paid",0,IF(AND(I12<>"",I12<=AsOf+AlertDays),1,0)))) | S12: =IF(AND(B12<>"",M12="",I12<>""),IF(L12<>"",L12,IF(H12="",0,H12)),0) | T12: =IF(AND(B12<>"",M12="",I12<>""),1/I12,0) | U12: =IF(AND(B12<>"",M12="",I12<>""),I12,"") | V12: =IF(U12="","",IF(U12<AsOf,1,IF(U12<=AsOf+AlertDays,2,IF(U12<=AsOf+2*AlertDays,3,"")))) | W12: =IF(V12="","",IF(O12="OVERDUE","Overdue payment: ","Payment due: ")&B12&" — "&C12&" ("&CurSym&" "&FIXED(S12,0)&")") | Z12: =IF('Contractors'!B12="","",'Contractors'!B12) | AA12: =IF(Z12="","",'Contractors'!K12) | AB12: =IF(Z12="","",SUMIFS($L$6:$L$205,$B$6:$B$205,Z12)) | AC12: =IF(Z12="","",SUMIFS($N$6:$N$205,$B$6:$B$205,Z12)) | AD12: =IF(Z12="","",AA12-AC12) | AE12: =IF(Z12="","",IFERROR(1/SUMPRODUCT(MAX(($B$6:$B$205=Z12)*$T$6:$T$205)),"")) | AF12: =IF(AE12="","",SUMIFS($S$6:$S$205,$B$6:$B$205,Z12,$I$6:$I$205,AE12))
B13: Hansen Demolition | C13: Completion 70% | F13: 0.7 | H13: =IF(B13="","",IF(G13<>"",G13,IF(F13<>"",F13*IFERROR(INDEX('Contractors'!$I$6:$I$35,MATCH(B13,'Contractors'!$B$6:$B$35,0)),0),""))) | I13: 46147 | J13: H-107 | K13: 46142 | L13: 2660 | M13: 46146 | N13: 2660 | O13: =IF(B13="","",IF(M13<>"","Paid",IF(AND(I13<>"",I13<AsOf),"OVERDUE",IF(OR(K13<>"",L13<>""),"Invoiced","Scheduled")))) | P13: =IF(B13="","",IF(E13<>"",E13,IFERROR(INDEX('Contractors'!$D$6:$D$35,MATCH(B13,'Contractors'!$B$6:$B$35,0)),""))) | Q13: =IF(B13="","",IF(D13<>"",D13,IFERROR(INDEX('Contractors'!$E$6:$E$35,MATCH(B13,'Contractors'!$B$6:$B$35,0)),""))) | R13: =IF(O13="","",IF(O13="OVERDUE",2,IF(O13="Paid",0,IF(AND(I13<>"",I13<=AsOf+AlertDays),1,0)))) | S13: =IF(AND(B13<>"",M13="",I13<>""),IF(L13<>"",L13,IF(H13="",0,H13)),0) | T13: =IF(AND(B13<>"",M13="",I13<>""),1/I13,0) | U13: =IF(AND(B13<>"",M13="",I13<>""),I13,"") | V13: =IF(U13="","",IF(U13<AsOf,1,IF(U13<=AsOf+AlertDays,2,IF(U13<=AsOf+2*AlertDays,3,"")))) | W13: =IF(V13="","",IF(O13="OVERDUE","Overdue payment: ","Payment due: ")&B13&" — "&C13&" ("&CurSym&" "&FIXED(S13,0)&")") | Z13: =IF('Contractors'!B13="","",'Contractors'!B13) | AA13: =IF(Z13="","",'Contractors'!K13) | AB13: =IF(Z13="","",SUMIFS($L$6:$L$205,$B$6:$B$205,Z13)) | AC13: =IF(Z13="","",SUMIFS($N$6:$N$205,$B$6:$B$205,Z13)) | AD13: =IF(Z13="","",AA13-AC13) | AE13: =IF(Z13="","",IFERROR(1/SUMPRODUCT(MAX(($B$6:$B$205=Z13)*$T$6:$T$205)),"")) | AF13: =IF(AE13="","",SUMIFS($S$6:$S$205,$B$6:$B$205,Z13,$I$6:$I$205,AE13))
B14: Bright Spark Electric | C14: Deposit 30% | F14: 0.3 | H14: =IF(B14="","",IF(G14<>"",G14,IF(F14<>"",F14*IFERROR(INDEX('Contractors'!$I$6:$I$35,MATCH(B14,'Contractors'!$B$6:$B$35,0)),0),""))) | I14: 46150 | J14: BS-2026-04 | K14: 46146 | L14: 3150 | M14: 46149 | N14: 3150 | O14: =IF(B14="","",IF(M14<>"","Paid",IF(AND(I14<>"",I14<AsOf),"OVERDUE",IF(OR(K14<>"",L14<>""),"Invoiced","Scheduled")))) | P14: =IF(B14="","",IF(E14<>"",E14,IFERROR(INDEX('Contractors'!$D$6:$D$35,MATCH(B14,'Contractors'!$B$6:$B$35,0)),""))) | Q14: =IF(B14="","",IF(D14<>"",D14,IFERROR(INDEX('Contractors'!$E$6:$E$35,MATCH(B14,'Contractors'!$B$6:$B$35,0)),""))) | R14: =IF(O14="","",IF(O14="OVERDUE",2,IF(O14="Paid",0,IF(AND(I14<>"",I14<=AsOf+AlertDays),1,0)))) | S14: =IF(AND(B14<>"",M14="",I14<>""),IF(L14<>"",L14,IF(H14="",0,H14)),0) | T14: =IF(AND(B14<>"",M14="",I14<>""),1/I14,0) | U14: =IF(AND(B14<>"",M14="",I14<>""),I14,"") | V14: =IF(U14="","",IF(U14<AsOf,1,IF(U14<=AsOf+AlertDays,2,IF(U14<=AsOf+2*AlertDays,3,"")))) | W14: =IF(V14="","",IF(O14="OVERDUE","Overdue payment: ","Payment due: ")&B14&" — "&C14&" ("&CurSym&" "&FIXED(S14,0)&")") | Z14: =IF('Contractors'!B14="","",'Contractors'!B14) | AA14: =IF(Z14="","",'Contractors'!K14) | AB14: =IF(Z14="","",SUMIFS($L$6:$L$205,$B$6:$B$205,Z14)) | AC14: =IF(Z14="","",SUMIFS($N$6:$N$205,$B$6:$B$205,Z14)) | AD14: =IF(Z14="","",AA14-AC14) | AE14: =IF(Z14="","",IFERROR(1/SUMPRODUCT(MAX(($B$6:$B$205=Z14)*$T$6:$T$205)),"")) | AF14: =IF(AE14="","",SUMIFS($S$6:$S$205,$B$6:$B$205,Z14,$I$6:$I$205,AE14))
B15: FlowRight Plumbing | C15: Start of works 30% | F15: 0.3 | H15: =IF(B15="","",IF(G15<>"",G15,IF(F15<>"",F15*IFERROR(INDEX('Contractors'!$I$6:$I$35,MATCH(B15,'Contractors'!$B$6:$B$35,0)),0),""))) | I15: 46154 | J15: FR-5501 | K15: 46150 | L15: 2760 | M15: 46153 | N15: 2760 | O15: =IF(B15="","",IF(M15<>"","Paid",IF(AND(I15<>"",I15<AsOf),"OVERDUE",IF(OR(K15<>"",L15<>""),"Invoiced","Scheduled")))) | P15: =IF(B15="","",IF(E15<>"",E15,IFERROR(INDEX('Contractors'!$D$6:$D$35,MATCH(B15,'Contractors'!$B$6:$B$35,0)),""))) | Q15: =IF(B15="","",IF(D15<>"",D15,IFERROR(INDEX('Contractors'!$E$6:$E$35,MATCH(B15,'Contractors'!$B$6:$B$35,0)),""))) | R15: =IF(O15="","",IF(O15="OVERDUE",2,IF(O15="Paid",0,IF(AND(I15<>"",I15<=AsOf+AlertDays),1,0)))) | S15: =IF(AND(B15<>"",M15="",I15<>""),IF(L15<>"",L15,IF(H15="",0,H15)),0) | T15: =IF(AND(B15<>"",M15="",I15<>""),1/I15,0) | U15: =IF(AND(B15<>"",M15="",I15<>""),I15,"") | V15: =IF(U15="","",IF(U15<AsOf,1,IF(U15<=AsOf+AlertDays,2,IF(U15<=AsOf+2*AlertDays,3,"")))) | W15: =IF(V15="","",IF(O15="OVERDUE","Overdue payment: ","Payment due: ")&B15&" — "&C15&" ("&CurSym&" "&FIXED(S15,0)&")") | Z15: =IF('Contractors'!B15="","",'Contractors'!B15) | AA15: =IF(Z15="","",'Contractors'!K15) | AB15: =IF(Z15="","",SUMIFS($L$6:$L$205,$B$6:$B$205,Z15)) | AC15: =IF(Z15="","",SUMIFS($N$6:$N$205,$B$6:$B$205,Z15)) | AD15: =IF(Z15="","",AA15-AC15) | AE15: =IF(Z15="","",IFERROR(1/SUMPRODUCT(MAX(($B$6:$B$205=Z15)*$T$6:$T$205)),"")) | AF15: =IF(AE15="","",SUMIFS($S$6:$S$205,$B$6:$B$205,Z15,$I$6:$I$205,AE15))
B16: Nordic Kitchens | C16: Deposit 10% | D16: Kitchen | F16: 0.1 | H16: =IF(B16="","",IF(G16<>"",G16,IF(F16<>"",F16*IFERROR(INDEX('Contractors'!$I$6:$I$35,MATCH(B16,'Contractors'!$B$6:$B$35,0)),0),""))) | I16: 46157 | J16: NK-778 | K16: 46153 | L16: 1940 | M16: 46156 | N16: 1940 | O16: =IF(B16="","",IF(M16<>"","Paid",IF(AND(I16<>"",I16<AsOf),"OVERDUE",IF(OR(K16<>"",L16<>""),"Invoiced","Scheduled")))) | P16: =IF(B16="","",IF(E16<>"",E16,IFERROR(INDEX('Contractors'!$D$6:$D$35,MATCH(B16,'Contractors'!$B$6:$B$35,0)),""))) | Q16: =IF(B16="","",IF(D16<>"",D16,IFERROR(INDEX('Contractors'!$E$6:$E$35,MATCH(B16,'Contractors'!$B$6:$B$35,0)),""))) | R16: =IF(O16="","",IF(O16="OVERDUE",2,IF(O16="Paid",0,IF(AND(I16<>"",I16<=AsOf+AlertDays),1,0)))) | S16: =IF(AND(B16<>"",M16="",I16<>""),IF(L16<>"",L16,IF(H16="",0,H16)),0) | T16: =IF(AND(B16<>"",M16="",I16<>""),1/I16,0) | U16: =IF(AND(B16<>"",M16="",I16<>""),I16,"") | V16: =IF(U16="","",IF(U16<AsOf,1,IF(U16<=AsOf+AlertDays,2,IF(U16<=AsOf+2*AlertDays,3,"")))) | W16: =IF(V16="","",IF(O16="OVERDUE","Overdue payment: ","Payment due: ")&B16&" — "&C16&" ("&CurSym&" "&FIXED(S16,0)&")") | Z16: =IF('Contractors'!B16="","",'Contractors'!B16) | AA16: =IF(Z16="","",'Contractors'!K16) | AB16: =IF(Z16="","",SUMIFS($L$6:$L$205,$B$6:$B$205,Z16)) | AC16: =IF(Z16="","",SUMIFS($N$6:$N$205,$B$6:$B$205,Z16)) | AD16: =IF(Z16="","",AA16-AC16) | AE16: =IF(Z16="","",IFERROR(1/SUMPRODUCT(MAX(($B$6:$B$205=Z16)*$T$6:$T$205)),"")) | AF16: =IF(AE16="","",SUMIFS($S$6:$S$205,$B$6:$B$205,Z16,$I$6:$I$205,AE16))
B17: ClearView Windows | C17: Installation 50% | F17: 0.5 | H17: =IF(B17="","",IF(G17<>"",G17,IF(F17<>"",F17*IFERROR(INDEX('Contractors'!$I$6:$I$35,MATCH(B17,'Contractors'!$B$6:$B$35,0)),0),""))) | I17: 46157 | J17: CV-340 | K17: 46150 | L17: 6200 | M17: 46156 | N17: 6200 | O17: =IF(B17="","",IF(M17<>"","Paid",IF(AND(I17<>"",I17<AsOf),"OVERDUE",IF(OR(K17<>"",L17<>""),"Invoiced","Scheduled")))) | P17: =IF(B17="","",IF(E17<>"",E17,IFERROR(INDEX('Contractors'!$D$6:$D$35,MATCH(B17,'Contractors'!$B$6:$B$35,0)),""))) | Q17: =IF(B17="","",IF(D17<>"",D17,IFERROR(INDEX('Contractors'!$E$6:$E$35,MATCH(B17,'Contractors'!$B$6:$B$35,0)),""))) | R17: =IF(O17="","",IF(O17="OVERDUE",2,IF(O17="Paid",0,IF(AND(I17<>"",I17<=AsOf+AlertDays),1,0)))) | S17: =IF(AND(B17<>"",M17="",I17<>""),IF(L17<>"",L17,IF(H17="",0,H17)),0) | T17: =IF(AND(B17<>"",M17="",I17<>""),1/I17,0) | U17: =IF(AND(B17<>"",M17="",I17<>""),I17,"") | V17: =IF(U17="","",IF(U17<AsOf,1,IF(U17<=AsOf+AlertDays,2,IF(U17<=AsOf+2*AlertDays,3,"")))) | W17: =IF(V17="","",IF(O17="OVERDUE","Overdue payment: ","Payment due: ")&B17&" — "&C17&" ("&CurSym&" "&FIXED(S17,0)&")") | Z17: =IF('Contractors'!B17="","",'Contractors'!B17) | AA17: =IF(Z17="","",'Contractors'!K17) | AB17: =IF(Z17="","",SUMIFS($L$6:$L$205,$B$6:$B$205,Z17)) | AC17: =IF(Z17="","",SUMIFS($N$6:$N$205,$B$6:$B$205,Z17)) | AD17: =IF(Z17="","",AA17-AC17) | AE17: =IF(Z17="","",IFERROR(1/SUMPRODUCT(MAX(($B$6:$B$205=Z17)*$T$6:$T$205)),"")) | AF17: =IF(AE17="","",SUMIFS($S$6:$S$205,$B$6:$B$205,Z17,$I$6:$I$205,AE17))
B18: Solid Structures Ltd | C18: Completion 70% | F18: 0.7 | H18: =IF(B18="","",IF(G18<>"",G18,IF(F18<>"",F18*IFERROR(INDEX('Contractors'!$I$6:$I$35,MATCH(B18,'Contractors'!$B$6:$B$35,0)),0),""))) | I18: 46162 | J18: SS-19 | K18: 46154 | L18: 6580 | M18: 46161 | N18: 6580 | O18: =IF(B18="","",IF(M18<>"","Paid",IF(AND(I18<>"",I18<AsOf),"OVERDUE",IF(OR(K18<>"",L18<>""),"Invoiced","Scheduled")))) | P18: =IF(B18="","",IF(E18<>"",E18,IFERROR(INDEX('Contractors'!$D$6:$D$35,MATCH(B18,'Contractors'!$B$6:$B$35,0)),""))) | Q18: =IF(B18="","",IF(D18<>"",D18,IFERROR(INDEX('Contractors'!$E$6:$E$35,MATCH(B18,'Contractors'!$B$6:$B$35,0)),""))) | R18: =IF(O18="","",IF(O18="OVERDUE",2,IF(O18="Paid",0,IF(AND(I18<>"",I18<=AsOf+AlertDays),1,0)))) | S18: =IF(AND(B18<>"",M18="",I18<>""),IF(L18<>"",L18,IF(H18="",0,H18)),0) | T18: =IF(AND(B18<>"",M18="",I18<>""),1/I18,0) | U18: =IF(AND(B18<>"",M18="",I18<>""),I18,"") | V18: =IF(U18="","",IF(U18<AsOf,1,IF(U18<=AsOf+AlertDays,2,IF(U18<=AsOf+2*AlertDays,3,"")))) | W18: =IF(V18="","",IF(O18="OVERDUE","Overdue payment: ","Payment due: ")&B18&" — "&C18&" ("&CurSym&" "&FIXED(S18,0)&")") | Z18: =IF('Contractors'!B18="","",'Contractors'!B18) | AA18: =IF(Z18="","",'Contractors'!K18) | AB18: =IF(Z18="","",SUMIFS($L$6:$L$205,$B$6:$B$205,Z18)) | AC18: =IF(Z18="","",SUMIFS($N$6:$N$205,$B$6:$B$205,Z18)) | AD18: =IF(Z18="","",AA18-AC18) | AE18: =IF(Z18="","",IFERROR(1/SUMPRODUCT(MAX(($B$6:$B$205=Z18)*$T$6:$T$205)),"")) | AF18: =IF(AE18="","",SUMIFS($S$6:$S$205,$B$6:$B$205,Z18,$I$6:$I$205,AE18))
B19: Solid Structures Ltd | C19: Change order CO-1 (steel beam) | G19: 1200 | H19: =IF(B19="","",IF(G19<>"",G19,IF(F19<>"",F19*IFERROR(INDEX('Contractors'!$I$6:$I$35,MATCH(B19,'Contractors'!$B$6:$B$35,0)),0),""))) | I19: 46167 | J19: SS-20 | K19: 46160 | L19: 1200 | M19: 46167 | N19: 1200 | O19: =IF(B19="","",IF(M19<>"","Paid",IF(AND(I19<>"",I19<AsOf),"OVERDUE",IF(OR(K19<>"",L19<>""),"Invoiced","Scheduled")))) | P19: =IF(B19="","",IF(E19<>"",E19,IFERROR(INDEX('Contractors'!$D$6:$D$35,MATCH(B19,'Contractors'!$B$6:$B$35,0)),""))) | Q19: =IF(B19="","",IF(D19<>"",D19,IFERROR(INDEX('Contractors'!$E$6:$E$35,MATCH(B19,'Contractors'!$B$6:$B$35,0)),""))) | R19: =IF(O19="","",IF(O19="OVERDUE",2,IF(O19="Paid",0,IF(AND(I19<>"",I19<=AsOf+AlertDays),1,0)))) | S19: =IF(AND(B19<>"",M19="",I19<>""),IF(L19<>"",L19,IF(H19="",0,H19)),0) | T19: =IF(AND(B19<>"",M19="",I19<>""),1/I19,0) | U19: =IF(AND(B19<>"",M19="",I19<>""),I19,"") | V19: =IF(U19="","",IF(U19<AsOf,1,IF(U19<=AsOf+AlertDays,2,IF(U19<=AsOf+2*AlertDays,3,"")))) | W19: =IF(V19="","",IF(O19="OVERDUE","Overdue payment: ","Payment due: ")&B19&" — "&C19&" ("&CurSym&" "&FIXED(S19,0)&")") | Z19: =IF('Contractors'!B19="","",'Contractors'!B19) | AA19: =IF(Z19="","",'Contractors'!K19) | AB19: =IF(Z19="","",SUMIFS($L$6:$L$205,$B$6:$B$205,Z19)) | AC19: =IF(Z19="","",SUMIFS($N$6:$N$205,$B$6:$B$205,Z19)) | AD19: =IF(Z19="","",AA19-AC19) | AE19: =IF(Z19="","",IFERROR(1/SUMPRODUCT(MAX(($B$6:$B$205=Z19)*$T$6:$T$205)),"")) | AF19: =IF(AE19="","",SUMIFS($S$6:$S$205,$B$6:$B$205,Z19,$I$6:$I$205,AE19))
B20: Bright Spark Electric | C20: First fix 30% | F20: 0.3 | H20: =IF(B20="","",IF(G20<>"",G20,IF(F20<>"",F20*IFERROR(INDEX('Contractors'!$I$6:$I$35,MATCH(B20,'Contractors'!$B$6:$B$35,0)),0),""))) | I20: 46174 | J20: BS-2026-07 | K20: 46168 | L20: 3150 | M20: 46172 | N20: 3150 | O20: =IF(B20="","",IF(M20<>"","Paid",IF(AND(I20<>"",I20<AsOf),"OVERDUE",IF(OR(K20<>"",L20<>""),"Invoiced","Scheduled")))) | P20: =IF(B20="","",IF(E20<>"",E20,IFERROR(INDEX('Contractors'!$D$6:$D$35,MATCH(B20,'Contractors'!$B$6:$B$35,0)),""))) | Q20: =IF(B20="","",IF(D20<>"",D20,IFERROR(INDEX('Contractors'!$E$6:$E$35,MATCH(B20,'Contractors'!$B$6:$B$35,0)),""))) | R20: =IF(O20="","",IF(O20="OVERDUE",2,IF(O20="Paid",0,IF(AND(I20<>"",I20<=AsOf+AlertDays),1,0)))) | S20: =IF(AND(B20<>"",M20="",I20<>""),IF(L20<>"",L20,IF(H20="",0,H20)),0) | T20: =IF(AND(B20<>"",M20="",I20<>""),1/I20,0) | U20: =IF(AND(B20<>"",M20="",I20<>""),I20,"") | V20: =IF(U20="","",IF(U20<AsOf,1,IF(U20<=AsOf+AlertDays,2,IF(U20<=AsOf+2*AlertDays,3,"")))) | W20: =IF(V20="","",IF(O20="OVERDUE","Overdue payment: ","Payment due: ")&B20&" — "&C20&" ("&CurSym&" "&FIXED(S20,0)&")") | Z20: =IF('Contractors'!B20="","",'Contractors'!B20) | AA20: =IF(Z20="","",'Contractors'!K20) | AB20: =IF(Z20="","",SUMIFS($L$6:$L$205,$B$6:$B$205,Z20)) | AC20: =IF(Z20="","",SUMIFS($N$6:$N$205,$B$6:$B$205,Z20)) | AD20: =IF(Z20="","",AA20-AC20) | AE20: =IF(Z20="","",IFERROR(1/SUMPRODUCT(MAX(($B$6:$B$205=Z20)*$T$6:$T$205)),"")) | AF20: =IF(AE20="","",SUMIFS($S$6:$S$205,$B$6:$B$205,Z20,$I$6:$I$205,AE20))
B21: ClimaHeat HVAC | C21: Equipment 30% | F21: 0.3 | H21: =IF(B21="","",IF(G21<>"",G21,IF(F21<>"",F21*IFERROR(INDEX('Contractors'!$I$6:$I$35,MATCH(B21,'Contractors'!$B$6:$B$35,0)),0),""))) | I21: 46178 | J21: CH-90 | K21: 46174 | L21: 2790 | M21: 46177 | N21: 2790 | O21: =IF(B21="","",IF(M21<>"","Paid",IF(AND(I21<>"",I21<AsOf),"OVERDUE",IF(OR(K21<>"",L21<>""),"Invoiced","Scheduled")))) | P21: =IF(B21="","",IF(E21<>"",E21,IFERROR(INDEX('Contractors'!$D$6:$D$35,MATCH(B21,'Contractors'!$B$6:$B$35,0)),""))) | Q21: =IF(B21="","",IF(D21<>"",D21,IFERROR(INDEX('Contractors'!$E$6:$E$35,MATCH(B21,'Contractors'!$B$6:$B$35,0)),""))) | R21: =IF(O21="","",IF(O21="OVERDUE",2,IF(O21="Paid",0,IF(AND(I21<>"",I21<=AsOf+AlertDays),1,0)))) | S21: =IF(AND(B21<>"",M21="",I21<>""),IF(L21<>"",L21,IF(H21="",0,H21)),0) | T21: =IF(AND(B21<>"",M21="",I21<>""),1/I21,0) | U21: =IF(AND(B21<>"",M21="",I21<>""),I21,"") | V21: =IF(U21="","",IF(U21<AsOf,1,IF(U21<=AsOf+AlertDays,2,IF(U21<=AsOf+2*AlertDays,3,"")))) | W21: =IF(V21="","",IF(O21="OVERDUE","Overdue payment: ","Payment due: ")&B21&" — "&C21&" ("&CurSym&" "&FIXED(S21,0)&")") | Z21: =IF('Contractors'!B21="","",'Contractors'!B21) | AA21: =IF(Z21="","",'Contractors'!K21) | AB21: =IF(Z21="","",SUMIFS($L$6:$L$205,$B$6:$B$205,Z21)) | AC21: =IF(Z21="","",SUMIFS($N$6:$N$205,$B$6:$B$205,Z21)) | AD21: =IF(Z21="","",AA21-AC21) | AE21: =IF(Z21="","",IFERROR(1/SUMPRODUCT(MAX(($B$6:$B$205=Z21)*$T$6:$T$205)),"")) | AF21: =IF(AE21="","",SUMIFS($S$6:$S$205,$B$6:$B$205,Z21,$I$6:$I$205,AE21))
B22: FlowRight Plumbing | C22: Rough-in complete 40% | F22: 0.4 | H22: =IF(B22="","",IF(G22<>"",G22,IF(F22<>"",F22*IFERROR(INDEX('Contractors'!$I$6:$I$35,MATCH(B22,'Contractors'!$B$6:$B$35,0)),0),""))) | I22: 46183 | J22: FR-5534 | K22: 46174 | L22: 3680 | O22: =IF(B22="","",IF(M22<>"","Paid",IF(AND(I22<>"",I22<AsOf),"OVERDUE",IF(OR(K22<>"",L22<>""),"Invoiced","Scheduled")))) | P22: =IF(B22="","",IF(E22<>"",E22,IFERROR(INDEX('Contractors'!$D$6:$D$35,MATCH(B22,'Contractors'!$B$6:$B$35,0)),""))) | Q22: =IF(B22="","",IF(D22<>"",D22,IFERROR(INDEX('Contractors'!$E$6:$E$35,MATCH(B22,'Contractors'!$B$6:$B$35,0)),""))) | R22: =IF(O22="","",IF(O22="OVERDUE",2,IF(O22="Paid",0,IF(AND(I22<>"",I22<=AsOf+AlertDays),1,0)))) | S22: =IF(AND(B22<>"",M22="",I22<>""),IF(L22<>"",L22,IF(H22="",0,H22)),0) | T22: =IF(AND(B22<>"",M22="",I22<>""),1/I22,0) | U22: =IF(AND(B22<>"",M22="",I22<>""),I22,"") | V22: =IF(U22="","",IF(U22<AsOf,1,IF(U22<=AsOf+AlertDays,2,IF(U22<=AsOf+2*AlertDays,3,"")))) | W22: =IF(V22="","",IF(O22="OVERDUE","Overdue payment: ","Payment due: ")&B22&" — "&C22&" ("&CurSym&" "&FIXED(S22,0)&")") | Z22: =IF('Contractors'!B22="","",'Contractors'!B22) | AA22: =IF(Z22="","",'Contractors'!K22) | AB22: =IF(Z22="","",SUMIFS($L$6:$L$205,$B$6:$B$205,Z22)) | AC22: =IF(Z22="","",SUMIFS($N$6:$N$205,$B$6:$B$205,Z22)) | AD22: =IF(Z22="","",AA22-AC22) | AE22: =IF(Z22="","",IFERROR(1/SUMPRODUCT(MAX(($B$6:$B$205=Z22)*$T$6:$T$205)),"")) | AF22: =IF(AE22="","",SUMIFS($S$6:$S$205,$B$6:$B$205,Z22,$I$6:$I$205,AE22))
B23: Aqua Bath Studio | C23: Deposit 20% | F23: 0.2 | H23: =IF(B23="","",IF(G23<>"",G23,IF(F23<>"",F23*IFERROR(INDEX('Contractors'!$I$6:$I$35,MATCH(B23,'Contractors'!$B$6:$B$35,0)),0),""))) | I23: 46192 | J23: ABS-301 | K23: 46185 | L23: 2240 | O23: =IF(B23="","",IF(M23<>"","Paid",IF(AND(I23<>"",I23<AsOf),"OVERDUE",IF(OR(K23<>"",L23<>""),"Invoiced","Scheduled")))) | P23: =IF(B23="","",IF(E23<>"",E23,IFERROR(INDEX('Contractors'!$D$6:$D$35,MATCH(B23,'Contractors'!$B$6:$B$35,0)),""))) | Q23: =IF(B23="","",IF(D23<>"",D23,IFERROR(INDEX('Contractors'!$E$6:$E$35,MATCH(B23,'Contractors'!$B$6:$B$35,0)),""))) | R23: =IF(O23="","",IF(O23="OVERDUE",2,IF(O23="Paid",0,IF(AND(I23<>"",I23<=AsOf+AlertDays),1,0)))) | S23: =IF(AND(B23<>"",M23="",I23<>""),IF(L23<>"",L23,IF(H23="",0,H23)),0) | T23: =IF(AND(B23<>"",M23="",I23<>""),1/I23,0) | U23: =IF(AND(B23<>"",M23="",I23<>""),I23,"") | V23: =IF(U23="","",IF(U23<AsOf,1,IF(U23<=AsOf+AlertDays,2,IF(U23<=AsOf+2*AlertDays,3,"")))) | W23: =IF(V23="","",IF(O23="OVERDUE","Overdue payment: ","Payment due: ")&B23&" — "&C23&" ("&CurSym&" "&FIXED(S23,0)&")") | Z23: =IF('Contractors'!B23="","",'Contractors'!B23) | AA23: =IF(Z23="","",'Contractors'!K23) | AB23: =IF(Z23="","",SUMIFS($L$6:$L$205,$B$6:$B$205,Z23)) | AC23: =IF(Z23="","",SUMIFS($N$6:$N$205,$B$6:$B$205,Z23)) | AD23: =IF(Z23="","",AA23-AC23) | AE23: =IF(Z23="","",IFERROR(1/SUMPRODUCT(MAX(($B$6:$B$205=Z23)*$T$6:$T$205)),"")) | AF23: =IF(AE23="","",SUMIFS($S$6:$S$205,$B$6:$B$205,Z23,$I$6:$I$205,AE23))
B24: ClearView Windows | C24: Final 10% (after snagging) | F24: 0.1 | H24: =IF(B24="","",IF(G24<>"",G24,IF(F24<>"",F24*IFERROR(INDEX('Contractors'!$I$6:$I$35,MATCH(B24,'Contractors'!$B$6:$B$35,0)),0),""))) | I24: 46193 | J24: CV-362 | K24: 46185 | L24: 1240 | O24: =IF(B24="","",IF(M24<>"","Paid",IF(AND(I24<>"",I24<AsOf),"OVERDUE",IF(OR(K24<>"",L24<>""),"Invoiced","Scheduled")))) | P24: =IF(B24="","",IF(E24<>"",E24,IFERROR(INDEX('Contractors'!$D$6:$D$35,MATCH(B24,'Contractors'!$B$6:$B$35,0)),""))) | Q24: =IF(B24="","",IF(D24<>"",D24,IFERROR(INDEX('Contractors'!$E$6:$E$35,MATCH(B24,'Contractors'!$B$6:$B$35,0)),""))) | R24: =IF(O24="","",IF(O24="OVERDUE",2,IF(O24="Paid",0,IF(AND(I24<>"",I24<=AsOf+AlertDays),1,0)))) | S24: =IF(AND(B24<>"",M24="",I24<>""),IF(L24<>"",L24,IF(H24="",0,H24)),0) | T24: =IF(AND(B24<>"",M24="",I24<>""),1/I24,0) | U24: =IF(AND(B24<>"",M24="",I24<>""),I24,"") | V24: =IF(U24="","",IF(U24<AsOf,1,IF(U24<=AsOf+AlertDays,2,IF(U24<=AsOf+2*AlertDays,3,"")))) | W24: =IF(V24="","",IF(O24="OVERDUE","Overdue payment: ","Payment due: ")&B24&" — "&C24&" ("&CurSym&" "&FIXED(S24,0)&")") | Z24: =IF('Contractors'!B24="","",'Contractors'!B24) | AA24: =IF(Z24="","",'Contractors'!K24) | AB24: =IF(Z24="","",SUMIFS($L$6:$L$205,$B$6:$B$205,Z24)) | AC24: =IF(Z24="","",SUMIFS($N$6:$N$205,$B$6:$B$205,Z24)) | AD24: =IF(Z24="","",AA24-AC24) | AE24: =IF(Z24="","",IFERROR(1/SUMPRODUCT(MAX(($B$6:$B$205=Z24)*$T$6:$T$205)),"")) | AF24: =IF(AE24="","",SUMIFS($S$6:$S$205,$B$6:$B$205,Z24,$I$6:$I$205,AE24))
B25: TileDepot | C25: Bathroom 1 tiles | D25: Bathroom 1 | E25: Bathrooms | G25: 1450 | H25: =IF(B25="","",IF(G25<>"",G25,IF(F25<>"",F25*IFERROR(INDEX('Contractors'!$I$6:$I$35,MATCH(B25,'Contractors'!$B$6:$B$35,0)),0),""))) | I25: 46188 | J25: TD-4471 | K25: 46185 | L25: 1450 | M25: 46188 | N25: 1450 | O25: =IF(B25="","",IF(M25<>"","Paid",IF(AND(I25<>"",I25<AsOf),"OVERDUE",IF(OR(K25<>"",L25<>""),"Invoiced","Scheduled")))) | P25: =IF(B25="","",IF(E25<>"",E25,IFERROR(INDEX('Contractors'!$D$6:$D$35,MATCH(B25,'Contractors'!$B$6:$B$35,0)),""))) | Q25: =IF(B25="","",IF(D25<>"",D25,IFERROR(INDEX('Contractors'!$E$6:$E$35,MATCH(B25,'Contractors'!$B$6:$B$35,0)),""))) | R25: =IF(O25="","",IF(O25="OVERDUE",2,IF(O25="Paid",0,IF(AND(I25<>"",I25<=AsOf+AlertDays),1,0)))) | S25: =IF(AND(B25<>"",M25="",I25<>""),IF(L25<>"",L25,IF(H25="",0,H25)),0) | T25: =IF(AND(B25<>"",M25="",I25<>""),1/I25,0) | U25: =IF(AND(B25<>"",M25="",I25<>""),I25,"") | V25: =IF(U25="","",IF(U25<AsOf,1,IF(U25<=AsOf+AlertDays,2,IF(U25<=AsOf+2*AlertDays,3,"")))) | W25: =IF(V25="","",IF(O25="OVERDUE","Overdue payment: ","Payment due: ")&B25&" — "&C25&" ("&CurSym&" "&FIXED(S25,0)&")") | Z25: =IF('Contractors'!B25="","",'Contractors'!B25) | AA25: =IF(Z25="","",'Contractors'!K25) | AB25: =IF(Z25="","",SUMIFS($L$6:$L$205,$B$6:$B$205,Z25)) | AC25: =IF(Z25="","",SUMIFS($N$6:$N$205,$B$6:$B$205,Z25)) | AD25: =IF(Z25="","",AA25-AC25) | AE25: =IF(Z25="","",IFERROR(1/SUMPRODUCT(MAX(($B$6:$B$205=Z25)*$T$6:$T$205)),"")) | AF25: =IF(AE25="","",SUMIFS($S$6:$S$205,$B$6:$B$205,Z25,$I$6:$I$205,AE25))
B26: StoneWorks | C26: Quartz worktop | D26: Kitchen | E26: Kitchen | G26: 2450 | H26: =IF(B26="","",IF(G26<>"",G26,IF(F26<>"",F26*IFERROR(INDEX('Contractors'!$I$6:$I$35,MATCH(B26,'Contractors'!$B$6:$B$35,0)),0),""))) | I26: 46198 | O26: =IF(B26="","",IF(M26<>"","Paid",IF(AND(I26<>"",I26<AsOf),"OVERDUE",IF(OR(K26<>"",L26<>""),"Invoiced","Scheduled")))) | P26: =IF(B26="","",IF(E26<>"",E26,IFERROR(INDEX('Contractors'!$D$6:$D$35,MATCH(B26,'Contractors'!$B$6:$B$35,0)),""))) | Q26: =IF(B26="","",IF(D26<>"",D26,IFERROR(INDEX('Contractors'!$E$6:$E$35,MATCH(B26,'Contractors'!$B$6:$B$35,0)),""))) | R26: =IF(O26="","",IF(O26="OVERDUE",2,IF(O26="Paid",0,IF(AND(I26<>"",I26<=AsOf+AlertDays),1,0)))) | S26: =IF(AND(B26<>"",M26="",I26<>""),IF(L26<>"",L26,IF(H26="",0,H26)),0) | T26: =IF(AND(B26<>"",M26="",I26<>""),1/I26,0) | U26: =IF(AND(B26<>"",M26="",I26<>""),I26,"") | V26: =IF(U26="","",IF(U26<AsOf,1,IF(U26<=AsOf+AlertDays,2,IF(U26<=AsOf+2*AlertDays,3,"")))) | W26: =IF(V26="","",IF(O26="OVERDUE","Overdue payment: ","Payment due: ")&B26&" — "&C26&" ("&CurSym&" "&FIXED(S26,0)&")") | Z26: =IF('Contractors'!B26="","",'Contractors'!B26) | AA26: =IF(Z26="","",'Contractors'!K26) | AB26: =IF(Z26="","",SUMIFS($L$6:$L$205,$B$6:$B$205,Z26)) | AC26: =IF(Z26="","",SUMIFS($N$6:$N$205,$B$6:$B$205,Z26)) | AD26: =IF(Z26="","",AA26-AC26) | AE26: =IF(Z26="","",IFERROR(1/SUMPRODUCT(MAX(($B$6:$B$205=Z26)*$T$6:$T$205)),"")) | AF26: =IF(AE26="","",SUMIFS($S$6:$S$205,$B$6:$B$205,Z26,$I$6:$I$205,AE26))
B27: Nordic Kitchens | C27: Delivery 50% | D27: Kitchen | F27: 0.5 | H27: =IF(B27="","",IF(G27<>"",G27,IF(F27<>"",F27*IFERROR(INDEX('Contractors'!$I$6:$I$35,MATCH(B27,'Contractors'!$B$6:$B$35,0)),0),""))) | I27: 46202 | O27: =IF(B27="","",IF(M27<>"","Paid",IF(AND(I27<>"",I27<AsOf),"OVERDUE",IF(OR(K27<>"",L27<>""),"Invoiced","Scheduled")))) | P27: =IF(B27="","",IF(E27<>"",E27,IFERROR(INDEX('Contractors'!$D$6:$D$35,MATCH(B27,'Contractors'!$B$6:$B$35,0)),""))) | Q27: =IF(B27="","",IF(D27<>"",D27,IFERROR(INDEX('Contractors'!$E$6:$E$35,MATCH(B27,'Contractors'!$B$6:$B$35,0)),""))) | R27: =IF(O27="","",IF(O27="OVERDUE",2,IF(O27="Paid",0,IF(AND(I27<>"",I27<=AsOf+AlertDays),1,0)))) | S27: =IF(AND(B27<>"",M27="",I27<>""),IF(L27<>"",L27,IF(H27="",0,H27)),0) | T27: =IF(AND(B27<>"",M27="",I27<>""),1/I27,0) | U27: =IF(AND(B27<>"",M27="",I27<>""),I27,"") | V27: =IF(U27="","",IF(U27<AsOf,1,IF(U27<=AsOf+AlertDays,2,IF(U27<=AsOf+2*AlertDays,3,"")))) | W27: =IF(V27="","",IF(O27="OVERDUE","Overdue payment: ","Payment due: ")&B27&" — "&C27&" ("&CurSym&" "&FIXED(S27,0)&")") | Z27: =IF('Contractors'!B27="","",'Contractors'!B27) | AA27: =IF(Z27="","",'Contractors'!K27) | AB27: =IF(Z27="","",SUMIFS($L$6:$L$205,$B$6:$B$205,Z27)) | AC27: =IF(Z27="","",SUMIFS($N$6:$N$205,$B$6:$B$205,Z27)) | AD27: =IF(Z27="","",AA27-AC27) | AE27: =IF(Z27="","",IFERROR(1/SUMPRODUCT(MAX(($B$6:$B$205=Z27)*$T$6:$T$205)),"")) | AF27: =IF(AE27="","",SUMIFS($S$6:$S$205,$B$6:$B$205,Z27,$I$6:$I$205,AE27))
B28: ClimaHeat HVAC | C28: Commissioning 70% | F28: 0.7 | H28: =IF(B28="","",IF(G28<>"",G28,IF(F28<>"",F28*IFERROR(INDEX('Contractors'!$I$6:$I$35,MATCH(B28,'Contractors'!$B$6:$B$35,0)),0),""))) | I28: 46203 | O28: =IF(B28="","",IF(M28<>"","Paid",IF(AND(I28<>"",I28<AsOf),"OVERDUE",IF(OR(K28<>"",L28<>""),"Invoiced","Scheduled")))) | P28: =IF(B28="","",IF(E28<>"",E28,IFERROR(INDEX('Contractors'!$D$6:$D$35,MATCH(B28,'Contractors'!$B$6:$B$35,0)),""))) | Q28: =IF(B28="","",IF(D28<>"",D28,IFERROR(INDEX('Contractors'!$E$6:$E$35,MATCH(B28,'Contractors'!$B$6:$B$35,0)),""))) | R28: =IF(O28="","",IF(O28="OVERDUE",2,IF(O28="Paid",0,IF(AND(I28<>"",I28<=AsOf+AlertDays),1,0)))) | S28: =IF(AND(B28<>"",M28="",I28<>""),IF(L28<>"",L28,IF(H28="",0,H28)),0) | T28: =IF(AND(B28<>"",M28="",I28<>""),1/I28,0) | U28: =IF(AND(B28<>"",M28="",I28<>""),I28,"") | V28: =IF(U28="","",IF(U28<AsOf,1,IF(U28<=AsOf+AlertDays,2,IF(U28<=AsOf+2*AlertDays,3,"")))) | W28: =IF(V28="","",IF(O28="OVERDUE","Overdue payment: ","Payment due: ")&B28&" — "&C28&" ("&CurSym&" "&FIXED(S28,0)&")") | Z28: =IF('Contractors'!B28="","",'Contractors'!B28) | AA28: =IF(Z28="","",'Contractors'!K28) | AB28: =IF(Z28="","",SUMIFS($L$6:$L$205,$B$6:$B$205,Z28)) | AC28: =IF(Z28="","",SUMIFS($N$6:$N$205,$B$6:$B$205,Z28)) | AD28: =IF(Z28="","",AA28-AC28) | AE28: =IF(Z28="","",IFERROR(1/SUMPRODUCT(MAX(($B$6:$B$205=Z28)*$T$6:$T$205)),"")) | AF28: =IF(AE28="","",SUMIFS($S$6:$S$205,$B$6:$B$205,Z28,$I$6:$I$205,AE28))
B29: FlowRight Plumbing | C29: Final 30% | F29: 0.3 | H29: =IF(B29="","",IF(G29<>"",G29,IF(F29<>"",F29*IFERROR(INDEX('Contractors'!$I$6:$I$35,MATCH(B29,'Contractors'!$B$6:$B$35,0)),0),""))) | I29: 46223 | O29: =IF(B29="","",IF(M29<>"","Paid",IF(AND(I29<>"",I29<AsOf),"OVERDUE",IF(OR(K29<>"",L29<>""),"Invoiced","Scheduled")))) | P29: =IF(B29="","",IF(E29<>"",E29,IFERROR(INDEX('Contractors'!$D$6:$D$35,MATCH(B29,'Contractors'!$B$6:$B$35,0)),""))) | Q29: =IF(B29="","",IF(D29<>"",D29,IFERROR(INDEX('Contractors'!$E$6:$E$35,MATCH(B29,'Contractors'!$B$6:$B$35,0)),""))) | R29: =IF(O29="","",IF(O29="OVERDUE",2,IF(O29="Paid",0,IF(AND(I29<>"",I29<=AsOf+AlertDays),1,0)))) | S29: =IF(AND(B29<>"",M29="",I29<>""),IF(L29<>"",L29,IF(H29="",0,H29)),0) | T29: =IF(AND(B29<>"",M29="",I29<>""),1/I29,0) | U29: =IF(AND(B29<>"",M29="",I29<>""),I29,"") | V29: =IF(U29="","",IF(U29<AsOf,1,IF(U29<=AsOf+AlertDays,2,IF(U29<=AsOf+2*AlertDays,3,"")))) | W29: =IF(V29="","",IF(O29="OVERDUE","Overdue payment: ","Payment due: ")&B29&" — "&C29&" ("&CurSym&" "&FIXED(S29,0)&")") | Z29: =IF('Contractors'!B29="","",'Contractors'!B29) | AA29: =IF(Z29="","",'Contractors'!K29) | AB29: =IF(Z29="","",SUMIFS($L$6:$L$205,$B$6:$B$205,Z29)) | AC29: =IF(Z29="","",SUMIFS($N$6:$N$205,$B$6:$B$205,Z29)) | AD29: =IF(Z29="","",AA29-AC29) | AE29: =IF(Z29="","",IFERROR(1/SUMPRODUCT(MAX(($B$6:$B$205=Z29)*$T$6:$T$205)),"")) | AF29: =IF(AE29="","",SUMIFS($S$6:$S$205,$B$6:$B$205,Z29,$I$6:$I$205,AE29))
B30: Nordic Kitchens | C30: Completion 40% | D30: Kitchen | F30: 0.4 | H30: =IF(B30="","",IF(G30<>"",G30,IF(F30<>"",F30*IFERROR(INDEX('Contractors'!$I$6:$I$35,MATCH(B30,'Contractors'!$B$6:$B$35,0)),0),""))) | I30: 46223 | O30: =IF(B30="","",IF(M30<>"","Paid",IF(AND(I30<>"",I30<AsOf),"OVERDUE",IF(OR(K30<>"",L30<>""),"Invoiced","Scheduled")))) | P30: =IF(B30="","",IF(E30<>"",E30,IFERROR(INDEX('Contractors'!$D$6:$D$35,MATCH(B30,'Contractors'!$B$6:$B$35,0)),""))) | Q30: =IF(B30="","",IF(D30<>"",D30,IFERROR(INDEX('Contractors'!$E$6:$E$35,MATCH(B30,'Contractors'!$B$6:$B$35,0)),""))) | R30: =IF(O30="","",IF(O30="OVERDUE",2,IF(O30="Paid",0,IF(AND(I30<>"",I30<=AsOf+AlertDays),1,0)))) | S30: =IF(AND(B30<>"",M30="",I30<>""),IF(L30<>"",L30,IF(H30="",0,H30)),0) | T30: =IF(AND(B30<>"",M30="",I30<>""),1/I30,0) | U30: =IF(AND(B30<>"",M30="",I30<>""),I30,"") | V30: =IF(U30="","",IF(U30<AsOf,1,IF(U30<=AsOf+AlertDays,2,IF(U30<=AsOf+2*AlertDays,3,"")))) | W30: =IF(V30="","",IF(O30="OVERDUE","Overdue payment: ","Payment due: ")&B30&" — "&C30&" ("&CurSym&" "&FIXED(S30,0)&")") | Z30: =IF('Contractors'!B30="","",'Contractors'!B30) | AA30: =IF(Z30="","",'Contractors'!K30) | AB30: =IF(Z30="","",SUMIFS($L$6:$L$205,$B$6:$B$205,Z30)) | AC30: =IF(Z30="","",SUMIFS($N$6:$N$205,$B$6:$B$205,Z30)) | AD30: =IF(Z30="","",AA30-AC30) | AE30: =IF(Z30="","",IFERROR(1/SUMPRODUCT(MAX(($B$6:$B$205=Z30)*$T$6:$T$205)),"")) | AF30: =IF(AE30="","",SUMIFS($S$6:$S$205,$B$6:$B$205,Z30,$I$6:$I$205,AE30))
B31: Aqua Bath Studio | C31: Completion 80% | F31: 0.8 | H31: =IF(B31="","",IF(G31<>"",G31,IF(F31<>"",F31*IFERROR(INDEX('Contractors'!$I$6:$I$35,MATCH(B31,'Contractors'!$B$6:$B$35,0)),0),""))) | I31: 46234 | O31: =IF(B31="","",IF(M31<>"","Paid",IF(AND(I31<>"",I31<AsOf),"OVERDUE",IF(OR(K31<>"",L31<>""),"Invoiced","Scheduled")))) | P31: =IF(B31="","",IF(E31<>"",E31,IFERROR(INDEX('Contractors'!$D$6:$D$35,MATCH(B31,'Contractors'!$B$6:$B$35,0)),""))) | Q31: =IF(B31="","",IF(D31<>"",D31,IFERROR(INDEX('Contractors'!$E$6:$E$35,MATCH(B31,'Contractors'!$B$6:$B$35,0)),""))) | R31: =IF(O31="","",IF(O31="OVERDUE",2,IF(O31="Paid",0,IF(AND(I31<>"",I31<=AsOf+AlertDays),1,0)))) | S31: =IF(AND(B31<>"",M31="",I31<>""),IF(L31<>"",L31,IF(H31="",0,H31)),0) | T31: =IF(AND(B31<>"",M31="",I31<>""),1/I31,0) | U31: =IF(AND(B31<>"",M31="",I31<>""),I31,"") | V31: =IF(U31="","",IF(U31<AsOf,1,IF(U31<=AsOf+AlertDays,2,IF(U31<=AsOf+2*AlertDays,3,"")))) | W31: =IF(V31="","",IF(O31="OVERDUE","Overdue payment: ","Payment due: ")&B31&" — "&C31&" ("&CurSym&" "&FIXED(S31,0)&")") | Z31: =IF('Contractors'!B31="","",'Contractors'!B31) | AA31: =IF(Z31="","",'Contractors'!K31) | AB31: =IF(Z31="","",SUMIFS($L$6:$L$205,$B$6:$B$205,Z31)) | AC31: =IF(Z31="","",SUMIFS($N$6:$N$205,$B$6:$B$205,Z31)) | AD31: =IF(Z31="","",AA31-AC31) | AE31: =IF(Z31="","",IFERROR(1/SUMPRODUCT(MAX(($B$6:$B$205=Z31)*$T$6:$T$205)),"")) | AF31: =IF(AE31="","",SUMIFS($S$6:$S$205,$B$6:$B$205,Z31,$I$6:$I$205,AE31))
B32: Bright Spark Electric | C32: Final 40% | F32: 0.4 | H32: =IF(B32="","",IF(G32<>"",G32,IF(F32<>"",F32*IFERROR(INDEX('Contractors'!$I$6:$I$35,MATCH(B32,'Contractors'!$B$6:$B$35,0)),0),""))) | I32: 46246 | O32: =IF(B32="","",IF(M32<>"","Paid",IF(AND(I32<>"",I32<AsOf),"OVERDUE",IF(OR(K32<>"",L32<>""),"Invoiced","Scheduled")))) | P32: =IF(B32="","",IF(E32<>"",E32,IFERROR(INDEX('Contractors'!$D$6:$D$35,MATCH(B32,'Contractors'!$B$6:$B$35,0)),""))) | Q32: =IF(B32="","",IF(D32<>"",D32,IFERROR(INDEX('Contractors'!$E$6:$E$35,MATCH(B32,'Contractors'!$B$6:$B$35,0)),""))) | R32: =IF(O32="","",IF(O32="OVERDUE",2,IF(O32="Paid",0,IF(AND(I32<>"",I32<=AsOf+AlertDays),1,0)))) | S32: =IF(AND(B32<>"",M32="",I32<>""),IF(L32<>"",L32,IF(H32="",0,H32)),0) | T32: =IF(AND(B32<>"",M32="",I32<>""),1/I32,0) | U32: =IF(AND(B32<>"",M32="",I32<>""),I32,"") | V32: =IF(U32="","",IF(U32<AsOf,1,IF(U32<=AsOf+AlertDays,2,IF(U32<=AsOf+2*AlertDays,3,"")))) | W32: =IF(V32="","",IF(O32="OVERDUE","Overdue payment: ","Payment due: ")&B32&" — "&C32&" ("&CurSym&" "&FIXED(S32,0)&")") | Z32: =IF('Contractors'!B32="","",'Contractors'!B32) | AA32: =IF(Z32="","",'Contractors'!K32) | AB32: =IF(Z32="","",SUMIFS($L$6:$L$205,$B$6:$B$205,Z32)) | AC32: =IF(Z32="","",SUMIFS($N$6:$N$205,$B$6:$B$205,Z32)) | AD32: =IF(Z32="","",AA32-AC32) | AE32: =IF(Z32="","",IFERROR(1/SUMPRODUCT(MAX(($B$6:$B$205=Z32)*$T$6:$T$205)),"")) | AF32: =IF(AE32="","",SUMIFS($S$6:$S$205,$B$6:$B$205,Z32,$I$6:$I$205,AE32))
B33: GreenPlan Architects | C33: Final sign-off 25% | F33: 0.25 | H33: =IF(B33="","",IF(G33<>"",G33,IF(F33<>"",F33*IFERROR(INDEX('Contractors'!$I$6:$I$35,MATCH(B33,'Contractors'!$B$6:$B$35,0)),0),""))) | I33: 46254 | O33: =IF(B33="","",IF(M33<>"","Paid",IF(AND(I33<>"",I33<AsOf),"OVERDUE",IF(OR(K33<>"",L33<>""),"Invoiced","Scheduled")))) | P33: =IF(B33="","",IF(E33<>"",E33,IFERROR(INDEX('Contractors'!$D$6:$D$35,MATCH(B33,'Contractors'!$B$6:$B$35,0)),""))) | Q33: =IF(B33="","",IF(D33<>"",D33,IFERROR(INDEX('Contractors'!$E$6:$E$35,MATCH(B33,'Contractors'!$B$6:$B$35,0)),""))) | R33: =IF(O33="","",IF(O33="OVERDUE",2,IF(O33="Paid",0,IF(AND(I33<>"",I33<=AsOf+AlertDays),1,0)))) | S33: =IF(AND(B33<>"",M33="",I33<>""),IF(L33<>"",L33,IF(H33="",0,H33)),0) | T33: =IF(AND(B33<>"",M33="",I33<>""),1/I33,0) | U33: =IF(AND(B33<>"",M33="",I33<>""),I33,"") | V33: =IF(U33="","",IF(U33<AsOf,1,IF(U33<=AsOf+AlertDays,2,IF(U33<=AsOf+2*AlertDays,3,"")))) | W33: =IF(V33="","",IF(O33="OVERDUE","Overdue payment: ","Payment due: ")&B33&" — "&C33&" ("&CurSym&" "&FIXED(S33,0)&")") | Z33: =IF('Contractors'!B33="","",'Contractors'!B33) | AA33: =IF(Z33="","",'Contractors'!K33) | AB33: =IF(Z33="","",SUMIFS($L$6:$L$205,$B$6:$B$205,Z33)) | AC33: =IF(Z33="","",SUMIFS($N$6:$N$205,$B$6:$B$205,Z33)) | AD33: =IF(Z33="","",AA33-AC33) | AE33: =IF(Z33="","",IFERROR(1/SUMPRODUCT(MAX(($B$6:$B$205=Z33)*$T$6:$T$205)),"")) | AF33: =IF(AE33="","",SUMIFS($S$6:$S$205,$B$6:$B$205,Z33,$I$6:$I$205,AE33))
H34: =IF(B34="","",IF(G34<>"",G34,IF(F34<>"",F34*IFERROR(INDEX('Contractors'!$I$6:$I$35,MATCH(B34,'Contractors'!$B$6:$B$35,0)),0),""))) | O34: =IF(B34="","",IF(M34<>"","Paid",IF(AND(I34<>"",I34<AsOf),"OVERDUE",IF(OR(K34<>"",L34<>""),"Invoiced","Scheduled")))) | P34: =IF(B34="","",IF(E34<>"",E34,IFERROR(INDEX('Contractors'!$D$6:$D$35,MATCH(B34,'Contractors'!$B$6:$B$35,0)),""))) | Q34: =IF(B34="","",IF(D34<>"",D34,IFERROR(INDEX('Contractors'!$E$6:$E$35,MATCH(B34,'Contractors'!$B$6:$B$35,0)),""))) | R34: =IF(O34="","",IF(O34="OVERDUE",2,IF(O34="Paid",0,IF(AND(I34<>"",I34<=AsOf+AlertDays),1,0)))) | S34: =IF(AND(B34<>"",M34="",I34<>""),IF(L34<>"",L34,IF(H34="",0,H34)),0) | T34: =IF(AND(B34<>"",M34="",I34<>""),1/I34,0) | U34: =IF(AND(B34<>"",M34="",I34<>""),I34,"") | V34: =IF(U34="","",IF(U34<AsOf,1,IF(U34<=AsOf+AlertDays,2,IF(U34<=AsOf+2*AlertDays,3,"")))) | W34: =IF(V34="","",IF(O34="OVERDUE","Overdue payment: ","Payment due: ")&B34&" — "&C34&" ("&CurSym&" "&FIXED(S34,0)&")") | Z34: =IF('Contractors'!B34="","",'Contractors'!B34) | AA34: =IF(Z34="","",'Contractors'!K34) | AB34: =IF(Z34="","",SUMIFS($L$6:$L$205,$B$6:$B$205,Z34)) | AC34: =IF(Z34="","",SUMIFS($N$6:$N$205,$B$6:$B$205,Z34)) | AD34: =IF(Z34="","",AA34-AC34) | AE34: =IF(Z34="","",IFERROR(1/SUMPRODUCT(MAX(($B$6:$B$205=Z34)*$T$6:$T$205)),"")) | AF34: =IF(AE34="","",SUMIFS($S$6:$S$205,$B$6:$B$205,Z34,$I$6:$I$205,AE34))
H35: =IF(B35="","",IF(G35<>"",G35,IF(F35<>"",F35*IFERROR(INDEX('Contractors'!$I$6:$I$35,MATCH(B35,'Contractors'!$B$6:$B$35,0)),0),""))) | O35: =IF(B35="","",IF(M35<>"","Paid",IF(AND(I35<>"",I35<AsOf),"OVERDUE",IF(OR(K35<>"",L35<>""),"Invoiced","Scheduled")))) | P35: =IF(B35="","",IF(E35<>"",E35,IFERROR(INDEX('Contractors'!$D$6:$D$35,MATCH(B35,'Contractors'!$B$6:$B$35,0)),""))) | Q35: =IF(B35="","",IF(D35<>"",D35,IFERROR(INDEX('Contractors'!$E$6:$E$35,MATCH(B35,'Contractors'!$B$6:$B$35,0)),""))) | R35: =IF(O35="","",IF(O35="OVERDUE",2,IF(O35="Paid",0,IF(AND(I35<>"",I35<=AsOf+AlertDays),1,0)))) | S35: =IF(AND(B35<>"",M35="",I35<>""),IF(L35<>"",L35,IF(H35="",0,H35)),0) | T35: =IF(AND(B35<>"",M35="",I35<>""),1/I35,0) | U35: =IF(AND(B35<>"",M35="",I35<>""),I35,"") | V35: =IF(U35="","",IF(U35<AsOf,1,IF(U35<=AsOf+AlertDays,2,IF(U35<=AsOf+2*AlertDays,3,"")))) | W35: =IF(V35="","",IF(O35="OVERDUE","Overdue payment: ","Payment due: ")&B35&" — "&C35&" ("&CurSym&" "&FIXED(S35,0)&")") | Z35: =IF('Contractors'!B35="","",'Contractors'!B35) | AA35: =IF(Z35="","",'Contractors'!K35) | AB35: =IF(Z35="","",SUMIFS($L$6:$L$205,$B$6:$B$205,Z35)) | AC35: =IF(Z35="","",SUMIFS($N$6:$N$205,$B$6:$B$205,Z35)) | AD35: =IF(Z35="","",AA35-AC35) | AE35: =IF(Z35="","",IFERROR(1/SUMPRODUCT(MAX(($B$6:$B$205=Z35)*$T$6:$T$205)),"")) | AF35: =IF(AE35="","",SUMIFS($S$6:$S$205,$B$6:$B$205,Z35,$I$6:$I$205,AE35))
H36: =IF(B36="","",IF(G36<>"",G36,IF(F36<>"",F36*IFERROR(INDEX('Contractors'!$I$6:$I$35,MATCH(B36,'Contractors'!$B$6:$B$35,0)),0),""))) | O36: =IF(B36="","",IF(M36<>"","Paid",IF(AND(I36<>"",I36<AsOf),"OVERDUE",IF(OR(K36<>"",L36<>""),"Invoiced","Scheduled")))) | P36: =IF(B36="","",IF(E36<>"",E36,IFERROR(INDEX('Contractors'!$D$6:$D$35,MATCH(B36,'Contractors'!$B$6:$B$35,0)),""))) | Q36: =IF(B36="","",IF(D36<>"",D36,IFERROR(INDEX('Contractors'!$E$6:$E$35,MATCH(B36,'Contractors'!$B$6:$B$35,0)),""))) | R36: =IF(O36="","",IF(O36="OVERDUE",2,IF(O36="Paid",0,IF(AND(I36<>"",I36<=AsOf+AlertDays),1,0)))) | S36: =IF(AND(B36<>"",M36="",I36<>""),IF(L36<>"",L36,IF(H36="",0,H36)),0) | T36: =IF(AND(B36<>"",M36="",I36<>""),1/I36,0) | U36: =IF(AND(B36<>"",M36="",I36<>""),I36,"") | V36: =IF(U36="","",IF(U36<AsOf,1,IF(U36<=AsOf+AlertDays,2,IF(U36<=AsOf+2*AlertDays,3,"")))) | W36: =IF(V36="","",IF(O36="OVERDUE","Overdue payment: ","Payment due: ")&B36&" — "&C36&" ("&CurSym&" "&FIXED(S36,0)&")")
H37: =IF(B37="","",IF(G37<>"",G37,IF(F37<>"",F37*IFERROR(INDEX('Contractors'!$I$6:$I$35,MATCH(B37,'Contractors'!$B$6:$B$35,0)),0),""))) | O37: =IF(B37="","",IF(M37<>"","Paid",IF(AND(I37<>"",I37<AsOf),"OVERDUE",IF(OR(K37<>"",L37<>""),"Invoiced","Scheduled")))) | P37: =IF(B37="","",IF(E37<>"",E37,IFERROR(INDEX('Contractors'!$D$6:$D$35,MATCH(B37,'Contractors'!$B$6:$B$35,0)),""))) | Q37: =IF(B37="","",IF(D37<>"",D37,IFERROR(INDEX('Contractors'!$E$6:$E$35,MATCH(B37,'Contractors'!$B$6:$B$35,0)),""))) | R37: =IF(O37="","",IF(O37="OVERDUE",2,IF(O37="Paid",0,IF(AND(I37<>"",I37<=AsOf+AlertDays),1,0)))) | S37: =IF(AND(B37<>"",M37="",I37<>""),IF(L37<>"",L37,IF(H37="",0,H37)),0) | T37: =IF(AND(B37<>"",M37="",I37<>""),1/I37,0) | U37: =IF(AND(B37<>"",M37="",I37<>""),I37,"") | V37: =IF(U37="","",IF(U37<AsOf,1,IF(U37<=AsOf+AlertDays,2,IF(U37<=AsOf+2*AlertDays,3,"")))) | W37: =IF(V37="","",IF(O37="OVERDUE","Overdue payment: ","Payment due: ")&B37&" — "&C37&" ("&CurSym&" "&FIXED(S37,0)&")") | Z37: CASH FLOW — 12 months from project start
H38: =IF(B38="","",IF(G38<>"",G38,IF(F38<>"",F38*IFERROR(INDEX('Contractors'!$I$6:$I$35,MATCH(B38,'Contractors'!$B$6:$B$35,0)),0),""))) | O38: =IF(B38="","",IF(M38<>"","Paid",IF(AND(I38<>"",I38<AsOf),"OVERDUE",IF(OR(K38<>"",L38<>""),"Invoiced","Scheduled")))) | P38: =IF(B38="","",IF(E38<>"",E38,IFERROR(INDEX('Contractors'!$D$6:$D$35,MATCH(B38,'Contractors'!$B$6:$B$35,0)),""))) | Q38: =IF(B38="","",IF(D38<>"",D38,IFERROR(INDEX('Contractors'!$E$6:$E$35,MATCH(B38,'Contractors'!$B$6:$B$35,0)),""))) | R38: =IF(O38="","",IF(O38="OVERDUE",2,IF(O38="Paid",0,IF(AND(I38<>"",I38<=AsOf+AlertDays),1,0)))) | S38: =IF(AND(B38<>"",M38="",I38<>""),IF(L38<>"",L38,IF(H38="",0,H38)),0) | T38: =IF(AND(B38<>"",M38="",I38<>""),1/I38,0) | U38: =IF(AND(B38<>"",M38="",I38<>""),I38,"") | V38: =IF(U38="","",IF(U38<AsOf,1,IF(U38<=AsOf+AlertDays,2,IF(U38<=AsOf+2*AlertDays,3,"")))) | W38: =IF(V38="","",IF(O38="OVERDUE","Overdue payment: ","Payment due: ")&B38&" — "&C38&" ("&CurSym&" "&FIXED(S38,0)&")") | Z38: ="Cash needed in the next 30 days ("&CurSym&")" | AC38: =SUMIFS($S$6:$S$205,$I$6:$I$205,"<="&(AsOf+30))
H39: =IF(B39="","",IF(G39<>"",G39,IF(F39<>"",F39*IFERROR(INDEX('Contractors'!$I$6:$I$35,MATCH(B39,'Contractors'!$B$6:$B$35,0)),0),""))) | O39: =IF(B39="","",IF(M39<>"","Paid",IF(AND(I39<>"",I39<AsOf),"OVERDUE",IF(OR(K39<>"",L39<>""),"Invoiced","Scheduled")))) | P39: =IF(B39="","",IF(E39<>"",E39,IFERROR(INDEX('Contractors'!$D$6:$D$35,MATCH(B39,'Contractors'!$B$6:$B$35,0)),""))) | Q39: =IF(B39="","",IF(D39<>"",D39,IFERROR(INDEX('Contractors'!$E$6:$E$35,MATCH(B39,'Contractors'!$B$6:$B$35,0)),""))) | R39: =IF(O39="","",IF(O39="OVERDUE",2,IF(O39="Paid",0,IF(AND(I39<>"",I39<=AsOf+AlertDays),1,0)))) | S39: =IF(AND(B39<>"",M39="",I39<>""),IF(L39<>"",L39,IF(H39="",0,H39)),0) | T39: =IF(AND(B39<>"",M39="",I39<>""),1/I39,0) | U39: =IF(AND(B39<>"",M39="",I39<>""),I39,"") | V39: =IF(U39="","",IF(U39<AsOf,1,IF(U39<=AsOf+AlertDays,2,IF(U39<=AsOf+2*AlertDays,3,"")))) | W39: =IF(V39="","",IF(O39="OVERDUE","Overdue payment: ","Payment due: ")&B39&" — "&C39&" ("&CurSym&" "&FIXED(S39,0)&")")
H40: =IF(B40="","",IF(G40<>"",G40,IF(F40<>"",F40*IFERROR(INDEX('Contractors'!$I$6:$I$35,MATCH(B40,'Contractors'!$B$6:$B$35,0)),0),""))) | O40: =IF(B40="","",IF(M40<>"","Paid",IF(AND(I40<>"",I40<AsOf),"OVERDUE",IF(OR(K40<>"",L40<>""),"Invoiced","Scheduled")))) | P40: =IF(B40="","",IF(E40<>"",E40,IFERROR(INDEX('Contractors'!$D$6:$D$35,MATCH(B40,'Contractors'!$B$6:$B$35,0)),""))) | Q40: =IF(B40="","",IF(D40<>"",D40,IFERROR(INDEX('Contractors'!$E$6:$E$35,MATCH(B40,'Contractors'!$B$6:$B$35,0)),""))) | R40: =IF(O40="","",IF(O40="OVERDUE",2,IF(O40="Paid",0,IF(AND(I40<>"",I40<=AsOf+AlertDays),1,0)))) | S40: =IF(AND(B40<>"",M40="",I40<>""),IF(L40<>"",L40,IF(H40="",0,H40)),0) | T40: =IF(AND(B40<>"",M40="",I40<>""),1/I40,0) | U40: =IF(AND(B40<>"",M40="",I40<>""),I40,"") | V40: =IF(U40="","",IF(U40<AsOf,1,IF(U40<=AsOf+AlertDays,2,IF(U40<=AsOf+2*AlertDays,3,"")))) | W40: =IF(V40="","",IF(O40="OVERDUE","Overdue payment: ","Payment due: ")&B40&" — "&C40&" ("&CurSym&" "&FIXED(S40,0)&")") | Z40: Month | AA40: ="Paid ("&CurSym&")" | AB40: ="Still to pay ("&CurSym&")" | AC40: ="Total ("&CurSym&")" | AD40: ="Cumulative ("&CurSym&")"
H41: =IF(B41="","",IF(G41<>"",G41,IF(F41<>"",F41*IFERROR(INDEX('Contractors'!$I$6:$I$35,MATCH(B41,'Contractors'!$B$6:$B$35,0)),0),""))) | O41: =IF(B41="","",IF(M41<>"","Paid",IF(AND(I41<>"",I41<AsOf),"OVERDUE",IF(OR(K41<>"",L41<>""),"Invoiced","Scheduled")))) | P41: =IF(B41="","",IF(E41<>"",E41,IFERROR(INDEX('Contractors'!$D$6:$D$35,MATCH(B41,'Contractors'!$B$6:$B$35,0)),""))) | Q41: =IF(B41="","",IF(D41<>"",D41,IFERROR(INDEX('Contractors'!$E$6:$E$35,MATCH(B41,'Contractors'!$B$6:$B$35,0)),""))) | R41: =IF(O41="","",IF(O41="OVERDUE",2,IF(O41="Paid",0,IF(AND(I41<>"",I41<=AsOf+AlertDays),1,0)))) | S41: =IF(AND(B41<>"",M41="",I41<>""),IF(L41<>"",L41,IF(H41="",0,H41)),0) | T41: =IF(AND(B41<>"",M41="",I41<>""),1/I41,0) | U41: =IF(AND(B41<>"",M41="",I41<>""),I41,"") | V41: =IF(U41="","",IF(U41<AsOf,1,IF(U41<=AsOf+AlertDays,2,IF(U41<=AsOf+2*AlertDays,3,"")))) | W41: =IF(V41="","",IF(O41="OVERDUE","Overdue payment: ","Payment due: ")&B41&" — "&C41&" ("&CurSym&" "&FIXED(S41,0)&")") | Z41: =IF(ProjStart="","",DATE(YEAR(ProjStart),MONTH(ProjStart)+0,1)) | AA41: =IF(Z41="","",SUMIFS($N$6:$N$205,$M$6:$M$205,">="&Z41,$M$6:$M$205,"<"&DATE(YEAR(Z41),MONTH(Z41)+1,1))) | AB41: =IF(Z41="","",SUMIFS($S$6:$S$205,$I$6:$I$205,">="&Z41,$I$6:$I$205,"<"&DATE(YEAR(Z41),MONTH(Z41)+1,1))) | AC41: =IF(Z41="","",AA41+AB41) | AD41: =IF(Z41="","",SUM($AC$41:AC41))
H42: =IF(B42="","",IF(G42<>"",G42,IF(F42<>"",F42*IFERROR(INDEX('Contractors'!$I$6:$I$35,MATCH(B42,'Contractors'!$B$6:$B$35,0)),0),""))) | O42: =IF(B42="","",IF(M42<>"","Paid",IF(AND(I42<>"",I42<AsOf),"OVERDUE",IF(OR(K42<>"",L42<>""),"Invoiced","Scheduled")))) | P42: =IF(B42="","",IF(E42<>"",E42,IFERROR(INDEX('Contractors'!$D$6:$D$35,MATCH(B42,'Contractors'!$B$6:$B$35,0)),""))) | Q42: =IF(B42="","",IF(D42<>"",D42,IFERROR(INDEX('Contractors'!$E$6:$E$35,MATCH(B42,'Contractors'!$B$6:$B$35,0)),""))) | R42: =IF(O42="","",IF(O42="OVERDUE",2,IF(O42="Paid",0,IF(AND(I42<>"",I42<=AsOf+AlertDays),1,0)))) | S42: =IF(AND(B42<>"",M42="",I42<>""),IF(L42<>"",L42,IF(H42="",0,H42)),0) | T42: =IF(AND(B42<>"",M42="",I42<>""),1/I42,0) | U42: =IF(AND(B42<>"",M42="",I42<>""),I42,"") | V42: =IF(U42="","",IF(U42<AsOf,1,IF(U42<=AsOf+AlertDays,2,IF(U42<=AsOf+2*AlertDays,3,"")))) | W42: =IF(V42="","",IF(O42="OVERDUE","Overdue payment: ","Payment due: ")&B42&" — "&C42&" ("&CurSym&" "&FIXED(S42,0)&")") | Z42: =IF(ProjStart="","",DATE(YEAR(ProjStart),MONTH(ProjStart)+1,1)) | AA42: =IF(Z42="","",SUMIFS($N$6:$N$205,$M$6:$M$205,">="&Z42,$M$6:$M$205,"<"&DATE(YEAR(Z42),MONTH(Z42)+1,1))) | AB42: =IF(Z42="","",SUMIFS($S$6:$S$205,$I$6:$I$205,">="&Z42,$I$6:$I$205,"<"&DATE(YEAR(Z42),MONTH(Z42)+1,1))) | AC42: =IF(Z42="","",AA42+AB42) | AD42: =IF(Z42="","",SUM($AC$41:AC42))
H43: =IF(B43="","",IF(G43<>"",G43,IF(F43<>"",F43*IFERROR(INDEX('Contractors'!$I$6:$I$35,MATCH(B43,'Contractors'!$B$6:$B$35,0)),0),""))) | O43: =IF(B43="","",IF(M43<>"","Paid",IF(AND(I43<>"",I43<AsOf),"OVERDUE",IF(OR(K43<>"",L43<>""),"Invoiced","Scheduled")))) | P43: =IF(B43="","",IF(E43<>"",E43,IFERROR(INDEX('Contractors'!$D$6:$D$35,MATCH(B43,'Contractors'!$B$6:$B$35,0)),""))) | Q43: =IF(B43="","",IF(D43<>"",D43,IFERROR(INDEX('Contractors'!$E$6:$E$35,MATCH(B43,'Contractors'!$B$6:$B$35,0)),""))) | R43: =IF(O43="","",IF(O43="OVERDUE",2,IF(O43="Paid",0,IF(AND(I43<>"",I43<=AsOf+AlertDays),1,0)))) | S43: =IF(AND(B43<>"",M43="",I43<>""),IF(L43<>"",L43,IF(H43="",0,H43)),0) | T43: =IF(AND(B43<>"",M43="",I43<>""),1/I43,0) | U43: =IF(AND(B43<>"",M43="",I43<>""),I43,"") | V43: =IF(U43="","",IF(U43<AsOf,1,IF(U43<=AsOf+AlertDays,2,IF(U43<=AsOf+2*AlertDays,3,"")))) | W43: =IF(V43="","",IF(O43="OVERDUE","Overdue payment: ","Payment due: ")&B43&" — "&C43&" ("&CurSym&" "&FIXED(S43,0)&")") | Z43: =IF(ProjStart="","",DATE(YEAR(ProjStart),MONTH(ProjStart)+2,1)) | AA43: =IF(Z43="","",SUMIFS($N$6:$N$205,$M$6:$M$205,">="&Z43,$M$6:$M$205,"<"&DATE(YEAR(Z43),MONTH(Z43)+1,1))) | AB43: =IF(Z43="","",SUMIFS($S$6:$S$205,$I$6:$I$205,">="&Z43,$I$6:$I$205,"<"&DATE(YEAR(Z43),MONTH(Z43)+1,1))) | AC43: =IF(Z43="","",AA43+AB43) | AD43: =IF(Z43="","",SUM($AC$41:AC43))
H44: =IF(B44="","",IF(G44<>"",G44,IF(F44<>"",F44*IFERROR(INDEX('Contractors'!$I$6:$I$35,MATCH(B44,'Contractors'!$B$6:$B$35,0)),0),""))) | O44: =IF(B44="","",IF(M44<>"","Paid",IF(AND(I44<>"",I44<AsOf),"OVERDUE",IF(OR(K44<>"",L44<>""),"Invoiced","Scheduled")))) | P44: =IF(B44="","",IF(E44<>"",E44,IFERROR(INDEX('Contractors'!$D$6:$D$35,MATCH(B44,'Contractors'!$B$6:$B$35,0)),""))) | Q44: =IF(B44="","",IF(D44<>"",D44,IFERROR(INDEX('Contractors'!$E$6:$E$35,MATCH(B44,'Contractors'!$B$6:$B$35,0)),""))) | R44: =IF(O44="","",IF(O44="OVERDUE",2,IF(O44="Paid",0,IF(AND(I44<>"",I44<=AsOf+AlertDays),1,0)))) | S44: =IF(AND(B44<>"",M44="",I44<>""),IF(L44<>"",L44,IF(H44="",0,H44)),0) | T44: =IF(AND(B44<>"",M44="",I44<>""),1/I44,0) | U44: =IF(AND(B44<>"",M44="",I44<>""),I44,"") | V44: =IF(U44="","",IF(U44<AsOf,1,IF(U44<=AsOf+AlertDays,2,IF(U44<=AsOf+2*AlertDays,3,"")))) | W44: =IF(V44="","",IF(O44="OVERDUE","Overdue payment: ","Payment due: ")&B44&" — "&C44&" ("&CurSym&" "&FIXED(S44,0)&")") | Z44: =IF(ProjStart="","",DATE(YEAR(ProjStart),MONTH(ProjStart)+3,1)) | AA44: =IF(Z44="","",SUMIFS($N$6:$N$205,$M$6:$M$205,">="&Z44,$M$6:$M$205,"<"&DATE(YEAR(Z44),MONTH(Z44)+1,1))) | AB44: =IF(Z44="","",SUMIFS($S$6:$S$205,$I$6:$I$205,">="&Z44,$I$6:$I$205,"<"&DATE(YEAR(Z44),MONTH(Z44)+1,1))) | AC44: =IF(Z44="","",AA44+AB44) | AD44: =IF(Z44="","",SUM($AC$41:AC44))
H45: =IF(B45="","",IF(G45<>"",G45,IF(F45<>"",F45*IFERROR(INDEX('Contractors'!$I$6:$I$35,MATCH(B45,'Contractors'!$B$6:$B$35,0)),0),""))) | O45: =IF(B45="","",IF(M45<>"","Paid",IF(AND(I45<>"",I45<AsOf),"OVERDUE",IF(OR(K45<>"",L45<>""),"Invoiced","Scheduled")))) | P45: =IF(B45="","",IF(E45<>"",E45,IFERROR(INDEX('Contractors'!$D$6:$D$35,MATCH(B45,'Contractors'!$B$6:$B$35,0)),""))) | Q45: =IF(B45="","",IF(D45<>"",D45,IFERROR(INDEX('Contractors'!$E$6:$E$35,MATCH(B45,'Contractors'!$B$6:$B$35,0)),""))) | R45: =IF(O45="","",IF(O45="OVERDUE",2,IF(O45="Paid",0,IF(AND(I45<>"",I45<=AsOf+AlertDays),1,0)))) | S45: =IF(AND(B45<>"",M45="",I45<>""),IF(L45<>"",L45,IF(H45="",0,H45)),0) | T45: =IF(AND(B45<>"",M45="",I45<>""),1/I45,0) | U45: =IF(AND(B45<>"",M45="",I45<>""),I45,"") | V45: =IF(U45="","",IF(U45<AsOf,1,IF(U45<=AsOf+AlertDays,2,IF(U45<=AsOf+2*AlertDays,3,"")))) | W45: =IF(V45="","",IF(O45="OVERDUE","Overdue payment: ","Payment due: ")&B45&" — "&C45&" ("&CurSym&" "&FIXED(S45,0)&")") | Z45: =IF(ProjStart="","",DATE(YEAR(ProjStart),MONTH(ProjStart)+4,1)) | AA45: =IF(Z45="","",SUMIFS($N$6:$N$205,$M$6:$M$205,">="&Z45,$M$6:$M$205,"<"&DATE(YEAR(Z45),MONTH(Z45)+1,1))) | AB45: =IF(Z45="","",SUMIFS($S$6:$S$205,$I$6:$I$205,">="&Z45,$I$6:$I$205,"<"&DATE(YEAR(Z45),MONTH(Z45)+1,1))) | AC45: =IF(Z45="","",AA45+AB45) | AD45: =IF(Z45="","",SUM($AC$41:AC45))
H46: =IF(B46="","",IF(G46<>"",G46,IF(F46<>"",F46*IFERROR(INDEX('Contractors'!$I$6:$I$35,MATCH(B46,'Contractors'!$B$6:$B$35,0)),0),""))) | O46: =IF(B46="","",IF(M46<>"","Paid",IF(AND(I46<>"",I46<AsOf),"OVERDUE",IF(OR(K46<>"",L46<>""),"Invoiced","Scheduled")))) | P46: =IF(B46="","",IF(E46<>"",E46,IFERROR(INDEX('Contractors'!$D$6:$D$35,MATCH(B46,'Contractors'!$B$6:$B$35,0)),""))) | Q46: =IF(B46="","",IF(D46<>"",D46,IFERROR(INDEX('Contractors'!$E$6:$E$35,MATCH(B46,'Contractors'!$B$6:$B$35,0)),""))) | R46: =IF(O46="","",IF(O46="OVERDUE",2,IF(O46="Paid",0,IF(AND(I46<>"",I46<=AsOf+AlertDays),1,0)))) | S46: =IF(AND(B46<>"",M46="",I46<>""),IF(L46<>"",L46,IF(H46="",0,H46)),0) | T46: =IF(AND(B46<>"",M46="",I46<>""),1/I46,0) | U46: =IF(AND(B46<>"",M46="",I46<>""),I46,"") | V46: =IF(U46="","",IF(U46<AsOf,1,IF(U46<=AsOf+AlertDays,2,IF(U46<=AsOf+2*AlertDays,3,"")))) | W46: =IF(V46="","",IF(O46="OVERDUE","Overdue payment: ","Payment due: ")&B46&" — "&C46&" ("&CurSym&" "&FIXED(S46,0)&")") | Z46: =IF(ProjStart="","",DATE(YEAR(ProjStart),MONTH(ProjStart)+5,1)) | AA46: =IF(Z46="","",SUMIFS($N$6:$N$205,$M$6:$M$205,">="&Z46,$M$6:$M$205,"<"&DATE(YEAR(Z46),MONTH(Z46)+1,1))) | AB46: =IF(Z46="","",SUMIFS($S$6:$S$205,$I$6:$I$205,">="&Z46,$I$6:$I$205,"<"&DATE(YEAR(Z46),MONTH(Z46)+1,1))) | AC46: =IF(Z46="","",AA46+AB46) | AD46: =IF(Z46="","",SUM($AC$41:AC46))
H47: =IF(B47="","",IF(G47<>"",G47,IF(F47<>"",F47*IFERROR(INDEX('Contractors'!$I$6:$I$35,MATCH(B47,'Contractors'!$B$6:$B$35,0)),0),""))) | O47: =IF(B47="","",IF(M47<>"","Paid",IF(AND(I47<>"",I47<AsOf),"OVERDUE",IF(OR(K47<>"",L47<>""),"Invoiced","Scheduled")))) | P47: =IF(B47="","",IF(E47<>"",E47,IFERROR(INDEX('Contractors'!$D$6:$D$35,MATCH(B47,'Contractors'!$B$6:$B$35,0)),""))) | Q47: =IF(B47="","",IF(D47<>"",D47,IFERROR(INDEX('Contractors'!$E$6:$E$35,MATCH(B47,'Contractors'!$B$6:$B$35,0)),""))) | R47: =IF(O47="","",IF(O47="OVERDUE",2,IF(O47="Paid",0,IF(AND(I47<>"",I47<=AsOf+AlertDays),1,0)))) | S47: =IF(AND(B47<>"",M47="",I47<>""),IF(L47<>"",L47,IF(H47="",0,H47)),0) | T47: =IF(AND(B47<>"",M47="",I47<>""),1/I47,0) | U47: =IF(AND(B47<>"",M47="",I47<>""),I47,"") | V47: =IF(U47="","",IF(U47<AsOf,1,IF(U47<=AsOf+AlertDays,2,IF(U47<=AsOf+2*AlertDays,3,"")))) | W47: =IF(V47="","",IF(O47="OVERDUE","Overdue payment: ","Payment due: ")&B47&" — "&C47&" ("&CurSym&" "&FIXED(S47,0)&")") | Z47: =IF(ProjStart="","",DATE(YEAR(ProjStart),MONTH(ProjStart)+6,1)) | AA47: =IF(Z47="","",SUMIFS($N$6:$N$205,$M$6:$M$205,">="&Z47,$M$6:$M$205,"<"&DATE(YEAR(Z47),MONTH(Z47)+1,1))) | AB47: =IF(Z47="","",SUMIFS($S$6:$S$205,$I$6:$I$205,">="&Z47,$I$6:$I$205,"<"&DATE(YEAR(Z47),MONTH(Z47)+1,1))) | AC47: =IF(Z47="","",AA47+AB47) | AD47: =IF(Z47="","",SUM($AC$41:AC47))
H48: =IF(B48="","",IF(G48<>"",G48,IF(F48<>"",F48*IFERROR(INDEX('Contractors'!$I$6:$I$35,MATCH(B48,'Contractors'!$B$6:$B$35,0)),0),""))) | O48: =IF(B48="","",IF(M48<>"","Paid",IF(AND(I48<>"",I48<AsOf),"OVERDUE",IF(OR(K48<>"",L48<>""),"Invoiced","Scheduled")))) | P48: =IF(B48="","",IF(E48<>"",E48,IFERROR(INDEX('Contractors'!$D$6:$D$35,MATCH(B48,'Contractors'!$B$6:$B$35,0)),""))) | Q48: =IF(B48="","",IF(D48<>"",D48,IFERROR(INDEX('Contractors'!$E$6:$E$35,MATCH(B48,'Contractors'!$B$6:$B$35,0)),""))) | R48: =IF(O48="","",IF(O48="OVERDUE",2,IF(O48="Paid",0,IF(AND(I48<>"",I48<=AsOf+AlertDays),1,0)))) | S48: =IF(AND(B48<>"",M48="",I48<>""),IF(L48<>"",L48,IF(H48="",0,H48)),0) | T48: =IF(AND(B48<>"",M48="",I48<>""),1/I48,0) | U48: =IF(AND(B48<>"",M48="",I48<>""),I48,"") | V48: =IF(U48="","",IF(U48<AsOf,1,IF(U48<=AsOf+AlertDays,2,IF(U48<=AsOf+2*AlertDays,3,"")))) | W48: =IF(V48="","",IF(O48="OVERDUE","Overdue payment: ","Payment due: ")&B48&" — "&C48&" ("&CurSym&" "&FIXED(S48,0)&")") | Z48: =IF(ProjStart="","",DATE(YEAR(ProjStart),MONTH(ProjStart)+7,1)) | AA48: =IF(Z48="","",SUMIFS($N$6:$N$205,$M$6:$M$205,">="&Z48,$M$6:$M$205,"<"&DATE(YEAR(Z48),MONTH(Z48)+1,1))) | AB48: =IF(Z48="","",SUMIFS($S$6:$S$205,$I$6:$I$205,">="&Z48,$I$6:$I$205,"<"&DATE(YEAR(Z48),MONTH(Z48)+1,1))) | AC48: =IF(Z48="","",AA48+AB48) | AD48: =IF(Z48="","",SUM($AC$41:AC48))
H49: =IF(B49="","",IF(G49<>"",G49,IF(F49<>"",F49*IFERROR(INDEX('Contractors'!$I$6:$I$35,MATCH(B49,'Contractors'!$B$6:$B$35,0)),0),""))) | O49: =IF(B49="","",IF(M49<>"","Paid",IF(AND(I49<>"",I49<AsOf),"OVERDUE",IF(OR(K49<>"",L49<>""),"Invoiced","Scheduled")))) | P49: =IF(B49="","",IF(E49<>"",E49,IFERROR(INDEX('Contractors'!$D$6:$D$35,MATCH(B49,'Contractors'!$B$6:$B$35,0)),""))) | Q49: =IF(B49="","",IF(D49<>"",D49,IFERROR(INDEX('Contractors'!$E$6:$E$35,MATCH(B49,'Contractors'!$B$6:$B$35,0)),""))) | R49: =IF(O49="","",IF(O49="OVERDUE",2,IF(O49="Paid",0,IF(AND(I49<>"",I49<=AsOf+AlertDays),1,0)))) | S49: =IF(AND(B49<>"",M49="",I49<>""),IF(L49<>"",L49,IF(H49="",0,H49)),0) | T49: =IF(AND(B49<>"",M49="",I49<>""),1/I49,0) | U49: =IF(AND(B49<>"",M49="",I49<>""),I49,"") | V49: =IF(U49="","",IF(U49<AsOf,1,IF(U49<=AsOf+AlertDays,2,IF(U49<=AsOf+2*AlertDays,3,"")))) | W49: =IF(V49="","",IF(O49="OVERDUE","Overdue payment: ","Payment due: ")&B49&" — "&C49&" ("&CurSym&" "&FIXED(S49,0)&")") | Z49: =IF(ProjStart="","",DATE(YEAR(ProjStart),MONTH(ProjStart)+8,1)) | AA49: =IF(Z49="","",SUMIFS($N$6:$N$205,$M$6:$M$205,">="&Z49,$M$6:$M$205,"<"&DATE(YEAR(Z49),MONTH(Z49)+1,1))) | AB49: =IF(Z49="","",SUMIFS($S$6:$S$205,$I$6:$I$205,">="&Z49,$I$6:$I$205,"<"&DATE(YEAR(Z49),MONTH(Z49)+1,1))) | AC49: =IF(Z49="","",AA49+AB49) | AD49: =IF(Z49="","",SUM($AC$41:AC49))
H50: =IF(B50="","",IF(G50<>"",G50,IF(F50<>"",F50*IFERROR(INDEX('Contractors'!$I$6:$I$35,MATCH(B50,'Contractors'!$B$6:$B$35,0)),0),""))) | O50: =IF(B50="","",IF(M50<>"","Paid",IF(AND(I50<>"",I50<AsOf),"OVERDUE",IF(OR(K50<>"",L50<>""),"Invoiced","Scheduled")))) | P50: =IF(B50="","",IF(E50<>"",E50,IFERROR(INDEX('Contractors'!$D$6:$D$35,MATCH(B50,'Contractors'!$B$6:$B$35,0)),""))) | Q50: =IF(B50="","",IF(D50<>"",D50,IFERROR(INDEX('Contractors'!$E$6:$E$35,MATCH(B50,'Contractors'!$B$6:$B$35,0)),""))) | R50: =IF(O50="","",IF(O50="OVERDUE",2,IF(O50="Paid",0,IF(AND(I50<>"",I50<=AsOf+AlertDays),1,0)))) | S50: =IF(AND(B50<>"",M50="",I50<>""),IF(L50<>"",L50,IF(H50="",0,H50)),0) | T50: =IF(AND(B50<>"",M50="",I50<>""),1/I50,0) | U50: =IF(AND(B50<>"",M50="",I50<>""),I50,"") | V50: =IF(U50="","",IF(U50<AsOf,1,IF(U50<=AsOf+AlertDays,2,IF(U50<=AsOf+2*AlertDays,3,"")))) | W50: =IF(V50="","",IF(O50="OVERDUE","Overdue payment: ","Payment due: ")&B50&" — "&C50&" ("&CurSym&" "&FIXED(S50,0)&")") | Z50: =IF(ProjStart="","",DATE(YEAR(ProjStart),MONTH(ProjStart)+9,1)) | AA50: =IF(Z50="","",SUMIFS($N$6:$N$205,$M$6:$M$205,">="&Z50,$M$6:$M$205,"<"&DATE(YEAR(Z50),MONTH(Z50)+1,1))) | AB50: =IF(Z50="","",SUMIFS($S$6:$S$205,$I$6:$I$205,">="&Z50,$I$6:$I$205,"<"&DATE(YEAR(Z50),MONTH(Z50)+1,1))) | AC50: =IF(Z50="","",AA50+AB50) | AD50: =IF(Z50="","",SUM($AC$41:AC50))
H51: =IF(B51="","",IF(G51<>"",G51,IF(F51<>"",F51*IFERROR(INDEX('Contractors'!$I$6:$I$35,MATCH(B51,'Contractors'!$B$6:$B$35,0)),0),""))) | O51: =IF(B51="","",IF(M51<>"","Paid",IF(AND(I51<>"",I51<AsOf),"OVERDUE",IF(OR(K51<>"",L51<>""),"Invoiced","Scheduled")))) | P51: =IF(B51="","",IF(E51<>"",E51,IFERROR(INDEX('Contractors'!$D$6:$D$35,MATCH(B51,'Contractors'!$B$6:$B$35,0)),""))) | Q51: =IF(B51="","",IF(D51<>"",D51,IFERROR(INDEX('Contractors'!$E$6:$E$35,MATCH(B51,'Contractors'!$B$6:$B$35,0)),""))) | R51: =IF(O51="","",IF(O51="OVERDUE",2,IF(O51="Paid",0,IF(AND(I51<>"",I51<=AsOf+AlertDays),1,0)))) | S51: =IF(AND(B51<>"",M51="",I51<>""),IF(L51<>"",L51,IF(H51="",0,H51)),0) | T51: =IF(AND(B51<>"",M51="",I51<>""),1/I51,0) | U51: =IF(AND(B51<>"",M51="",I51<>""),I51,"") | V51: =IF(U51="","",IF(U51<AsOf,1,IF(U51<=AsOf+AlertDays,2,IF(U51<=AsOf+2*AlertDays,3,"")))) | W51: =IF(V51="","",IF(O51="OVERDUE","Overdue payment: ","Payment due: ")&B51&" — "&C51&" ("&CurSym&" "&FIXED(S51,0)&")") | Z51: =IF(ProjStart="","",DATE(YEAR(ProjStart),MONTH(ProjStart)+10,1)) | AA51: =IF(Z51="","",SUMIFS($N$6:$N$205,$M$6:$M$205,">="&Z51,$M$6:$M$205,"<"&DATE(YEAR(Z51),MONTH(Z51)+1,1))) | AB51: =IF(Z51="","",SUMIFS($S$6:$S$205,$I$6:$I$205,">="&Z51,$I$6:$I$205,"<"&DATE(YEAR(Z51),MONTH(Z51)+1,1))) | AC51: =IF(Z51="","",AA51+AB51) | AD51: =IF(Z51="","",SUM($AC$41:AC51))
H52: =IF(B52="","",IF(G52<>"",G52,IF(F52<>"",F52*IFERROR(INDEX('Contractors'!$I$6:$I$35,MATCH(B52,'Contractors'!$B$6:$B$35,0)),0),""))) | O52: =IF(B52="","",IF(M52<>"","Paid",IF(AND(I52<>"",I52<AsOf),"OVERDUE",IF(OR(K52<>"",L52<>""),"Invoiced","Scheduled")))) | P52: =IF(B52="","",IF(E52<>"",E52,IFERROR(INDEX('Contractors'!$D$6:$D$35,MATCH(B52,'Contractors'!$B$6:$B$35,0)),""))) | Q52: =IF(B52="","",IF(D52<>"",D52,IFERROR(INDEX('Contractors'!$E$6:$E$35,MATCH(B52,'Contractors'!$B$6:$B$35,0)),""))) | R52: =IF(O52="","",IF(O52="OVERDUE",2,IF(O52="Paid",0,IF(AND(I52<>"",I52<=AsOf+AlertDays),1,0)))) | S52: =IF(AND(B52<>"",M52="",I52<>""),IF(L52<>"",L52,IF(H52="",0,H52)),0) | T52: =IF(AND(B52<>"",M52="",I52<>""),1/I52,0) | U52: =IF(AND(B52<>"",M52="",I52<>""),I52,"") | V52: =IF(U52="","",IF(U52<AsOf,1,IF(U52<=AsOf+AlertDays,2,IF(U52<=AsOf+2*AlertDays,3,"")))) | W52: =IF(V52="","",IF(O52="OVERDUE","Overdue payment: ","Payment due: ")&B52&" — "&C52&" ("&CurSym&" "&FIXED(S52,0)&")") | Z52: =IF(ProjStart="","",DATE(YEAR(ProjStart),MONTH(ProjStart)+11,1)) | AA52: =IF(Z52="","",SUMIFS($N$6:$N$205,$M$6:$M$205,">="&Z52,$M$6:$M$205,"<"&DATE(YEAR(Z52),MONTH(Z52)+1,1))) | AB52: =IF(Z52="","",SUMIFS($S$6:$S$205,$I$6:$I$205,">="&Z52,$I$6:$I$205,"<"&DATE(YEAR(Z52),MONTH(Z52)+1,1))) | AC52: =IF(Z52="","",AA52+AB52) | AD52: =IF(Z52="","",SUM($AC$41:AC52))
H53: =IF(B53="","",IF(G53<>"",G53,IF(F53<>"",F53*IFERROR(INDEX('Contractors'!$I$6:$I$35,MATCH(B53,'Contractors'!$B$6:$B$35,0)),0),""))) | O53: =IF(B53="","",IF(M53<>"","Paid",IF(AND(I53<>"",I53<AsOf),"OVERDUE",IF(OR(K53<>"",L53<>""),"Invoiced","Scheduled")))) | P53: =IF(B53="","",IF(E53<>"",E53,IFERROR(INDEX('Contractors'!$D$6:$D$35,MATCH(B53,'Contractors'!$B$6:$B$35,0)),""))) | Q53: =IF(B53="","",IF(D53<>"",D53,IFERROR(INDEX('Contractors'!$E$6:$E$35,MATCH(B53,'Contractors'!$B$6:$B$35,0)),""))) | R53: =IF(O53="","",IF(O53="OVERDUE",2,IF(O53="Paid",0,IF(AND(I53<>"",I53<=AsOf+AlertDays),1,0)))) | S53: =IF(AND(B53<>"",M53="",I53<>""),IF(L53<>"",L53,IF(H53="",0,H53)),0) | T53: =IF(AND(B53<>"",M53="",I53<>""),1/I53,0) | U53: =IF(AND(B53<>"",M53="",I53<>""),I53,"") | V53: =IF(U53="","",IF(U53<AsOf,1,IF(U53<=AsOf+AlertDays,2,IF(U53<=AsOf+2*AlertDays,3,"")))) | W53: =IF(V53="","",IF(O53="OVERDUE","Overdue payment: ","Payment due: ")&B53&" — "&C53&" ("&CurSym&" "&FIXED(S53,0)&")")
H54: =IF(B54="","",IF(G54<>"",G54,IF(F54<>"",F54*IFERROR(INDEX('Contractors'!$I$6:$I$35,MATCH(B54,'Contractors'!$B$6:$B$35,0)),0),""))) | O54: =IF(B54="","",IF(M54<>"","Paid",IF(AND(I54<>"",I54<AsOf),"OVERDUE",IF(OR(K54<>"",L54<>""),"Invoiced","Scheduled")))) | P54: =IF(B54="","",IF(E54<>"",E54,IFERROR(INDEX('Contractors'!$D$6:$D$35,MATCH(B54,'Contractors'!$B$6:$B$35,0)),""))) | Q54: =IF(B54="","",IF(D54<>"",D54,IFERROR(INDEX('Contractors'!$E$6:$E$35,MATCH(B54,'Contractors'!$B$6:$B$35,0)),""))) | R54: =IF(O54="","",IF(O54="OVERDUE",2,IF(O54="Paid",0,IF(AND(I54<>"",I54<=AsOf+AlertDays),1,0)))) | S54: =IF(AND(B54<>"",M54="",I54<>""),IF(L54<>"",L54,IF(H54="",0,H54)),0) | T54: =IF(AND(B54<>"",M54="",I54<>""),1/I54,0) | U54: =IF(AND(B54<>"",M54="",I54<>""),I54,"") | V54: =IF(U54="","",IF(U54<AsOf,1,IF(U54<=AsOf+AlertDays,2,IF(U54<=AsOf+2*AlertDays,3,"")))) | W54: =IF(V54="","",IF(O54="OVERDUE","Overdue payment: ","Payment due: ")&B54&" — "&C54&" ("&CurSym&" "&FIXED(S54,0)&")")
H55: =IF(B55="","",IF(G55<>"",G55,IF(F55<>"",F55*IFERROR(INDEX('Contractors'!$I$6:$I$35,MATCH(B55,'Contractors'!$B$6:$B$35,0)),0),""))) | O55: =IF(B55="","",IF(M55<>"","Paid",IF(AND(I55<>"",I55<AsOf),"OVERDUE",IF(OR(K55<>"",L55<>""),"Invoiced","Scheduled")))) | P55: =IF(B55="","",IF(E55<>"",E55,IFERROR(INDEX('Contractors'!$D$6:$D$35,MATCH(B55,'Contractors'!$B$6:$B$35,0)),""))) | Q55: =IF(B55="","",IF(D55<>"",D55,IFERROR(INDEX('Contractors'!$E$6:$E$35,MATCH(B55,'Contractors'!$B$6:$B$35,0)),""))) | R55: =IF(O55="","",IF(O55="OVERDUE",2,IF(O55="Paid",0,IF(AND(I55<>"",I55<=AsOf+AlertDays),1,0)))) | S55: =IF(AND(B55<>"",M55="",I55<>""),IF(L55<>"",L55,IF(H55="",0,H55)),0) | T55: =IF(AND(B55<>"",M55="",I55<>""),1/I55,0) | U55: =IF(AND(B55<>"",M55="",I55<>""),I55,"") | V55: =IF(U55="","",IF(U55<AsOf,1,IF(U55<=AsOf+AlertDays,2,IF(U55<=AsOf+2*AlertDays,3,"")))) | W55: =IF(V55="","",IF(O55="OVERDUE","Overdue payment: ","Payment due: ")&B55&" — "&C55&" ("&CurSym&" "&FIXED(S55,0)&")")
H56: =IF(B56="","",IF(G56<>"",G56,IF(F56<>"",F56*IFERROR(INDEX('Contractors'!$I$6:$I$35,MATCH(B56,'Contractors'!$B$6:$B$35,0)),0),""))) | O56: =IF(B56="","",IF(M56<>"","Paid",IF(AND(I56<>"",I56<AsOf),"OVERDUE",IF(OR(K56<>"",L56<>""),"Invoiced","Scheduled")))) | P56: =IF(B56="","",IF(E56<>"",E56,IFERROR(INDEX('Contractors'!$D$6:$D$35,MATCH(B56,'Contractors'!$B$6:$B$35,0)),""))) | Q56: =IF(B56="","",IF(D56<>"",D56,IFERROR(INDEX('Contractors'!$E$6:$E$35,MATCH(B56,'Contractors'!$B$6:$B$35,0)),""))) | R56: =IF(O56="","",IF(O56="OVERDUE",2,IF(O56="Paid",0,IF(AND(I56<>"",I56<=AsOf+AlertDays),1,0)))) | S56: =IF(AND(B56<>"",M56="",I56<>""),IF(L56<>"",L56,IF(H56="",0,H56)),0) | T56: =IF(AND(B56<>"",M56="",I56<>""),1/I56,0) | U56: =IF(AND(B56<>"",M56="",I56<>""),I56,"") | V56: =IF(U56="","",IF(U56<AsOf,1,IF(U56<=AsOf+AlertDays,2,IF(U56<=AsOf+2*AlertDays,3,"")))) | W56: =IF(V56="","",IF(O56="OVERDUE","Overdue payment: ","Payment due: ")&B56&" — "&C56&" ("&CurSym&" "&FIXED(S56,0)&")")
H57: =IF(B57="","",IF(G57<>"",G57,IF(F57<>"",F57*IFERROR(INDEX('Contractors'!$I$6:$I$35,MATCH(B57,'Contractors'!$B$6:$B$35,0)),0),""))) | O57: =IF(B57="","",IF(M57<>"","Paid",IF(AND(I57<>"",I57<AsOf),"OVERDUE",IF(OR(K57<>"",L57<>""),"Invoiced","Scheduled")))) | P57: =IF(B57="","",IF(E57<>"",E57,IFERROR(INDEX('Contractors'!$D$6:$D$35,MATCH(B57,'Contractors'!$B$6:$B$35,0)),""))) | Q57: =IF(B57="","",IF(D57<>"",D57,IFERROR(INDEX('Contractors'!$E$6:$E$35,MATCH(B57,'Contractors'!$B$6:$B$35,0)),""))) | R57: =IF(O57="","",IF(O57="OVERDUE",2,IF(O57="Paid",0,IF(AND(I57<>"",I57<=AsOf+AlertDays),1,0)))) | S57: =IF(AND(B57<>"",M57="",I57<>""),IF(L57<>"",L57,IF(H57="",0,H57)),0) | T57: =IF(AND(B57<>"",M57="",I57<>""),1/I57,0) | U57: =IF(AND(B57<>"",M57="",I57<>""),I57,"") | V57: =IF(U57="","",IF(U57<AsOf,1,IF(U57<=AsOf+AlertDays,2,IF(U57<=AsOf+2*AlertDays,3,"")))) | W57: =IF(V57="","",IF(O57="OVERDUE","Overdue payment: ","Payment due: ")&B57&" — "&C57&" ("&CurSym&" "&FIXED(S57,0)&")")
H58: =IF(B58="","",IF(G58<>"",G58,IF(F58<>"",F58*IFERROR(INDEX('Contractors'!$I$6:$I$35,MATCH(B58,'Contractors'!$B$6:$B$35,0)),0),""))) | O58: =IF(B58="","",IF(M58<>"","Paid",IF(AND(I58<>"",I58<AsOf),"OVERDUE",IF(OR(K58<>"",L58<>""),"Invoiced","Scheduled")))) | P58: =IF(B58="","",IF(E58<>"",E58,IFERROR(INDEX('Contractors'!$D$6:$D$35,MATCH(B58,'Contractors'!$B$6:$B$35,0)),""))) | Q58: =IF(B58="","",IF(D58<>"",D58,IFERROR(INDEX('Contractors'!$E$6:$E$35,MATCH(B58,'Contractors'!$B$6:$B$35,0)),""))) | R58: =IF(O58="","",IF(O58="OVERDUE",2,IF(O58="Paid",0,IF(AND(I58<>"",I58<=AsOf+AlertDays),1,0)))) | S58: =IF(AND(B58<>"",M58="",I58<>""),IF(L58<>"",L58,IF(H58="",0,H58)),0) | T58: =IF(AND(B58<>"",M58="",I58<>""),1/I58,0) | U58: =IF(AND(B58<>"",M58="",I58<>""),I58,"") | V58: =IF(U58="","",IF(U58<AsOf,1,IF(U58<=AsOf+AlertDays,2,IF(U58<=AsOf+2*AlertDays,3,"")))) | W58: =IF(V58="","",IF(O58="OVERDUE","Overdue payment: ","Payment due: ")&B58&" — "&C58&" ("&CurSym&" "&FIXED(S58,0)&")")
H59: =IF(B59="","",IF(G59<>"",G59,IF(F59<>"",F59*IFERROR(INDEX('Contractors'!$I$6:$I$35,MATCH(B59,'Contractors'!$B$6:$B$35,0)),0),""))) | O59: =IF(B59="","",IF(M59<>"","Paid",IF(AND(I59<>"",I59<AsOf),"OVERDUE",IF(OR(K59<>"",L59<>""),"Invoiced","Scheduled")))) | P59: =IF(B59="","",IF(E59<>"",E59,IFERROR(INDEX('Contractors'!$D$6:$D$35,MATCH(B59,'Contractors'!$B$6:$B$35,0)),""))) | Q59: =IF(B59="","",IF(D59<>"",D59,IFERROR(INDEX('Contractors'!$E$6:$E$35,MATCH(B59,'Contractors'!$B$6:$B$35,0)),""))) | R59: =IF(O59="","",IF(O59="OVERDUE",2,IF(O59="Paid",0,IF(AND(I59<>"",I59<=AsOf+AlertDays),1,0)))) | S59: =IF(AND(B59<>"",M59="",I59<>""),IF(L59<>"",L59,IF(H59="",0,H59)),0) | T59: =IF(AND(B59<>"",M59="",I59<>""),1/I59,0) | U59: =IF(AND(B59<>"",M59="",I59<>""),I59,"") | V59: =IF(U59="","",IF(U59<AsOf,1,IF(U59<=AsOf+AlertDays,2,IF(U59<=AsOf+2*AlertDays,3,"")))) | W59: =IF(V59="","",IF(O59="OVERDUE","Overdue payment: ","Payment due: ")&B59&" — "&C59&" ("&CurSym&" "&FIXED(S59,0)&")")
H60: =IF(B60="","",IF(G60<>"",G60,IF(F60<>"",F60*IFERROR(INDEX('Contractors'!$I$6:$I$35,MATCH(B60,'Contractors'!$B$6:$B$35,0)),0),""))) | O60: =IF(B60="","",IF(M60<>"","Paid",IF(AND(I60<>"",I60<AsOf),"OVERDUE",IF(OR(K60<>"",L60<>""),"Invoiced","Scheduled")))) | P60: =IF(B60="","",IF(E60<>"",E60,IFERROR(INDEX('Contractors'!$D$6:$D$35,MATCH(B60,'Contractors'!$B$6:$B$35,0)),""))) | Q60: =IF(B60="","",IF(D60<>"",D60,IFERROR(INDEX('Contractors'!$E$6:$E$35,MATCH(B60,'Contractors'!$B$6:$B$35,0)),""))) | R60: =IF(O60="","",IF(O60="OVERDUE",2,IF(O60="Paid",0,IF(AND(I60<>"",I60<=AsOf+AlertDays),1,0)))) | S60: =IF(AND(B60<>"",M60="",I60<>""),IF(L60<>"",L60,IF(H60="",0,H60)),0) | T60: =IF(AND(B60<>"",M60="",I60<>""),1/I60,0) | U60: =IF(AND(B60<>"",M60="",I60<>""),I60,"") | V60: =IF(U60="","",IF(U60<AsOf,1,IF(U60<=AsOf+AlertDays,2,IF(U60<=AsOf+2*AlertDays,3,"")))) | W60: =IF(V60="","",IF(O60="OVERDUE","Overdue payment: ","Payment due: ")&B60&" — "&C60&" ("&CurSym&" "&FIXED(S60,0)&")")
H61: =IF(B61="","",IF(G61<>"",G61,IF(F61<>"",F61*IFERROR(INDEX('Contractors'!$I$6:$I$35,MATCH(B61,'Contractors'!$B$6:$B$35,0)),0),""))) | O61: =IF(B61="","",IF(M61<>"","Paid",IF(AND(I61<>"",I61<AsOf),"OVERDUE",IF(OR(K61<>"",L61<>""),"Invoiced","Scheduled")))) | P61: =IF(B61="","",IF(E61<>"",E61,IFERROR(INDEX('Contractors'!$D$6:$D$35,MATCH(B61,'Contractors'!$B$6:$B$35,0)),""))) | Q61: =IF(B61="","",IF(D61<>"",D61,IFERROR(INDEX('Contractors'!$E$6:$E$35,MATCH(B61,'Contractors'!$B$6:$B$35,0)),""))) | R61: =IF(O61="","",IF(O61="OVERDUE",2,IF(O61="Paid",0,IF(AND(I61<>"",I61<=AsOf+AlertDays),1,0)))) | S61: =IF(AND(B61<>"",M61="",I61<>""),IF(L61<>"",L61,IF(H61="",0,H61)),0) | T61: =IF(AND(B61<>"",M61="",I61<>""),1/I61,0) | U61: =IF(AND(B61<>"",M61="",I61<>""),I61,"") | V61: =IF(U61="","",IF(U61<AsOf,1,IF(U61<=AsOf+AlertDays,2,IF(U61<=AsOf+2*AlertDays,3,"")))) | W61: =IF(V61="","",IF(O61="OVERDUE","Overdue payment: ","Payment due: ")&B61&" — "&C61&" ("&CurSym&" "&FIXED(S61,0)&")")
H62: =IF(B62="","",IF(G62<>"",G62,IF(F62<>"",F62*IFERROR(INDEX('Contractors'!$I$6:$I$35,MATCH(B62,'Contractors'!$B$6:$B$35,0)),0),""))) | O62: =IF(B62="","",IF(M62<>"","Paid",IF(AND(I62<>"",I62<AsOf),"OVERDUE",IF(OR(K62<>"",L62<>""),"Invoiced","Scheduled")))) | P62: =IF(B62="","",IF(E62<>"",E62,IFERROR(INDEX('Contractors'!$D$6:$D$35,MATCH(B62,'Contractors'!$B$6:$B$35,0)),""))) | Q62: =IF(B62="","",IF(D62<>"",D62,IFERROR(INDEX('Contractors'!$E$6:$E$35,MATCH(B62,'Contractors'!$B$6:$B$35,0)),""))) | R62: =IF(O62="","",IF(O62="OVERDUE",2,IF(O62="Paid",0,IF(AND(I62<>"",I62<=AsOf+AlertDays),1,0)))) | S62: =IF(AND(B62<>"",M62="",I62<>""),IF(L62<>"",L62,IF(H62="",0,H62)),0) | T62: =IF(AND(B62<>"",M62="",I62<>""),1/I62,0) | U62: =IF(AND(B62<>"",M62="",I62<>""),I62,"") | V62: =IF(U62="","",IF(U62<AsOf,1,IF(U62<=AsOf+AlertDays,2,IF(U62<=AsOf+2*AlertDays,3,"")))) | W62: =IF(V62="","",IF(O62="OVERDUE","Overdue payment: ","Payment due: ")&B62&" — "&C62&" ("&CurSym&" "&FIXED(S62,0)&")")
H63: =IF(B63="","",IF(G63<>"",G63,IF(F63<>"",F63*IFERROR(INDEX('Contractors'!$I$6:$I$35,MATCH(B63,'Contractors'!$B$6:$B$35,0)),0),""))) | O63: =IF(B63="","",IF(M63<>"","Paid",IF(AND(I63<>"",I63<AsOf),"OVERDUE",IF(OR(K63<>"",L63<>""),"Invoiced","Scheduled")))) | P63: =IF(B63="","",IF(E63<>"",E63,IFERROR(INDEX('Contractors'!$D$6:$D$35,MATCH(B63,'Contractors'!$B$6:$B$35,0)),""))) | Q63: =IF(B63="","",IF(D63<>"",D63,IFERROR(INDEX('Contractors'!$E$6:$E$35,MATCH(B63,'Contractors'!$B$6:$B$35,0)),""))) | R63: =IF(O63="","",IF(O63="OVERDUE",2,IF(O63="Paid",0,IF(AND(I63<>"",I63<=AsOf+AlertDays),1,0)))) | S63: =IF(AND(B63<>"",M63="",I63<>""),IF(L63<>"",L63,IF(H63="",0,H63)),0) | T63: =IF(AND(B63<>"",M63="",I63<>""),1/I63,0) | U63: =IF(AND(B63<>"",M63="",I63<>""),I63,"") | V63: =IF(U63="","",IF(U63<AsOf,1,IF(U63<=AsOf+AlertDays,2,IF(U63<=AsOf+2*AlertDays,3,"")))) | W63: =IF(V63="","",IF(O63="OVERDUE","Overdue payment: ","Payment due: ")&B63&" — "&C63&" ("&CurSym&" "&FIXED(S63,0)&")")
H64: =IF(B64="","",IF(G64<>"",G64,IF(F64<>"",F64*IFERROR(INDEX('Contractors'!$I$6:$I$35,MATCH(B64,'Contractors'!$B$6:$B$35,0)),0),""))) | O64: =IF(B64="","",IF(M64<>"","Paid",IF(AND(I64<>"",I64<AsOf),"OVERDUE",IF(OR(K64<>"",L64<>""),"Invoiced","Scheduled")))) | P64: =IF(B64="","",IF(E64<>"",E64,IFERROR(INDEX('Contractors'!$D$6:$D$35,MATCH(B64,'Contractors'!$B$6:$B$35,0)),""))) | Q64: =IF(B64="","",IF(D64<>"",D64,IFERROR(INDEX('Contractors'!$E$6:$E$35,MATCH(B64,'Contractors'!$B$6:$B$35,0)),""))) | R64: =IF(O64="","",IF(O64="OVERDUE",2,IF(O64="Paid",0,IF(AND(I64<>"",I64<=AsOf+AlertDays),1,0)))) | S64: =IF(AND(B64<>"",M64="",I64<>""),IF(L64<>"",L64,IF(H64="",0,H64)),0) | T64: =IF(AND(B64<>"",M64="",I64<>""),1/I64,0) | U64: =IF(AND(B64<>"",M64="",I64<>""),I64,"") | V64: =IF(U64="","",IF(U64<AsOf,1,IF(U64<=AsOf+AlertDays,2,IF(U64<=AsOf+2*AlertDays,3,"")))) | W64: =IF(V64="","",IF(O64="OVERDUE","Overdue payment: ","Payment due: ")&B64&" — "&C64&" ("&CurSym&" "&FIXED(S64,0)&")")
... H205: =IF(B205="","",IF(G205<>"",G205,IF(F205<>"",F205*IFERROR(INDEX('Contractors'!$I$6:$I$35,MATCH(B205,'Contractors'!$B$6:$B$35,0)),0),""))) | O205: =IF(B205="","",IF(M205<>"","Paid",IF(AND(I205<>"",I205<AsOf),"OVERDUE",IF(OR(K205<>"",L205<>""),"Invoiced","Scheduled")))) | P205: =IF(B205="","",IF(E205<>"",E205,IFERROR(INDEX('Contractors'!$D$6:$D$35,MATCH(B205,'Contractors'!$B$6:$B$35,0)),""))) | Q205: =IF(B205="","",IF(D205<>"",D205,IFERROR(INDEX('Contractors'!$E$6:$E$35,MATCH(B205,'Contractors'!$B$6:$B$35,0)),""))) | R205: =IF(O205="","",IF(O205="OVERDUE",2,IF(O205="Paid",0,IF(AND(I205<>"",I205<=AsOf+AlertDays),1,0)))) | S205: =IF(AND(B205<>"",M205="",I205<>""),IF(L205<>"",L205,IF(H205="",0,H205)),0) | T205: =IF(AND(B205<>"",M205="",I205<>""),1/I205,0) | U205: =IF(AND(B205<>"",M205="",I205<>""),I205,"") | V205: =IF(U205="","",IF(U205<AsOf,1,IF(U205<=AsOf+AlertDays,2,IF(U205<=AsOf+2*AlertDays,3,"")))) | W205: =IF(V205="","",IF(O205="OVERDUE","Overdue payment: ","Payment due: ")&B205&" — "&C205&" ("&CurSym&" "&FIXED(S205,0)&")")

Sheet Change Orders
B1: 🔁 Change Orders
B2: What this tab does: logs every change to the plan and previews its effect on budget, contingency and move-in date BEFORE you approve it.
B3: © 2026 Hang Nguyen — Renovation OS. Licensed to the original purchaser for personal use only. Do not share, copy, resell or redistribute.
B4: ⚠️ Never approve a change without checking this preview → the grey columns show your forecast, contingency and move-in date IF you approve.
B6: CO # | C6: Date requested | D6: Requested by | E6: Contractor | F6: Budget category | G6: Room | H6: What changes | I6: Reason | J6: ="Extra cost ("&CurSym&")" | K6: Extra days | L6: Status | M6: Decision date | N6: ="Forecast if approved ("&CurSym&")" | O6: ="Contingency left if approved ("&CurSym&")" | P6: Move-in if approved | Q6: vs working budget | R6: lvl | S6: due | T6: pri | U6: text
B7: CO-1 | C7: 46144 | D7: Contractor | E7: Solid Structures Ltd | F7: Structural | G7: Living room | H7: Heavier steel beam required by structural engineer | I7: Unforeseen condition | J7: 1200 | K7: 2 | L7: Approved | M7: 46145 | N7: =IF(AND(H7="",J7=""),"",ForecastTotal+IF(L7="Approved",0,IF(J7="",0,J7))) | O7: =IF(N7="","",ContAmt-MAX(0,N7-WorkBudget)) | P7: =IF(OR(N7="",ForecastEnd=""),"",ForecastEnd+IF(L7="Approved",0,IF(K7="",0,K7))) | Q7: =IF(OR(N7="",WorkBudget=0),"",N7/WorkBudget-1) | R7: =IF(N7="","",IF(N7<=WorkBudget,0,IF(N7<=TotalBudget,1,2))) | S7: =IF(AND(OR(H7<>"",J7<>""),OR(L7="Pending",L7=""),C7<>""),C7+3,"") | T7: =IF(S7="","",IF(AsOf>S7,1,2)) | U7: =IF(T7="","","Decide on change order "&B7&": "&H7&" (+"&CurSym&" "&FIXED(IF(J7="",0,J7),0)&")")
B8: CO-2 | C8: 46162 | D8: Owner | E8: Nordic Kitchens | F8: Kitchen | G8: Kitchen | H8: Add pantry cabinet + soft-close upgrade | I8: Client choice | J8: 900 | K8: 0 | L8: Approved | M8: 46164 | N8: =IF(AND(H8="",J8=""),"",ForecastTotal+IF(L8="Approved",0,IF(J8="",0,J8))) | O8: =IF(N8="","",ContAmt-MAX(0,N8-WorkBudget)) | P8: =IF(OR(N8="",ForecastEnd=""),"",ForecastEnd+IF(L8="Approved",0,IF(K8="",0,K8))) | Q8: =IF(OR(N8="",WorkBudget=0),"",N8/WorkBudget-1) | R8: =IF(N8="","",IF(N8<=WorkBudget,0,IF(N8<=TotalBudget,1,2))) | S8: =IF(AND(OR(H8<>"",J8<>""),OR(L8="Pending",L8=""),C8<>""),C8+3,"") | T8: =IF(S8="","",IF(AsOf>S8,1,2)) | U8: =IF(T8="","","Decide on change order "&B8&": "&H8&" (+"&CurSym&" "&FIXED(IF(J8="",0,J8),0)&")")
B9: CO-3 | C9: 46167 | D9: Contractor | E9: ClearView Windows | F9: Windows & doors | G9: Living room | H9: Upgrade sliding door to triple glazing | I9: Client choice | J9: 2100 | K9: 5 | L9: Rejected | M9: 46170 | N9: =IF(AND(H9="",J9=""),"",ForecastTotal+IF(L9="Approved",0,IF(J9="",0,J9))) | O9: =IF(N9="","",ContAmt-MAX(0,N9-WorkBudget)) | P9: =IF(OR(N9="",ForecastEnd=""),"",ForecastEnd+IF(L9="Approved",0,IF(K9="",0,K9))) | Q9: =IF(OR(N9="",WorkBudget=0),"",N9/WorkBudget-1) | R9: =IF(N9="","",IF(N9<=WorkBudget,0,IF(N9<=TotalBudget,1,2))) | S9: =IF(AND(OR(H9<>"",J9<>""),OR(L9="Pending",L9=""),C9<>""),C9+3,"") | T9: =IF(S9="","",IF(AsOf>S9,1,2)) | U9: =IF(T9="","","Decide on change order "&B9&": "&H9&" (+"&CurSym&" "&FIXED(IF(J9="",0,J9),0)&")")
B10: CO-4 | C10: 46174 | D10: Owner | E10: Aqua Bath Studio | F10: Bathrooms | G10: Bathroom 1 | H10: Electric underfloor heating in bathroom 1 | I10: Client choice | J10: 1650 | K10: 1 | L10: Approved | M10: 46176 | N10: =IF(AND(H10="",J10=""),"",ForecastTotal+IF(L10="Approved",0,IF(J10="",0,J10))) | O10: =IF(N10="","",ContAmt-MAX(0,N10-WorkBudget)) | P10: =IF(OR(N10="",ForecastEnd=""),"",ForecastEnd+IF(L10="Approved",0,IF(K10="",0,K10))) | Q10: =IF(OR(N10="",WorkBudget=0),"",N10/WorkBudget-1) | R10: =IF(N10="","",IF(N10<=WorkBudget,0,IF(N10<=TotalBudget,1,2))) | S10: =IF(AND(OR(H10<>"",J10<>""),OR(L10="Pending",L10=""),C10<>""),C10+3,"") | T10: =IF(S10="","",IF(AsOf>S10,1,2)) | U10: =IF(T10="","","Decide on change order "&B10&": "&H10&" (+"&CurSym&" "&FIXED(IF(J10="",0,J10),0)&")")
B11: CO-5 | C11: 46182 | D11: Contractor | E11: Bright Spark Electric | F11: Electrical | G11: Whole house | H11: EV charger + 6 extra circuits | I11: Client choice | J11: 3400 | K11: 5 | L11: Pending | N11: =IF(AND(H11="",J11=""),"",ForecastTotal+IF(L11="Approved",0,IF(J11="",0,J11))) | O11: =IF(N11="","",ContAmt-MAX(0,N11-WorkBudget)) | P11: =IF(OR(N11="",ForecastEnd=""),"",ForecastEnd+IF(L11="Approved",0,IF(K11="",0,K11))) | Q11: =IF(OR(N11="",WorkBudget=0),"",N11/WorkBudget-1) | R11: =IF(N11="","",IF(N11<=WorkBudget,0,IF(N11<=TotalBudget,1,2))) | S11: =IF(AND(OR(H11<>"",J11<>""),OR(L11="Pending",L11=""),C11<>""),C11+3,"") | T11: =IF(S11="","",IF(AsOf>S11,1,2)) | U11: =IF(T11="","","Decide on change order "&B11&": "&H11&" (+"&CurSym&" "&FIXED(IF(J11="",0,J11),0)&")")
N12: =IF(AND(H12="",J12=""),"",ForecastTotal+IF(L12="Approved",0,IF(J12="",0,J12))) | O12: =IF(N12="","",ContAmt-MAX(0,N12-WorkBudget)) | P12: =IF(OR(N12="",ForecastEnd=""),"",ForecastEnd+IF(L12="Approved",0,IF(K12="",0,K12))) | Q12: =IF(OR(N12="",WorkBudget=0),"",N12/WorkBudget-1) | R12: =IF(N12="","",IF(N12<=WorkBudget,0,IF(N12<=TotalBudget,1,2))) | S12: =IF(AND(OR(H12<>"",J12<>""),OR(L12="Pending",L12=""),C12<>""),C12+3,"") | T12: =IF(S12="","",IF(AsOf>S12,1,2)) | U12: =IF(T12="","","Decide on change order "&B12&": "&H12&" (+"&CurSym&" "&FIXED(IF(J12="",0,J12),0)&")")
N13: =IF(AND(H13="",J13=""),"",ForecastTotal+IF(L13="Approved",0,IF(J13="",0,J13))) | O13: =IF(N13="","",ContAmt-MAX(0,N13-WorkBudget)) | P13: =IF(OR(N13="",ForecastEnd=""),"",ForecastEnd+IF(L13="Approved",0,IF(K13="",0,K13))) | Q13: =IF(OR(N13="",WorkBudget=0),"",N13/WorkBudget-1) | R13: =IF(N13="","",IF(N13<=WorkBudget,0,IF(N13<=TotalBudget,1,2))) | S13: =IF(AND(OR(H13<>"",J13<>""),OR(L13="Pending",L13=""),C13<>""),C13+3,"") | T13: =IF(S13="","",IF(AsOf>S13,1,2)) | U13: =IF(T13="","","Decide on change order "&B13&": "&H13&" (+"&CurSym&" "&FIXED(IF(J13="",0,J13),0)&")")
N14: =IF(AND(H14="",J14=""),"",ForecastTotal+IF(L14="Approved",0,IF(J14="",0,J14))) | O14: =IF(N14="","",ContAmt-MAX(0,N14-WorkBudget)) | P14: =IF(OR(N14="",ForecastEnd=""),"",ForecastEnd+IF(L14="Approved",0,IF(K14="",0,K14))) | Q14: =IF(OR(N14="",WorkBudget=0),"",N14/WorkBudget-1) | R14: =IF(N14="","",IF(N14<=WorkBudget,0,IF(N14<=TotalBudget,1,2))) | S14: =IF(AND(OR(H14<>"",J14<>""),OR(L14="Pending",L14=""),C14<>""),C14+3,"") | T14: =IF(S14="","",IF(AsOf>S14,1,2)) | U14: =IF(T14="","","Decide on change order "&B14&": "&H14&" (+"&CurSym&" "&FIXED(IF(J14="",0,J14),0)&")")
N15: =IF(AND(H15="",J15=""),"",ForecastTotal+IF(L15="Approved",0,IF(J15="",0,J15))) | O15: =IF(N15="","",ContAmt-MAX(0,N15-WorkBudget)) | P15: =IF(OR(N15="",ForecastEnd=""),"",ForecastEnd+IF(L15="Approved",0,IF(K15="",0,K15))) | Q15: =IF(OR(N15="",WorkBudget=0),"",N15/WorkBudget-1) | R15: =IF(N15="","",IF(N15<=WorkBudget,0,IF(N15<=TotalBudget,1,2))) | S15: =IF(AND(OR(H15<>"",J15<>""),OR(L15="Pending",L15=""),C15<>""),C15+3,"") | T15: =IF(S15="","",IF(AsOf>S15,1,2)) | U15: =IF(T15="","","Decide on change order "&B15&": "&H15&" (+"&CurSym&" "&FIXED(IF(J15="",0,J15),0)&")")
N16: =IF(AND(H16="",J16=""),"",ForecastTotal+IF(L16="Approved",0,IF(J16="",0,J16))) | O16: =IF(N16="","",ContAmt-MAX(0,N16-WorkBudget)) | P16: =IF(OR(N16="",ForecastEnd=""),"",ForecastEnd+IF(L16="Approved",0,IF(K16="",0,K16))) | Q16: =IF(OR(N16="",WorkBudget=0),"",N16/WorkBudget-1) | R16: =IF(N16="","",IF(N16<=WorkBudget,0,IF(N16<=TotalBudget,1,2))) | S16: =IF(AND(OR(H16<>"",J16<>""),OR(L16="Pending",L16=""),C16<>""),C16+3,"") | T16: =IF(S16="","",IF(AsOf>S16,1,2)) | U16: =IF(T16="","","Decide on change order "&B16&": "&H16&" (+"&CurSym&" "&FIXED(IF(J16="",0,J16),0)&")")
N17: =IF(AND(H17="",J17=""),"",ForecastTotal+IF(L17="Approved",0,IF(J17="",0,J17))) | O17: =IF(N17="","",ContAmt-MAX(0,N17-WorkBudget)) | P17: =IF(OR(N17="",ForecastEnd=""),"",ForecastEnd+IF(L17="Approved",0,IF(K17="",0,K17))) | Q17: =IF(OR(N17="",WorkBudget=0),"",N17/WorkBudget-1) | R17: =IF(N17="","",IF(N17<=WorkBudget,0,IF(N17<=TotalBudget,1,2))) | S17: =IF(AND(OR(H17<>"",J17<>""),OR(L17="Pending",L17=""),C17<>""),C17+3,"") | T17: =IF(S17="","",IF(AsOf>S17,1,2)) | U17: =IF(T17="","","Decide on change order "&B17&": "&H17&" (+"&CurSym&" "&FIXED(IF(J17="",0,J17),0)&")")
N18: =IF(AND(H18="",J18=""),"",ForecastTotal+IF(L18="Approved",0,IF(J18="",0,J18))) | O18: =IF(N18="","",ContAmt-MAX(0,N18-WorkBudget)) | P18: =IF(OR(N18="",ForecastEnd=""),"",ForecastEnd+IF(L18="Approved",0,IF(K18="",0,K18))) | Q18: =IF(OR(N18="",WorkBudget=0),"",N18/WorkBudget-1) | R18: =IF(N18="","",IF(N18<=WorkBudget,0,IF(N18<=TotalBudget,1,2))) | S18: =IF(AND(OR(H18<>"",J18<>""),OR(L18="Pending",L18=""),C18<>""),C18+3,"") | T18: =IF(S18="","",IF(AsOf>S18,1,2)) | U18: =IF(T18="","","Decide on change order "&B18&": "&H18&" (+"&CurSym&" "&FIXED(IF(J18="",0,J18),0)&")")
N19: =IF(AND(H19="",J19=""),"",ForecastTotal+IF(L19="Approved",0,IF(J19="",0,J19))) | O19: =IF(N19="","",ContAmt-MAX(0,N19-WorkBudget)) | P19: =IF(OR(N19="",ForecastEnd=""),"",ForecastEnd+IF(L19="Approved",0,IF(K19="",0,K19))) | Q19: =IF(OR(N19="",WorkBudget=0),"",N19/WorkBudget-1) | R19: =IF(N19="","",IF(N19<=WorkBudget,0,IF(N19<=TotalBudget,1,2))) | S19: =IF(AND(OR(H19<>"",J19<>""),OR(L19="Pending",L19=""),C19<>""),C19+3,"") | T19: =IF(S19="","",IF(AsOf>S19,1,2)) | U19: =IF(T19="","","Decide on change order "&B19&": "&H19&" (+"&CurSym&" "&FIXED(IF(J19="",0,J19),0)&")")
N20: =IF(AND(H20="",J20=""),"",ForecastTotal+IF(L20="Approved",0,IF(J20="",0,J20))) | O20: =IF(N20="","",ContAmt-MAX(0,N20-WorkBudget)) | P20: =IF(OR(N20="",ForecastEnd=""),"",ForecastEnd+IF(L20="Approved",0,IF(K20="",0,K20))) | Q20: =IF(OR(N20="",WorkBudget=0),"",N20/WorkBudget-1) | R20: =IF(N20="","",IF(N20<=WorkBudget,0,IF(N20<=TotalBudget,1,2))) | S20: =IF(AND(OR(H20<>"",J20<>""),OR(L20="Pending",L20=""),C20<>""),C20+3,"") | T20: =IF(S20="","",IF(AsOf>S20,1,2)) | U20: =IF(T20="","","Decide on change order "&B20&": "&H20&" (+"&CurSym&" "&FIXED(IF(J20="",0,J20),0)&")")
N21: =IF(AND(H21="",J21=""),"",ForecastTotal+IF(L21="Approved",0,IF(J21="",0,J21))) | O21: =IF(N21="","",ContAmt-MAX(0,N21-WorkBudget)) | P21: =IF(OR(N21="",ForecastEnd=""),"",ForecastEnd+IF(L21="Approved",0,IF(K21="",0,K21))) | Q21: =IF(OR(N21="",WorkBudget=0),"",N21/WorkBudget-1) | R21: =IF(N21="","",IF(N21<=WorkBudget,0,IF(N21<=TotalBudget,1,2))) | S21: =IF(AND(OR(H21<>"",J21<>""),OR(L21="Pending",L21=""),C21<>""),C21+3,"") | T21: =IF(S21="","",IF(AsOf>S21,1,2)) | U21: =IF(T21="","","Decide on change order "&B21&": "&H21&" (+"&CurSym&" "&FIXED(IF(J21="",0,J21),0)&")")
N22: =IF(AND(H22="",J22=""),"",ForecastTotal+IF(L22="Approved",0,IF(J22="",0,J22))) | O22: =IF(N22="","",ContAmt-MAX(0,N22-WorkBudget)) | P22: =IF(OR(N22="",ForecastEnd=""),"",ForecastEnd+IF(L22="Approved",0,IF(K22="",0,K22))) | Q22: =IF(OR(N22="",WorkBudget=0),"",N22/WorkBudget-1) | R22: =IF(N22="","",IF(N22<=WorkBudget,0,IF(N22<=TotalBudget,1,2))) | S22: =IF(AND(OR(H22<>"",J22<>""),OR(L22="Pending",L22=""),C22<>""),C22+3,"") | T22: =IF(S22="","",IF(AsOf>S22,1,2)) | U22: =IF(T22="","","Decide on change order "&B22&": "&H22&" (+"&CurSym&" "&FIXED(IF(J22="",0,J22),0)&")")
N23: =IF(AND(H23="",J23=""),"",ForecastTotal+IF(L23="Approved",0,IF(J23="",0,J23))) | O23: =IF(N23="","",ContAmt-MAX(0,N23-WorkBudget)) | P23: =IF(OR(N23="",ForecastEnd=""),"",ForecastEnd+IF(L23="Approved",0,IF(K23="",0,K23))) | Q23: =IF(OR(N23="",WorkBudget=0),"",N23/WorkBudget-1) | R23: =IF(N23="","",IF(N23<=WorkBudget,0,IF(N23<=TotalBudget,1,2))) | S23: =IF(AND(OR(H23<>"",J23<>""),OR(L23="Pending",L23=""),C23<>""),C23+3,"") | T23: =IF(S23="","",IF(AsOf>S23,1,2)) | U23: =IF(T23="","","Decide on change order "&B23&": "&H23&" (+"&CurSym&" "&FIXED(IF(J23="",0,J23),0)&")")
... N106: =IF(AND(H106="",J106=""),"",ForecastTotal+IF(L106="Approved",0,IF(J106="",0,J106))) | O106: =IF(N106="","",ContAmt-MAX(0,N106-WorkBudget)) | P106: =IF(OR(N106="",ForecastEnd=""),"",ForecastEnd+IF(L106="Approved",0,IF(K106="",0,K106))) | Q106: =IF(OR(N106="",WorkBudget=0),"",N106/WorkBudget-1) | R106: =IF(N106="","",IF(N106<=WorkBudget,0,IF(N106<=TotalBudget,1,2))) | S106: =IF(AND(OR(H106<>"",J106<>""),OR(L106="Pending",L106=""),C106<>""),C106+3,"") | T106: =IF(S106="","",IF(AsOf>S106,1,2)) | U106: =IF(T106="","","Decide on change order "&B106&": "&H106&" (+"&CurSym&" "&FIXED(IF(J106="",0,J106),0)&")")

Sheet Timeline
B1: 📅 Timeline
B2: What this tab does: tasks with durations and dependencies → start/end dates, late warnings and a 52-week Gantt chart. Forecast finish feeds the Dashboard.
B3: © 2026 Hang Nguyen — Renovation OS. Licensed to the original purchaser for personal use only. Do not share, copy, resell or redistribute.
C4: Forecast finish | D4: =IF(COUNT(L7:L156)=0,"",MAX(L7:L156)) | E4: Target move-in | G4: =IF(TargetEnd="","",TargetEnd) | I4: =IF(OR(ForecastEnd="",TargetEnd=""),"",IF(ForecastEnd>TargetEnd,"🔴 "&(ForecastEnd-TargetEnd)&" days late",IF(ForecastEnd=TargetEnd,"🟢 on target","🟢 "&(TargetEnd-ForecastEnd)&" days early"))) | R4: =AsOf | X4: Gantt: teal = planned · grey = done · red = late · yellow column = this week
B6: ID | C6: Phase | D6: Task | E6: Room | F6: Contractor | G6: Duration (days) | H6: Predecessor ID | I6: Earliest start (optional) | J6: Start | K6: Delay (days) | L6: End | M6: Status | N6: Done date | O6: Affects N tasks | P6: Flag | Q6: code | R6: first | S6: okey | T6: due | U6: pri | V6: text | X6: =IF(ProjStart="","",ProjStart-IF(WeekStart="Sunday",WEEKDAY(ProjStart,1)-1,WEEKDAY(ProjStart,3))) | Y6: =IF(X6="","",X6+7) | Z6: =IF(Y6="","",Y6+7) | AA6: =IF(Z6="","",Z6+7) | AB6: =IF(AA6="","",AA6+7) | AC6: =IF(AB6="","",AB6+7) | AD6: =IF(AC6="","",AC6+7) | AE6: =IF(AD6="","",AD6+7) | AF6: =IF(AE6="","",AE6+7) | ... BW6: =IF(BV6="","",BV6+7)
B7: 1 | C7: Pre-construction | D7: Design & plans | E7: Whole house | F7: GreenPlan Architects | G7: 21 | J7: =IF(OR(D7="",ProjStart=""),"",MAX(ProjStart,IF(I7<>"",I7,0),IF(H7="",0,IFERROR(INDEX($L$6:L6,MATCH(H7,$B$6:B6,0))+1,0)))) | L7: =IF(J7="","",J7+MAX(1,G7)+IF(K7="",0,K7)-1) | M7: Done | N7: 46101 | O7: =IF(D7="","",COUNTIF($H$7:$H$156,B7)) | P7: =IF(D7="","",IF(AND(H7<>"",H7>=B7),"⚠️ Predecessor must be above",IF(M7="Done","✓ Done",IF(Q7=3,"🔴 Late",IF(M7="In progress","In progress",""))))) | Q7: =IF(OR(D7="",L7=""),"",IF(M7="Done",2,IF(AsOf>L7,3,1))) | R7: =IF(OR(E7="",F7=""),0,IF(COUNTIFS($E$7:E7,E7,$F$7:F7,F7)=1,1,0)) | S7: =IF(R7=1,E7&"|"&SUMIFS($R$7:R7,$E$7:E7,E7),"") | T7: =IF(Q7="","",IF(Q7=3,L7,IF(OR(M7="Not started",M7=""),J7,""))) | U7: =IF(T7="","",IF(Q7=3,1,IF(T7="","",IF(T7<AsOf,1,IF(T7<=AsOf+AlertDays,2,IF(T7<=AsOf+2*AlertDays,3,"")))))) | V7: =IF(U7="","",IF(Q7=3,"Late task: "&D7,IF(T7<AsOf,"Should have started: ","Starts soon: ")&D7)&IF(F7="",""," — "&F7))
